Workbook

Sheet Instructions
A1: Purpose:
A2: To determine the benefits and total resources (benefits + earned income) available to clients at different earned income levels. To determine the change in benefits and total resources as clients move from one earned income level to another.
A4: ***IMPORTANT DISCLAIMER****
A5: This calculator has the following built in assumptions that may not be applicable for all family situations: ▪ The household has no more than 8 members ▪ There are no child(ren) only cases ▪ All children are blood related or adoptive siblings ▪ There are no step-parents in the household ▪ There are no minor parents ▪ The household is eligible for all selected benefits ▪ The household did not have any countable resources ▪ There is no self-employment income ▪ The children are assumed to be eligible to be claimed as dependents for the household adult and will not be claimed as dependents on anyone else's tax return ▪ There are no child support payments ▪ Children do not have any income ▪ The household does not take the TANF child care/incapacitated adult deduction ▪ Childcare will be provided at a Level 1 Center-based program ▪ The family is not homeless ▪ All household members reside in the home ▪ The family does not live in a group home/institution ▪ There is no unreimbursed: 1)medical care for elderly or disabled individuals, 2) expenses allowing a disabled person to work that exceeds 3% of annual income ▪ Any adult receiving SSI/SSDI is not working ▪ There is no employer-provided health insurance ▪ The second lowest cost Silver plan (SLCSP) was selected on the CoverVA website with no cost-sharing ▪ The calculations for the housing choice voucher do not include a childcare deduction ▪ The rental unit size is based on 2 ppl/bedroom (adults and children separate) ▪ Initial housing choice voucher income limits are 50% of AMI, new income are not subjected to an income check ▪ Utilities are not inclded in the rent ▪ No adults are eligible for WIC-only children <5 years old-no pregnant women
A7: Instructions
A8: Hunter Sm
A10: Data Sources
A11: Child Care Subsidy rates sourced from: https://fusion.dss.virginia.gov/Portals/[ccecd]/T224%20Child%20Care%20Subsidy%20Program%20Manual_Effective%20October%201_2024.pdf?ver=2024-09-30-111401-117 Rates updated 7/1/2025 https://www.childcare.virginia.gov/home/showpublisheddocument/62604/638864381965000000
A12: Federal EITC Calculated using https://apps.irs.gov/app/eitc/results/, state EITC calculated using https://www.tax.virginia.gov/low-income-individuals-credit
A13: SLCSP sourced from https://enroll.marketplace.virginia.gov/hix/preeligibility#/
A14: Housing Choice Voucher rates sources from10/10/2024 https://www.huduser.gov/portal/datasets/il/il2024/2024summary.odn., https://www.huduser.gov/portal/datasets/fmr/fmrs/FY2024_code/select_Geography.odn, https://www.virginiahousing.com/partners/housing-choice-vouchers/payment-standards Income limits: https://www.huduser.gov/portal/datasets/il.html#data_2025 FY 2024 Fair Market Rent Documentation System: https://www.huduser.gov/portal/datasets/fmr/fmrs/FY2025_code/2025state_summary.odn HCV calculations sourced from https://www.hud.gov/sites/dfiles/PIH/documents/HCV_Guidebook_Calculating_Rent_and_HAP_Payments.pdf
A15: Medicaid income limits sourced from: https://fusion.dss.virginia.gov/Portals/%5Bbp%5D/Medicaid/Resources%20and%20Job%20Aids/01.20.24%20Income%20Limits.docx Medicaid benefit determined by averaging state and federal spending per Medicaid enrollee, sourced from Federa Reserve Bank of Atlanta at https://emar-data-tools.shinyapps.io/prd_dashboard/
... A29: SSI basic monthly payment : https://www.ssa.gov/pubs/EN-05-11002.pdf

Sheet Total income package
A1: Location Information
A2: Locality | B2: Select from drop-down menu
B3: Buckingham
A5: Benefits Information
A6: Select benefit programs
A8: TRUE
C9: At least one adult must have earned income to select EITC At least one tax filer must be between 25-64 years if claiming EITC credit AND have no qualifying children
A10: TRUE
A12: TRUE
C13: If housing choice voucher is selected-how many bedrooms is the unit? Select from drop down list | D13: 4 | E13: s
A14: TRUE
A16: TRUE
A18: TRUE
C19: If choosing TANF benefits-select only one TANF program (TANF or TANF/VIEW)
A20: TRUE
A22: FALSE
A24: TRUE
A26: Household Information
A27: Calculator valid for households up to 8 people
A30: Number of adults in household | B30: 3 | C30: Include adults and children receiving SSI/SSDI
A31: Number of children ( 18 years old or less) in household | B31: 2
A32: Total number of people in household (Calculated) | B32: =IF(B30+B31>8,"Only valid for up to 8 people",B30+B31) -> 5
A35: Age(s) of Household Members
A36: Age(s) of adult(s): | B36: Enter age (in years)
A37: Adult 1 | B37: 34 | C37: Is this adult a parent of any of the children listed below? Select yes or no. | E37: Yes
A38: Adult 2 | B38: 28 | C38: Is this adult a parent of any of the children listed below? Select yes or no. | E38: Yes
A39: Adult 3 | B39: 80 | C39: Is this adult a parent of any of the children listed below? Select yes or no. | E39: No
A40: Adult 4 | C40: Is this adult a parent of any of the children listed below? Select yes or no. | E40: No
A41: Adult 5 | C41: Is this adult a parent of any of the children listed below? Select yes or no.
A42: Adult 6 | C42: Is this adult a parent of any of the children listed below? Select yes or no.
A43: Adult 7 | C43: Is this adult a parent of any of the children listed below? Select yes or no.
A44: Adult 8 | C44: Is this adult a parent of any of the children listed below? Select yes or no.
A46: Age categories of children (The number of children listed here should match the number of children in the household above.) | B46: Select from drop-down menu | C46: For children: Select: "Infant" if child is 16 months or younger "Toddler" if child is 16-23 months "Two year old" if child is 24-36 months "Prechool" if child is 36 months to 5 years and not yet in kindergarten "School age" if child is eligible to attend public school but less than 13 years "13 years or older" if child is 13 years or older and capable of caring from themselves "13-18" years old if child is physically or mentally incapable of caring for themselves
A48: Child 1 | B48: School age
A49: Child 2 | B49: Infant
A50: Child 3
A51: Child 4
A52: Child 5
A53: Child 6
A54: Child 7
A57: Disability information
A58: Disability Status-Adult | C58: If Disabled: Adult
A59: Are any adults disabled? (Yes or No) (Select from drop down list) | B59: Yes | C59: How many disabled adults are the family head or spouse? | D59: 1 | E59: How many non-elderly (under 61 years) adults are disabled who are NOT the family head or spouse? | G59: How many are disabled AND elderly (62 years or older) | H59: 1
A61: Is there SSI income (Adult )? (Yes or No) | B61: Yes | C61: How many disabled adults receiving SSI are also a parent to the child(ren) listed above? | D61: 1 | E61: How many adults in the household receive SSI? | F61: 1 | G61: How much is the total adult SSI income? | H61: 200
A63: Disability Status-Child(ren)
A64: Are any children disabled? (Yes or No) | B64: Yes | C64: How many children are disabled? | D64: 1
A66: Is there SSI income (Child)? (Yes or No) | B66: Yes | C66: How many children receive SSI/SSDI? | D66: 1 | E66: How much is the total Child SSI/SSDI | F66: 50
A68: Housing information
A69: What are the qualified shelter expenses? | B69: 500 | C69: Rent, mortgage, loan payments, or other continuing charges that lead to ownership of a home, mobile home, or other type of shelter
A70: Is the Standard Utility Allowance being used or actual utility expenses? (Select from the drop down list) | B70: Actual monthly utility costs | C70: What are the monthly utility expenses? | D70: 700
A72: Tax filing status | B72: Married filing jointly | C72: Must be selected for EITC
A74: Will there be a change in income levels? (Yes or No)
A76: Income of adult(s) who answered "Yes" to being a parent to the children
A77: Current all adult MONTHLY earned income (round up to the closest dollar amount) | B77: 1423 | C77: Do not count the income of the elderly, disabled adult or spouse | D77: If you need a monthly income calculator click here
A78: NEW all adult MONTHLY earned income (round up to the closest dollar amount) | B78: 3000 | C78: Do not count the income of the elderly, disabled adult or spouse
A80: Is there Social Security Income? | B80: Yes | C80: What is the Social security income of adult(s) who answered "Yes" to being a parent to the children? | D80: 0
A82: Income of adult(s) who answered "No" to being a parent to the children
A83: Current all adult MONTHLY earned income (round up to the closest dollar amount) | C83: Do not count the income of the elderly, disabled adult or spouse | D83: If you need a monthly income calculator click here
A84: NEW all adult MONTHLY earned income (round up to the closest dollar amount) | C84: Do not count the income of the elderly, disabled adult or spouse
A86: Is there Social Security Income? | B86: No | C86: What is the Social security income of adult(s) who answered "No" to being a parent to the children? | D86: 0
A89: Household income | C89: Monthly Selected benefits | D89: Overall Resources Selected benefits + income | E89: Child care subsidy | F89: EITC + VA EITC (EITC/12) | G89: Health Insurance Marketplace Subsidies | H89: HCV Program | I89: Medicaid | J89: SNAP | K89: TANF | L89: TANF/VIEW | M89: WIC
A90: Total Household income | B90: =B77+B83 -> 1423 | C90: =SUM(E90:M90) -> 6921.189 | D90: =SUM(E90:M90)+B90 -> 8344.189 | E90: ='Child care subsidy'!S208 -> 1980 | F90: =EITC!E208/12 -> 654.58 | G90: ='Health insurance subsidy '!L220 -> 0 | H90: ='Housing Voucher'!Q209 -> 1026.099 | I90: =Medicaid!N212 -> 2188.75 | J90: =SNAP!V209 -> 1035 | K90: =MAX('TANF-VIEW'!L212,'TANF-VIEW'!T212) -> 0 | L90: ='TANF-VIEW'!T212 -> 0 | M90: =WIC!F211 -> 36.76 | N90: Current monthly income
A91: New total household income | B91: =B78+B84 -> 3000 | C91: =SUM(E91:M91) -> 5828.9625 | D91: =SUM(E91:M91)+B91 -> 8828.9625 | E91: ='Child care subsidy'!S210 -> 1980 | F91: =EITC!E210/12 -> 603.45355 | G91: ='Health insurance subsidy '!L222 -> 0 | H91: ='Housing Voucher'!Q211 -> 552.999 | I91: =Medicaid!N214 -> 2188.75 | J91: =SNAP!V211 -> 467 | K91: =MAX('TANF-VIEW'!L214,'TANF-VIEW'!T214) -> 0 | L91: ='TANF-VIEW'!T214 -> 0 | M91: =WIC!F213 -> 36.76 | N91: New monthly income
B92: Difference | C92: =C91-C90 -> -1092.2265 | D92: =D91-D90 -> 484.77355
B119: Starting income

Sheet Income conversions
A1: Convert hourly wage to monthly income
A2: Hourly wage | B2: 12
A3: How many hours (total) worked in a month | B3: 20
A5: Monthly earned income (gross) | B5: =B2*B3 -> 240
A6: Annual earned income (gross) | B6: =B5*12 -> 2880
A8: Convert annual income to monthly income
A9: Annual income (gross) | B9: 30000
A10: Monthly earned income (gross) | B10: =B9/12 -> 2500
A13: Return to Total Income tab

Sheet Use this for graphs
A1: Annual earned income | B1: Monthly earned income | C1: Annual Child Care Subsidy | D1: TANF | E1: Annual SNAP Benefit | F1: Annual WIC Benefit | G1: Housing Choice Voucher | H1: Fed + State EITC | I1: Value of Medicaid | J1: Value of Marketplace Subsidies | K1: Total benefits | L1: Total benefits + income
A2: 0 | B2: =A2/12 -> 0 | C2: ='Child care subsidy'!S5*12 -> 24000 | D2: =MAX('TANF-VIEW'!L9,'TANF-VIEW'!T9)*12 -> 4620 | E2: =SNAP!V6*12 -> 14196 | F2: =WIC!F8*12 -> 441.12 | G2: ='Housing Voucher'!Q6*12 -> 16049.988 | H2: =EITC!E5 -> 0 | I2: =Medicaid!N9*12 -> 26265 | K2: =SUM(C2:I2) -> 85572.108 | L2: =A2+K2 -> 85572.108 | M2: =L2/12 -> 7131.009
A3: 500 | B3: =A3/12 -> 41.666667 | C3: ='Child care subsidy'!S6*12 -> 23975 | D3: =MAX('TANF-VIEW'!L10,'TANF-VIEW'!T10)*12 -> 4620 | E3: =SNAP!V7*12 -> 14196 | F3: =WIC!F9*12 -> 441.12 | G3: ='Housing Voucher'!Q7*12 -> 15899.988 | H3: =EITC!E6 -> 240 | I3: =Medicaid!N10*12 -> 26265 | K3: =SUM(C3:I3) -> 85637.108 | L3: =A3+K3 -> 86137.108 | M3: =L3/12 -> 7178.0923
A4: 1000 | B4: =A4/12 -> 83.333333 | C4: ='Child care subsidy'!S7*12 -> 23950 | D4: =MAX('TANF-VIEW'!L11,'TANF-VIEW'!T11)*12 -> 4620 | E4: =SNAP!V8*12 -> 14196 | F4: =WIC!F10*12 -> 441.12 | G4: ='Housing Voucher'!Q8*12 -> 15749.988 | H4: =EITC!E7 -> 480 | I4: =Medicaid!N11*12 -> 26265 | K4: =SUM(C4:I4) -> 85702.108 | L4: =A4+K4 -> 86702.108 | M4: =L4/12 -> 7225.1757
A5: 1500 | B5: =A5/12 -> 125 | C5: ='Child care subsidy'!S8*12 -> 23925 | D5: =MAX('TANF-VIEW'!L12,'TANF-VIEW'!T12)*12 -> 4620 | E5: =SNAP!V9*12 -> 14196 | F5: =WIC!F11*12 -> 441.12 | G5: ='Housing Voucher'!Q9*12 -> 15599.988 | H5: =EITC!E8 -> 720 | I5: =Medicaid!N12*12 -> 26265 | K5: =SUM(C5:I5) -> 85767.108 | L5: =A5+K5 -> 87267.108 | M5: =L5/12 -> 7272.259
A6: 2000 | B6: =A6/12 -> 166.66667 | C6: ='Child care subsidy'!S9*12 -> 23900 | D6: =MAX('TANF-VIEW'!L13,'TANF-VIEW'!T13)*12 -> 4620 | E6: =SNAP!V10*12 -> 14196 | F6: =WIC!F12*12 -> 441.12 | G6: ='Housing Voucher'!Q10*12 -> 15449.988 | H6: =EITC!E9 -> 960 | I6: =Medicaid!N13*12 -> 26265 | K6: =SUM(C6:I6) -> 85832.108 | L6: =A6+K6 -> 87832.108 | M6: =L6/12 -> 7319.3423
A7: 2500 | B7: =A7/12 -> 208.33333 | C7: ='Child care subsidy'!S10*12 -> 23875 | D7: =MAX('TANF-VIEW'!L14,'TANF-VIEW'!T14)*12 -> 4620 | E7: =SNAP!V11*12 -> 14196 | F7: =WIC!F13*12 -> 441.12 | G7: ='Housing Voucher'!Q11*12 -> 15299.988 | H7: =EITC!E10 -> 1200 | I7: =Medicaid!N14*12 -> 26265 | K7: =SUM(C7:I7) -> 85897.108 | L7: =A7+K7 -> 88397.108 | M7: =L7/12 -> 7366.4257
A8: 3000 | B8: =A8/12 -> 250 | C8: ='Child care subsidy'!S11*12 -> 23850 | D8: =MAX('TANF-VIEW'!L15,'TANF-VIEW'!T15)*12 -> 4226.4 | E8: =SNAP!V12*12 -> 14196 | F8: =WIC!F14*12 -> 441.12 | G8: ='Housing Voucher'!Q12*12 -> 15268.068 | H8: =EITC!E11 -> 1440 | I8: =Medicaid!N15*12 -> 26265 | K8: =SUM(C8:I8) -> 85686.588 | L8: =A8+K8 -> 88686.588 | M8: =L8/12 -> 7390.549
A9: 3500 | B9: =A9/12 -> 291.66667 | C9: ='Child care subsidy'!S12*12 -> 23825 | D9: =MAX('TANF-VIEW'!L16,'TANF-VIEW'!T16)*12 -> 3826.4 | E9: =SNAP!V13*12 -> 14196 | F9: =WIC!F15*12 -> 441.12 | G9: ='Housing Voucher'!Q13*12 -> 15238.068 | H9: =EITC!E12 -> 1680 | I9: =Medicaid!N16*12 -> 26265 | K9: =SUM(C9:I9) -> 85471.588 | L9: =A9+K9 -> 88971.588 | M9: =L9/12 -> 7414.299
A10: 4000 | B10: =A10/12 -> 333.33333 | C10: ='Child care subsidy'!S13*12 -> 23800 | D10: =MAX('TANF-VIEW'!L17,'TANF-VIEW'!T17)*12 -> 3426.4 | E10: =SNAP!V14*12 -> 14196 | F10: =WIC!F16*12 -> 441.12 | G10: ='Housing Voucher'!Q14*12 -> 15208.068 | H10: =EITC!E13 -> 1920 | I10: =Medicaid!N17*12 -> 26265 | K10: =SUM(C10:I10) -> 85256.588 | L10: =A10+K10 -> 89256.588 | M10: =L10/12 -> 7438.049
A11: 4500 | B11: =A11/12 -> 375 | C11: ='Child care subsidy'!S14*12 -> 23775 | D11: =MAX('TANF-VIEW'!L18,'TANF-VIEW'!T18)*12 -> 3026.4 | E11: =SNAP!V15*12 -> 14196 | F11: =WIC!F17*12 -> 441.12 | G11: ='Housing Voucher'!Q15*12 -> 15178.068 | H11: =EITC!E14 -> 2160 | I11: =Medicaid!N18*12 -> 26265 | K11: =SUM(C11:I11) -> 85041.588 | L11: =A11+K11 -> 89541.588 | M11: =L11/12 -> 7461.799
A12: 5000 | B12: =A12/12 -> 416.66667 | C12: ='Child care subsidy'!S15*12 -> 23760 | D12: =MAX('TANF-VIEW'!L19,'TANF-VIEW'!T19)*12 -> 2626.4 | E12: =SNAP!V16*12 -> 14196 | F12: =WIC!F18*12 -> 441.12 | G12: ='Housing Voucher'!Q16*12 -> 15148.068 | H12: =EITC!E15 -> 2400 | I12: =Medicaid!N19*12 -> 26265 | K12: =SUM(C12:I12) -> 84836.588 | L12: =A12+K12 -> 89836.588 | M12: =L12/12 -> 7486.3823
A13: 5500 | B13: =A13/12 -> 458.33333 | C13: ='Child care subsidy'!S16*12 -> 23760 | D13: =MAX('TANF-VIEW'!L20,'TANF-VIEW'!T20)*12 -> 2226.4 | E13: =SNAP!V17*12 -> 14196 | F13: =WIC!F19*12 -> 441.12 | G13: ='Housing Voucher'!Q17*12 -> 15118.068 | H13: =EITC!E16 -> 2640 | I13: =Medicaid!N20*12 -> 26265 | K13: =SUM(C13:I13) -> 84646.588 | L13: =A13+K13 -> 90146.588 | M13: =L13/12 -> 7512.2157
... A132: 65000 | B132: =A132/12 -> 5416.6667 | C132: ='Child care subsidy'!S135*12 -> 20750 | D132: =MAX('TANF-VIEW'!L139,'TANF-VIEW'!T139)*12 -> 0 | E132: =SNAP!V136*12 -> 0 | F132: =WIC!F138*12 -> 441.12 | G132: ='Housing Voucher'!Q136*12 -> 0 | H132: =EITC!E135 -> 0 | I132: =Medicaid!N139*12 -> 7644 | K132: =SUM(C132:I132) -> 28835.12 | L132: =A132+K132 -> 93835.12 | M132: =L132/12 -> 7819.5933
A133: 65500 | B133: =A133/12 -> 5458.3333 | C133: ='Child care subsidy'!S136*12 -> 20725 | D133: =MAX('TANF-VIEW'!L140,'TANF-VIEW'!T140)*12 -> 0 | E133: =SNAP!V137*12 -> 0 | F133: =WIC!F139*12 -> 441.12 | G133: ='Housing Voucher'!Q137*12 -> 0 | H133: =EITC!E136 -> 0 | I133: =Medicaid!N140*12 -> 7644 | K133: =SUM(C133:I133) -> 28810.12 | L133: =A133+K133 -> 94310.12 | M133: =L133/12 -> 7859.1767 | P133: =C135/12 -> 1722.9167
A134: 66000 | B134: =A134/12 -> 5500 | C134: ='Child care subsidy'!S137*12 -> 20700 | D134: =MAX('TANF-VIEW'!L141,'TANF-VIEW'!T141)*12 -> 0 | E134: =SNAP!V138*12 -> 0 | F134: =WIC!F140*12 -> 441.12 | G134: ='Housing Voucher'!Q138*12 -> 0 | H134: =EITC!E137 -> 0 | I134: =Medicaid!N141*12 -> 7644 | K134: =SUM(C134:I134) -> 28785.12 | L134: =A134+K134 -> 94785.12 | M134: =L134/12 -> 7898.76
A135: 66500 | B135: =A135/12 -> 5541.6667 | C135: ='Child care subsidy'!S138*12 -> 20675 | D135: =MAX('TANF-VIEW'!L142,'TANF-VIEW'!T142)*12 -> 0 | E135: =SNAP!V139*12 -> 0 | F135: =WIC!F141*12 -> 441.12 | G135: ='Housing Voucher'!Q139*12 -> 0 | H135: =EITC!E138 -> 0 | I135: =Medicaid!N142*12 -> 7644 | K135: =SUM(C135:I135) -> 28760.12 | L135: =A135+K135 -> 95260.12 | M135: =L135/12 -> 7938.3433
A136: 67000 | B136: =A136/12 -> 5583.3333 | C136: ='Child care subsidy'!S139*12 -> 20650 | D136: =MAX('TANF-VIEW'!L143,'TANF-VIEW'!T143)*12 -> 0 | E136: =SNAP!V140*12 -> 0 | F136: =WIC!F142*12 -> 0 | G136: ='Housing Voucher'!Q140*12 -> 0 | H136: =EITC!E139 -> 0 | I136: =Medicaid!N143*12 -> 7644 | K136: =SUM(C136:I136) -> 28294 | L136: =A136+K136 -> 95294 | M136: =L136/12 -> 7941.1667
A137: 67500 | B137: =A137/12 -> 5625 | C137: ='Child care subsidy'!S140*12 -> 20625 | D137: =MAX('TANF-VIEW'!L144,'TANF-VIEW'!T144)*12 -> 0 | E137: =SNAP!V141*12 -> 0 | F137: =WIC!F143*12 -> 0 | G137: ='Housing Voucher'!Q141*12 -> 0 | H137: =EITC!E140 -> 0 | I137: =Medicaid!N144*12 -> 7644 | K137: =SUM(C137:I137) -> 28269 | L137: =A137+K137 -> 95769 | M137: =L137/12 -> 7980.75
A138: 68000 | B138: =A138/12 -> 5666.6667 | C138: ='Child care subsidy'!S141*12 -> 20600 | D138: =MAX('TANF-VIEW'!L145,'TANF-VIEW'!T145)*12 -> 0 | E138: =SNAP!V142*12 -> 0 | F138: =WIC!F144*12 -> 0 | G138: ='Housing Voucher'!Q142*12 -> 0 | H138: =EITC!E141 -> 0 | I138: =Medicaid!N145*12 -> 7644 | K138: =SUM(C138:I138) -> 28244 | L138: =A138+K138 -> 96244 | M138: =L138/12 -> 8020.3333
A139: 68500 | B139: =A139/12 -> 5708.3333 | C139: ='Child care subsidy'!S142*12 -> 20575 | D139: =MAX('TANF-VIEW'!L146,'TANF-VIEW'!T146)*12 -> 0 | E139: =SNAP!V143*12 -> 0 | F139: =WIC!F145*12 -> 0 | G139: ='Housing Voucher'!Q143*12 -> 0 | H139: =EITC!E142 -> 0 | I139: =Medicaid!N146*12 -> 7644 | K139: =SUM(C139:I139) -> 28219 | L139: =A139+K139 -> 96719 | M139: =L139/12 -> 8059.9167
A140: 69000 | B140: =A140/12 -> 5750 | C140: ='Child care subsidy'!S143*12 -> 20550 | D140: =MAX('TANF-VIEW'!L147,'TANF-VIEW'!T147)*12 -> 0 | E140: =SNAP!V144*12 -> 0 | F140: =WIC!F146*12 -> 0 | G140: ='Housing Voucher'!Q144*12 -> 0 | H140: =EITC!E143 -> 0 | I140: =Medicaid!N147*12 -> 7644 | K140: =SUM(C140:I140) -> 28194 | L140: =A140+K140 -> 97194 | M140: =L140/12 -> 8099.5
A141: 69500 | B141: =A141/12 -> 5791.6667 | C141: ='Child care subsidy'!S144*12 -> 20525 | D141: =MAX('TANF-VIEW'!L148,'TANF-VIEW'!T148)*12 -> 0 | E141: =SNAP!V145*12 -> 0 | F141: =WIC!F147*12 -> 0 | G141: ='Housing Voucher'!Q145*12 -> 0 | H141: =EITC!E144 -> 0 | I141: =Medicaid!N148*12 -> 7644 | K141: =SUM(C141:I141) -> 28169 | L141: =A141+K141 -> 97669 | M141: =L141/12 -> 8139.0833
A142: 70000 | B142: =A142/12 -> 5833.3333 | C142: ='Child care subsidy'!S145*12 -> 20500 | D142: =MAX('TANF-VIEW'!L149,'TANF-VIEW'!T149)*12 -> 0 | E142: =SNAP!V146*12 -> 0 | F142: =WIC!F148*12 -> 0 | G142: ='Housing Voucher'!Q146*12 -> 0 | H142: =EITC!E145 -> 0 | I142: =Medicaid!N149*12 -> 7644 | K142: =SUM(C142:I142) -> 28144 | L142: =A142+K142 -> 98144 | M142: =L142/12 -> 8178.6667
A143: 70500 | B143: =A143/12 -> 5875 | C143: ='Child care subsidy'!S146*12 -> 20475 | D143: =MAX('TANF-VIEW'!L150,'TANF-VIEW'!T150)*12 -> 0 | E143: =SNAP!V147*12 -> 0 | F143: =WIC!F149*12 -> 0 | G143: ='Housing Voucher'!Q147*12 -> 0 | H143: =EITC!E146 -> 0 | I143: =Medicaid!N150*12 -> 7644 | K143: =SUM(C143:I143) -> 28119 | L143: =A143+K143 -> 98619 | M143: =L143/12 -> 8218.25
A144: 71000 | B144: =A144/12 -> 5916.6667 | C144: ='Child care subsidy'!S147*12 -> 20450 | D144: =MAX('TANF-VIEW'!L151,'TANF-VIEW'!T151)*12 -> 0 | E144: =SNAP!V148*12 -> 0 | F144: =WIC!F150*12 -> 0 | G144: ='Housing Voucher'!Q148*12 -> 0 | H144: =EITC!E147 -> 0 | I144: =Medicaid!N151*12 -> 7644 | K144: =SUM(C144:I144) -> 28094 | L144: =A144+K144 -> 99094 | M144: =L144/12 -> 8257.8333
A145: 71500 | B145: =A145/12 -> 5958.3333 | C145: ='Child care subsidy'!S148*12 -> 20425 | D145: =MAX('TANF-VIEW'!L152,'TANF-VIEW'!T152)*12 -> 0 | E145: =SNAP!V149*12 -> 0 | F145: =WIC!F151*12 -> 0 | G145: ='Housing Voucher'!Q149*12 -> 0 | H145: =EITC!E148 -> 0 | I145: =Medicaid!N152*12 -> 7644 | K145: =SUM(C145:I145) -> 28069 | L145: =A145+K145 -> 99569 | M145: =L145/12 -> 8297.4167
... A202: 100000 | B202: =A202/12 -> 8333.3333 | C202: ='Child care subsidy'!S205*12 -> 17000 | D202: =MAX('TANF-VIEW'!L209,'TANF-VIEW'!T209)*12 -> 0 | E202: =SNAP!V206*12 -> 0 | F202: =WIC!F208*12 -> 0 | G202: ='Housing Voucher'!Q206*12 -> 0 | H202: =EITC!E205 -> 0 | I202: =Medicaid!N209*12 -> 0 | K202: =SUM(C202:I202) -> 17000 | L202: =A202+K202 -> 117000 | M202: =L202/12 -> 9750

Sheet Data validation
A1: Localities | B1: Benefit programs | E1: Ages | G1: Filing status
A2: Accomack | B2: Child care subsidy | E2: Infant | G2: Married filing jointly
A3: Albemarle | B3: EITC (Fed & State) | E3: Toddler | G3: Single, head of household, qualifying surviving spouse
A4: Alexandria City | B4: Health insurance marketplace subsidies | E4: Two year old
A5: Alleghany | B5: Housing choice voucher | E5: Preschool
A6: Amelia | B6: Medicaid | E6: School age
A7: Amherst | B7: SNAP | E7: 13 years or older | G7: Not valid for >10 household members
A8: Appomattox | B8: TANF | E8: 13-18 years old
A9: Arlington County | B9: TANF/VIEW | G9: # of bedrooms
A10: Augusta | B10: WIC | E10: Addition/Subtraction | G10: 1
A11: Bath | E11: Addition | G11: 2
A12: Bedford | B12: Yes/No | E12: Subtraction | G12: 3
A13: Bland | B13: Yes | G13: 4
A14: Botetourt | B14: No
A15: Bristol | E15: Yes/No ABD
A16: Brunswick | E16: Yes-aged
A17: Buchanan | E17: Yes-blind
A18: Buckingham | B18: Incomes | E18: Yes-disabled
A19: Buena Vista | B19: 0 | E19: No
A20: Campbell | B20: 1000
A21: Caroline | B21: 2000
A22: Carroll | B22: 3000 | E22: SUA
A23: Charles City | B23: 4000 | E23: Standard Utility Allowance (SUA)
A24: Charlotte | B24: 5000 | E24: Actual monthly utility costs
A25: Charlottesville City | B25: 6000
A26: Chesapeake | B26: 7000
A27: Chesterfield | B27: 8000
A28: Clarke | B28: 9000
A29: Colonial Heights | B29: 10000
A30: Covington | B30: 11000
A31: Craig | B31: 12000
A32: Culpeper | B32: 13000
A33: Cumberland | B33: 14000
A34: Danville city | B34: 15000
A35: Dickenson County | B35: 16000
A36: Dinwiddie | B36: 17000
... A119: Stafford | B119: 100000
A120: Staunton City
A121: Suffolk
A122: Surry
A123: Sussex
A124: Tazewell
A125: Virginia Beach City
A126: Warren
A127: Washington
A128: Waynesboro City
A129: Westmoreland
A130: Williamsburg City
A131: Winchester City
... A134: York

Sheet Graphs

Sheet Child care subsidy
A1: Location | B1: Number in Household | C1: Number of eligible children infant | D1: Number of eligible children toddler | E1: Number of eligible children 2yo | F1: Number of eligible children preschool | G1: Number of eligible children school age | H1: Number of eligible children 13-18 unable to care for themselves | J1: Annual FPL for Household number | K1: Monthly FPL for Household number | M1: Monthly income limit for group and HH size | N1: 85% SMI | O1: Child care disregards SSI, TANF, child earnings if <18 | S1: =1344/20 -> 67.2
A2: ='Total income package'!B3 -> Buckingham | B2: ='Total income package'!B32 -> 5 | C2: =COUNTIF('Total income package'!$B$48:$B$54,"Infant") -> 1 | D2: =COUNTIF('Total income package'!$B$48:$B$54,"Toddler") -> 0 | E2: =COUNTIF('Total income package'!$B$48:$B$54,"Two year old") -> 0 | F2: =COUNTIF('Total income package'!$B$48:$B$54,"Preschool") -> 0 | G2: =COUNTIF('Total income package'!$B$48:$B$54,"School age") -> 1 | H2: =COUNTIF('Total income package'!$B$48:$B$54,"13-18 years old") -> 0 | J2: =VLOOKUP(B2,'Program specific data'!A5:C13,2) -> 38680 | K2: =VLOOKUP(B2,'Program specific data'!A5:C13,3) -> 3223.3333 | M2: =IF(A3=1,VLOOKUP(B2,'Program specific data'!A20:F27,3,FALSE),IF(A3=2,VLOOKUP(B2,'Program specific data'!A20:F27,4,FALSE),IF(A3=3,VLOOKUP(B2,'Program specific data'!A20:F27,5),IF(A3=4,VLOOKUP(B2,'Program specific data'!A20:F27,6,FALSE))))) -> 4835 | N2: =VLOOKUP(B2,'Program specific data'!A20:B27,2) -> 11011
A3: =VLOOKUP('Total income package'!B3,'Location specific data'!A3:AM135,39,FALSE) -> 1 | F3: Level I Care Center Max Reimbursement Rate (Full Day)
A4: Annual earned income | B4: Monthly earned income | C4: Social Security income | D4: Total Income | E4: % FPL | F4: Eligible by 85% SMI & have a child <5 yrs & not started kindergarten? | G4: Eligible by %FPL for locality? | H4: Eligible by in TANF | I4: Monthly copayment per child | J4: Monthly Infant | K4: Monthly Toddler | L4: Monthly 2yo | M4: Monthly Pre-school | N4: Monthly School Age and/or 13-18 unable to care for self | O4: Monthly copay based on number of children | P4: 5% of monthly income | Q4: Copay for 3 children | R4: Family copay if not >5% of income & capped at 3 children | S4: Monthly Child care benefit (Reimbursement - copay) If eligible via SMI, TANF, or FPL and Child Care subsidy is selected
A5: 0 | B5: =A5/12 -> 0 | C5: ='Total income package'!$D$80 -> 0 | D5: =B5+C5 -> 0 | E5: =D5/$K$2 -> 0 | F5: =IF(AND(B5<$N$2,SUM($C$2:$F$2)>0),"Yes","No") -> Yes | G5: =IF(B5<$M$2,"Yes","No") -> Yes | H5: =IF(OR('TANF-VIEW'!L9>0,'TANF-VIEW'!T9>0),"Yes","No") -> Yes | I5: =IF(B5>=$N$2,0,IF(E5>3.5,375*SUM($C$2:$H$2),IF(E5>3,325*SUM($C$2:$H$2),IF(E5>2.5,275*SUM($C$2:$H$2),IF(E5>2,225*SUM($C$2:$H$2),IF(E5>1.5,175*SUM($C$2:$H$2),IF(E5>1,125*SUM($C$2:$H$2),IF(E5>0,5*SUM($C$2:$H$2),0)))))))) -> 0 | J5: =(IF(B5>$N$2,0,VLOOKUP('Total income package'!$B$3,'Location specific data'!$A$3:$AO$135,33,FALSE))*$C$2)*20 -> 1400 | K5: =IF(B5>$N$2,0,VLOOKUP('Total income package'!$B$3,'Location specific data'!$A$3:$AO$135,34,FALSE))*$D$2*20 -> 0 | L5: =IF(B5>$N$2,0,VLOOKUP('Total income package'!$B$3,'Location specific data'!$A$3:$AO$135,35,FALSE))*$E$2*20 -> 0 | M5: =IF(B5>$N$2,0,VLOOKUP('Total income package'!$B$3,'Location specific data'!$A$3:$AO$135,36,FALSE))*$F$2*20 -> 0 | N5: =IF(B5>$N$2,0,VLOOKUP('Total income package'!$B$3,'Location specific data'!$A$3:$AO$135,37,FALSE))*($G$2+$H$2)*20 -> 600 | O5: =I5*SUM($C$2:$H$2) -> 0 | P5: =B5*0.05 -> 0 | Q5: =I5*3 -> 0 | R5: =IF(MIN(O5,P5)<Q5,MIN(O5,P5),Q5) -> 0 | S5: =IF(AND('Total income package'!$A$8=TRUE,OR(F5="Yes",G5="Yes",H5="Yes")),SUM(J5:N5)-R5,0) -> 2000
A6: 500 | B6: =A6/12 -> 41.666667 | C6: ='Total income package'!$D$80 -> 0 | D6: =B6+C6 -> 41.666667 | E6: =D6/$K$2 -> 0.012926577 | F6: =IF(AND(B6<$N$2,SUM($C$2:$F$2)>0),"Yes","No") -> Yes | G6: =IF(B6<$M$2,"Yes","No") -> Yes | H6: =IF(OR('TANF-VIEW'!L10>0,'TANF-VIEW'!T10>0),"Yes","No") -> Yes | I6: =IF(B6>=$N$2,0,IF(E6>3.5,375*SUM($C$2:$H$2),IF(E6>3,325*SUM($C$2:$H$2),IF(E6>2.5,275*SUM($C$2:$H$2),IF(E6>2,225*SUM($C$2:$H$2),IF(E6>1.5,175*SUM($C$2:$H$2),IF(E6>1,125*SUM($C$2:$H$2),IF(E6>0,5*SUM($C$2:$H$2),0)))))))) -> 10 | J6: =(IF(B6>$N$2,0,VLOOKUP('Total income package'!$B$3,'Location specific data'!$A$3:$AO$135,33,FALSE))*$C$2)*20 -> 1400 | K6: =IF(B6>$N$2,0,VLOOKUP('Total income package'!$B$3,'Location specific data'!$A$3:$AO$135,34,FALSE))*$D$2*20 -> 0 | L6: =IF(B6>$N$2,0,VLOOKUP('Total income package'!$B$3,'Location specific data'!$A$3:$AO$135,35,FALSE))*$E$2*20 -> 0 | M6: =IF(B6>$N$2,0,VLOOKUP('Total income package'!$B$3,'Location specific data'!$A$3:$AO$135,36,FALSE))*$F$2*20 -> 0 | N6: =IF(B6>$N$2,0,VLOOKUP('Total income package'!$B$3,'Location specific data'!$A$3:$AO$135,37,FALSE))*($G$2+$H$2)*20 -> 600 | O6: =I6*SUM($C$2:$H$2) -> 20 | P6: =B6*0.05 -> 2.0833333 | Q6: =I6*3 -> 30 | R6: =IF(MIN(O6,P6)<Q6,MIN(O6,P6),Q6) -> 2.0833333 | S6: =IF(AND('Total income package'!$A$8=TRUE,OR(F6="Yes",G6="Yes",H6="Yes")),SUM(J6:N6)-R6,0) -> 1997.9167
A7: 1000 | B7: =A7/12 -> 83.333333 | C7: ='Total income package'!$D$80 -> 0 | D7: =B7+C7 -> 83.333333 | E7: =D7/$K$2 -> 0.025853154 | F7: =IF(AND(B7<$N$2,SUM($C$2:$F$2)>0),"Yes","No") -> Yes | G7: =IF(B7<$M$2,"Yes","No") -> Yes | H7: =IF(OR('TANF-VIEW'!L11>0,'TANF-VIEW'!T11>0),"Yes","No") -> Yes | I7: =IF(B7>=$N$2,0,IF(E7>3.5,375*SUM($C$2:$H$2),IF(E7>3,325*SUM($C$2:$H$2),IF(E7>2.5,275*SUM($C$2:$H$2),IF(E7>2,225*SUM($C$2:$H$2),IF(E7>1.5,175*SUM($C$2:$H$2),IF(E7>1,125*SUM($C$2:$H$2),IF(E7>0,5*SUM($C$2:$H$2),0)))))))) -> 10 | J7: =(IF(B7>$N$2,0,VLOOKUP('Total income package'!$B$3,'Location specific data'!$A$3:$AO$135,33,FALSE))*$C$2)*20 -> 1400 | K7: =IF(B7>$N$2,0,VLOOKUP('Total income package'!$B$3,'Location specific data'!$A$3:$AO$135,34,FALSE))*$D$2*20 -> 0 | L7: =IF(B7>$N$2,0,VLOOKUP('Total income package'!$B$3,'Location specific data'!$A$3:$AO$135,35,FALSE))*$E$2*20 -> 0 | M7: =IF(B7>$N$2,0,VLOOKUP('Total income package'!$B$3,'Location specific data'!$A$3:$AO$135,36,FALSE))*$F$2*20 -> 0 | N7: =IF(B7>$N$2,0,VLOOKUP('Total income package'!$B$3,'Location specific data'!$A$3:$AO$135,37,FALSE))*($G$2+$H$2)*20 -> 600 | O7: =I7*SUM($C$2:$H$2) -> 20 | P7: =B7*0.05 -> 4.1666667 | Q7: =I7*3 -> 30 | R7: =IF(MIN(O7,P7)<Q7,MIN(O7,P7),Q7) -> 4.1666667 | S7: =IF(AND('Total income package'!$A$8=TRUE,OR(F7="Yes",G7="Yes",H7="Yes")),SUM(J7:N7)-R7,0) -> 1995.8333
A8: 1500 | B8: =A8/12 -> 125 | C8: ='Total income package'!$D$80 -> 0 | D8: =B8+C8 -> 125 | E8: =D8/$K$2 -> 0.038779731 | F8: =IF(AND(B8<$N$2,SUM($C$2:$F$2)>0),"Yes","No") -> Yes | G8: =IF(B8<$M$2,"Yes","No") -> Yes | H8: =IF(OR('TANF-VIEW'!L12>0,'TANF-VIEW'!T12>0),"Yes","No") -> Yes | I8: =IF(B8>=$N$2,0,IF(E8>3.5,375*SUM($C$2:$H$2),IF(E8>3,325*SUM($C$2:$H$2),IF(E8>2.5,275*SUM($C$2:$H$2),IF(E8>2,225*SUM($C$2:$H$2),IF(E8>1.5,175*SUM($C$2:$H$2),IF(E8>1,125*SUM($C$2:$H$2),IF(E8>0,5*SUM($C$2:$H$2),0)))))))) -> 10 | J8: =(IF(B8>$N$2,0,VLOOKUP('Total income package'!$B$3,'Location specific data'!$A$3:$AO$135,33,FALSE))*$C$2)*20 -> 1400 | K8: =IF(B8>$N$2,0,VLOOKUP('Total income package'!$B$3,'Location specific data'!$A$3:$AO$135,34,FALSE))*$D$2*20 -> 0 | L8: =IF(B8>$N$2,0,VLOOKUP('Total income package'!$B$3,'Location specific data'!$A$3:$AO$135,35,FALSE))*$E$2*20 -> 0 | M8: =IF(B8>$N$2,0,VLOOKUP('Total income package'!$B$3,'Location specific data'!$A$3:$AO$135,36,FALSE))*$F$2*20 -> 0 | N8: =IF(B8>$N$2,0,VLOOKUP('Total income package'!$B$3,'Location specific data'!$A$3:$AO$135,37,FALSE))*($G$2+$H$2)*20 -> 600 | O8: =I8*SUM($C$2:$H$2) -> 20 | P8: =B8*0.05 -> 6.25 | Q8: =I8*3 -> 30 | R8: =IF(MIN(O8,P8)<Q8,MIN(O8,P8),Q8) -> 6.25 | S8: =IF(AND('Total income package'!$A$8=TRUE,OR(F8="Yes",G8="Yes",H8="Yes")),SUM(J8:N8)-R8,0) -> 1993.75
A9: 2000 | B9: =A9/12 -> 166.66667 | C9: ='Total income package'!$D$80 -> 0 | D9: =B9+C9 -> 166.66667 | E9: =D9/$K$2 -> 0.051706308 | F9: =IF(AND(B9<$N$2,SUM($C$2:$F$2)>0),"Yes","No") -> Yes | G9: =IF(B9<$M$2,"Yes","No") -> Yes | H9: =IF(OR('TANF-VIEW'!L13>0,'TANF-VIEW'!T13>0),"Yes","No") -> Yes | I9: =IF(B9>=$N$2,0,IF(E9>3.5,375*SUM($C$2:$H$2),IF(E9>3,325*SUM($C$2:$H$2),IF(E9>2.5,275*SUM($C$2:$H$2),IF(E9>2,225*SUM($C$2:$H$2),IF(E9>1.5,175*SUM($C$2:$H$2),IF(E9>1,125*SUM($C$2:$H$2),IF(E9>0,5*SUM($C$2:$H$2),0)))))))) -> 10 | J9: =(IF(B9>$N$2,0,VLOOKUP('Total income package'!$B$3,'Location specific data'!$A$3:$AO$135,33,FALSE))*$C$2)*20 -> 1400 | K9: =IF(B9>$N$2,0,VLOOKUP('Total income package'!$B$3,'Location specific data'!$A$3:$AO$135,34,FALSE))*$D$2*20 -> 0 | L9: =IF(B9>$N$2,0,VLOOKUP('Total income package'!$B$3,'Location specific data'!$A$3:$AO$135,35,FALSE))*$E$2*20 -> 0 | M9: =IF(B9>$N$2,0,VLOOKUP('Total income package'!$B$3,'Location specific data'!$A$3:$AO$135,36,FALSE))*$F$2*20 -> 0 | N9: =IF(B9>$N$2,0,VLOOKUP('Total income package'!$B$3,'Location specific data'!$A$3:$AO$135,37,FALSE))*($G$2+$H$2)*20 -> 600 | O9: =I9*SUM($C$2:$H$2) -> 20 | P9: =B9*0.05 -> 8.3333333 | Q9: =I9*3 -> 30 | R9: =IF(MIN(O9,P9)<Q9,MIN(O9,P9),Q9) -> 8.3333333 | S9: =IF(AND('Total income package'!$A$8=TRUE,OR(F9="Yes",G9="Yes",H9="Yes")),SUM(J9:N9)-R9,0) -> 1991.6667
A10: 2500 | B10: =A10/12 -> 208.33333 | C10: ='Total income package'!$D$80 -> 0 | D10: =B10+C10 -> 208.33333 | E10: =D10/$K$2 -> 0.064632885 | F10: =IF(AND(B10<$N$2,SUM($C$2:$F$2)>0),"Yes","No") -> Yes | G10: =IF(B10<$M$2,"Yes","No") -> Yes | H10: =IF(OR('TANF-VIEW'!L14>0,'TANF-VIEW'!T14>0),"Yes","No") -> Yes | I10: =IF(B10>=$N$2,0,IF(E10>3.5,375*SUM($C$2:$H$2),IF(E10>3,325*SUM($C$2:$H$2),IF(E10>2.5,275*SUM($C$2:$H$2),IF(E10>2,225*SUM($C$2:$H$2),IF(E10>1.5,175*SUM($C$2:$H$2),IF(E10>1,125*SUM($C$2:$H$2),IF(E10>0,5*SUM($C$2:$H$2),0)))))))) -> 10 | J10: =(IF(B10>$N$2,0,VLOOKUP('Total income package'!$B$3,'Location specific data'!$A$3:$AO$135,33,FALSE))*$C$2)*20 -> 1400 | K10: =IF(B10>$N$2,0,VLOOKUP('Total income package'!$B$3,'Location specific data'!$A$3:$AO$135,34,FALSE))*$D$2*20 -> 0 | L10: =IF(B10>$N$2,0,VLOOKUP('Total income package'!$B$3,'Location specific data'!$A$3:$AO$135,35,FALSE))*$E$2*20 -> 0 | M10: =IF(B10>$N$2,0,VLOOKUP('Total income package'!$B$3,'Location specific data'!$A$3:$AO$135,36,FALSE))*$F$2*20 -> 0 | N10: =IF(B10>$N$2,0,VLOOKUP('Total income package'!$B$3,'Location specific data'!$A$3:$AO$135,37,FALSE))*($G$2+$H$2)*20 -> 600 | O10: =I10*SUM($C$2:$H$2) -> 20 | P10: =B10*0.05 -> 10.416667 | Q10: =I10*3 -> 30 | R10: =IF(MIN(O10,P10)<Q10,MIN(O10,P10),Q10) -> 10.416667 | S10: =IF(AND('Total income package'!$A$8=TRUE,OR(F10="Yes",G10="Yes",H10="Yes")),SUM(J10:N10)-R10,0) -> 1989.5833
A11: 3000 | B11: =A11/12 -> 250 | C11: ='Total income package'!$D$80 -> 0 | D11: =B11+C11 -> 250 | E11: =D11/$K$2 -> 0.077559462 | F11: =IF(AND(B11<$N$2,SUM($C$2:$F$2)>0),"Yes","No") -> Yes | G11: =IF(B11<$M$2,"Yes","No") -> Yes | H11: =IF(OR('TANF-VIEW'!L15>0,'TANF-VIEW'!T15>0),"Yes","No") -> Yes | I11: =IF(B11>=$N$2,0,IF(E11>3.5,375*SUM($C$2:$H$2),IF(E11>3,325*SUM($C$2:$H$2),IF(E11>2.5,275*SUM($C$2:$H$2),IF(E11>2,225*SUM($C$2:$H$2),IF(E11>1.5,175*SUM($C$2:$H$2),IF(E11>1,125*SUM($C$2:$H$2),IF(E11>0,5*SUM($C$2:$H$2),0)))))))) -> 10 | J11: =(IF(B11>$N$2,0,VLOOKUP('Total income package'!$B$3,'Location specific data'!$A$3:$AO$135,33,FALSE))*$C$2)*20 -> 1400 | K11: =IF(B11>$N$2,0,VLOOKUP('Total income package'!$B$3,'Location specific data'!$A$3:$AO$135,34,FALSE))*$D$2*20 -> 0 | L11: =IF(B11>$N$2,0,VLOOKUP('Total income package'!$B$3,'Location specific data'!$A$3:$AO$135,35,FALSE))*$E$2*20 -> 0 | M11: =IF(B11>$N$2,0,VLOOKUP('Total income package'!$B$3,'Location specific data'!$A$3:$AO$135,36,FALSE))*$F$2*20 -> 0 | N11: =IF(B11>$N$2,0,VLOOKUP('Total income package'!$B$3,'Location specific data'!$A$3:$AO$135,37,FALSE))*($G$2+$H$2)*20 -> 600 | O11: =I11*SUM($C$2:$H$2) -> 20 | P11: =B11*0.05 -> 12.5 | Q11: =I11*3 -> 30 | R11: =IF(MIN(O11,P11)<Q11,MIN(O11,P11),Q11) -> 12.5 | S11: =IF(AND('Total income package'!$A$8=TRUE,OR(F11="Yes",G11="Yes",H11="Yes")),SUM(J11:N11)-R11,0) -> 1987.5
A12: 3500 | B12: =A12/12 -> 291.66667 | C12: ='Total income package'!$D$80 -> 0 | D12: =B12+C12 -> 291.66667 | E12: =D12/$K$2 -> 0.090486039 | F12: =IF(AND(B12<$N$2,SUM($C$2:$F$2)>0),"Yes","No") -> Yes | G12: =IF(B12<$M$2,"Yes","No") -> Yes | H12: =IF(OR('TANF-VIEW'!L16>0,'TANF-VIEW'!T16>0),"Yes","No") -> Yes | I12: =IF(B12>=$N$2,0,IF(E12>3.5,375*SUM($C$2:$H$2),IF(E12>3,325*SUM($C$2:$H$2),IF(E12>2.5,275*SUM($C$2:$H$2),IF(E12>2,225*SUM($C$2:$H$2),IF(E12>1.5,175*SUM($C$2:$H$2),IF(E12>1,125*SUM($C$2:$H$2),IF(E12>0,5*SUM($C$2:$H$2),0)))))))) -> 10 | J12: =(IF(B12>$N$2,0,VLOOKUP('Total income package'!$B$3,'Location specific data'!$A$3:$AO$135,33,FALSE))*$C$2)*20 -> 1400 | K12: =IF(B12>$N$2,0,VLOOKUP('Total income package'!$B$3,'Location specific data'!$A$3:$AO$135,34,FALSE))*$D$2*20 -> 0 | L12: =IF(B12>$N$2,0,VLOOKUP('Total income package'!$B$3,'Location specific data'!$A$3:$AO$135,35,FALSE))*$E$2*20 -> 0 | M12: =IF(B12>$N$2,0,VLOOKUP('Total income package'!$B$3,'Location specific data'!$A$3:$AO$135,36,FALSE))*$F$2*20 -> 0 | N12: =IF(B12>$N$2,0,VLOOKUP('Total income package'!$B$3,'Location specific data'!$A$3:$AO$135,37,FALSE))*($G$2+$H$2)*20 -> 600 | O12: =I12*SUM($C$2:$H$2) -> 20 | P12: =B12*0.05 -> 14.583333 | Q12: =I12*3 -> 30 | R12: =IF(MIN(O12,P12)<Q12,MIN(O12,P12),Q12) -> 14.583333 | S12: =IF(AND('Total income package'!$A$8=TRUE,OR(F12="Yes",G12="Yes",H12="Yes")),SUM(J12:N12)-R12,0) -> 1985.4167
A13: 4000 | B13: =A13/12 -> 333.33333 | C13: ='Total income package'!$D$80 -> 0 | D13: =B13+C13 -> 333.33333 | E13: =D13/$K$2 -> 0.10341262 | F13: =IF(AND(B13<$N$2,SUM($C$2:$F$2)>0),"Yes","No") -> Yes | G13: =IF(B13<$M$2,"Yes","No") -> Yes | H13: =IF(OR('TANF-VIEW'!L17>0,'TANF-VIEW'!T17>0),"Yes","No") -> Yes | I13: =IF(B13>=$N$2,0,IF(E13>3.5,375*SUM($C$2:$H$2),IF(E13>3,325*SUM($C$2:$H$2),IF(E13>2.5,275*SUM($C$2:$H$2),IF(E13>2,225*SUM($C$2:$H$2),IF(E13>1.5,175*SUM($C$2:$H$2),IF(E13>1,125*SUM($C$2:$H$2),IF(E13>0,5*SUM($C$2:$H$2),0)))))))) -> 10 | J13: =(IF(B13>$N$2,0,VLOOKUP('Total income package'!$B$3,'Location specific data'!$A$3:$AO$135,33,FALSE))*$C$2)*20 -> 1400 | K13: =IF(B13>$N$2,0,VLOOKUP('Total income package'!$B$3,'Location specific data'!$A$3:$AO$135,34,FALSE))*$D$2*20 -> 0 | L13: =IF(B13>$N$2,0,VLOOKUP('Total income package'!$B$3,'Location specific data'!$A$3:$AO$135,35,FALSE))*$E$2*20 -> 0 | M13: =IF(B13>$N$2,0,VLOOKUP('Total income package'!$B$3,'Location specific data'!$A$3:$AO$135,36,FALSE))*$F$2*20 -> 0 | N13: =IF(B13>$N$2,0,VLOOKUP('Total income package'!$B$3,'Location specific data'!$A$3:$AO$135,37,FALSE))*($G$2+$H$2)*20 -> 600 | O13: =I13*SUM($C$2:$H$2) -> 20 | P13: =B13*0.05 -> 16.666667 | Q13: =I13*3 -> 30 | R13: =IF(MIN(O13,P13)<Q13,MIN(O13,P13),Q13) -> 16.666667 | S13: =IF(AND('Total income package'!$A$8=TRUE,OR(F13="Yes",G13="Yes",H13="Yes")),SUM(J13:N13)-R13,0) -> 1983.3333
A14: 4500 | B14: =A14/12 -> 375 | C14: ='Total income package'!$D$80 -> 0 | D14: =B14+C14 -> 375 | E14: =D14/$K$2 -> 0.11633919 | F14: =IF(AND(B14<$N$2,SUM($C$2:$F$2)>0),"Yes","No") -> Yes | G14: =IF(B14<$M$2,"Yes","No") -> Yes | H14: =IF(OR('TANF-VIEW'!L18>0,'TANF-VIEW'!T18>0),"Yes","No") -> Yes | I14: =IF(B14>=$N$2,0,IF(E14>3.5,375*SUM($C$2:$H$2),IF(E14>3,325*SUM($C$2:$H$2),IF(E14>2.5,275*SUM($C$2:$H$2),IF(E14>2,225*SUM($C$2:$H$2),IF(E14>1.5,175*SUM($C$2:$H$2),IF(E14>1,125*SUM($C$2:$H$2),IF(E14>0,5*SUM($C$2:$H$2),0)))))))) -> 10 | J14: =(IF(B14>$N$2,0,VLOOKUP('Total income package'!$B$3,'Location specific data'!$A$3:$AO$135,33,FALSE))*$C$2)*20 -> 1400 | K14: =IF(B14>$N$2,0,VLOOKUP('Total income package'!$B$3,'Location specific data'!$A$3:$AO$135,34,FALSE))*$D$2*20 -> 0 | L14: =IF(B14>$N$2,0,VLOOKUP('Total income package'!$B$3,'Location specific data'!$A$3:$AO$135,35,FALSE))*$E$2*20 -> 0 | M14: =IF(B14>$N$2,0,VLOOKUP('Total income package'!$B$3,'Location specific data'!$A$3:$AO$135,36,FALSE))*$F$2*20 -> 0 | N14: =IF(B14>$N$2,0,VLOOKUP('Total income package'!$B$3,'Location specific data'!$A$3:$AO$135,37,FALSE))*($G$2+$H$2)*20 -> 600 | O14: =I14*SUM($C$2:$H$2) -> 20 | P14: =B14*0.05 -> 18.75 | Q14: =I14*3 -> 30 | R14: =IF(MIN(O14,P14)<Q14,MIN(O14,P14),Q14) -> 18.75 | S14: =IF(AND('Total income package'!$A$8=TRUE,OR(F14="Yes",G14="Yes",H14="Yes")),SUM(J14:N14)-R14,0) -> 1981.25
A15: 5000 | B15: =A15/12 -> 416.66667 | C15: ='Total income package'!$D$80 -> 0 | D15: =B15+C15 -> 416.66667 | E15: =D15/$K$2 -> 0.12926577 | F15: =IF(AND(B15<$N$2,SUM($C$2:$F$2)>0),"Yes","No") -> Yes | G15: =IF(B15<$M$2,"Yes","No") -> Yes | H15: =IF(OR('TANF-VIEW'!L19>0,'TANF-VIEW'!T19>0),"Yes","No") -> Yes | I15: =IF(B15>=$N$2,0,IF(E15>3.5,375*SUM($C$2:$H$2),IF(E15>3,325*SUM($C$2:$H$2),IF(E15>2.5,275*SUM($C$2:$H$2),IF(E15>2,225*SUM($C$2:$H$2),IF(E15>1.5,175*SUM($C$2:$H$2),IF(E15>1,125*SUM($C$2:$H$2),IF(E15>0,5*SUM($C$2:$H$2),0)))))))) -> 10 | J15: =(IF(B15>$N$2,0,VLOOKUP('Total income package'!$B$3,'Location specific data'!$A$3:$AO$135,33,FALSE))*$C$2)*20 -> 1400 | K15: =IF(B15>$N$2,0,VLOOKUP('Total income package'!$B$3,'Location specific data'!$A$3:$AO$135,34,FALSE))*$D$2*20 -> 0 | L15: =IF(B15>$N$2,0,VLOOKUP('Total income package'!$B$3,'Location specific data'!$A$3:$AO$135,35,FALSE))*$E$2*20 -> 0 | M15: =IF(B15>$N$2,0,VLOOKUP('Total income package'!$B$3,'Location specific data'!$A$3:$AO$135,36,FALSE))*$F$2*20 -> 0 | N15: =IF(B15>$N$2,0,VLOOKUP('Total income package'!$B$3,'Location specific data'!$A$3:$AO$135,37,FALSE))*($G$2+$H$2)*20 -> 600 | O15: =I15*SUM($C$2:$H$2) -> 20 | P15: =B15*0.05 -> 20.833333 | Q15: =I15*3 -> 30 | R15: =IF(MIN(O15,P15)<Q15,MIN(O15,P15),Q15) -> 20 | S15: =IF(AND('Total income package'!$A$8=TRUE,OR(F15="Yes",G15="Yes",H15="Yes")),SUM(J15:N15)-R15,0) -> 1980
A16: 5500 | B16: =A16/12 -> 458.33333 | C16: ='Total income package'!$D$80 -> 0 | D16: =B16+C16 -> 458.33333 | E16: =D16/$K$2 -> 0.14219235 | F16: =IF(AND(B16<$N$2,SUM($C$2:$F$2)>0),"Yes","No") -> Yes | G16: =IF(B16<$M$2,"Yes","No") -> Yes | H16: =IF(OR('TANF-VIEW'!L20>0,'TANF-VIEW'!T20>0),"Yes","No") -> Yes | I16: =IF(B16>=$N$2,0,IF(E16>3.5,375*SUM($C$2:$H$2),IF(E16>3,325*SUM($C$2:$H$2),IF(E16>2.5,275*SUM($C$2:$H$2),IF(E16>2,225*SUM($C$2:$H$2),IF(E16>1.5,175*SUM($C$2:$H$2),IF(E16>1,125*SUM($C$2:$H$2),IF(E16>0,5*SUM($C$2:$H$2),0)))))))) -> 10 | J16: =(IF(B16>$N$2,0,VLOOKUP('Total income package'!$B$3,'Location specific data'!$A$3:$AO$135,33,FALSE))*$C$2)*20 -> 1400 | K16: =IF(B16>$N$2,0,VLOOKUP('Total income package'!$B$3,'Location specific data'!$A$3:$AO$135,34,FALSE))*$D$2*20 -> 0 | L16: =IF(B16>$N$2,0,VLOOKUP('Total income package'!$B$3,'Location specific data'!$A$3:$AO$135,35,FALSE))*$E$2*20 -> 0 | M16: =IF(B16>$N$2,0,VLOOKUP('Total income package'!$B$3,'Location specific data'!$A$3:$AO$135,36,FALSE))*$F$2*20 -> 0 | N16: =IF(B16>$N$2,0,VLOOKUP('Total income package'!$B$3,'Location specific data'!$A$3:$AO$135,37,FALSE))*($G$2+$H$2)*20 -> 600 | O16: =I16*SUM($C$2:$H$2) -> 20 | P16: =B16*0.05 -> 22.916667 | Q16: =I16*3 -> 30 | R16: =IF(MIN(O16,P16)<Q16,MIN(O16,P16),Q16) -> 20 | S16: =IF(AND('Total income package'!$A$8=TRUE,OR(F16="Yes",G16="Yes",H16="Yes")),SUM(J16:N16)-R16,0) -> 1980
... A204: 99500 | B204: =A204/12 -> 8291.6667 | C204: ='Total income package'!$D$80 -> 0 | D204: =B204+C204 -> 8291.6667 | E204: =D204/$K$2 -> 2.5723888 | F204: =IF(AND(B204<$N$2,SUM($C$2:$F$2)>0),"Yes","No") -> Yes | G204: =IF(B204<$M$2,"Yes","No") -> No | H204: =IF(OR('TANF-VIEW'!L208>0,'TANF-VIEW'!T208>0),"Yes","No") -> No | I204: =IF(B204>=$N$2,0,IF(E204>3.5,375*SUM($C$2:$H$2),IF(E204>3,325*SUM($C$2:$H$2),IF(E204>2.5,275*SUM($C$2:$H$2),IF(E204>2,225*SUM($C$2:$H$2),IF(E204>1.5,175*SUM($C$2:$H$2),IF(E204>1,125*SUM($C$2:$H$2),IF(E204>0,5*SUM($C$2:$H$2),0)))))))) -> 550 | J204: =(IF(B204>$N$2,0,VLOOKUP('Total income package'!$B$3,'Location specific data'!$A$3:$AO$135,33,FALSE))*$C$2)*20 -> 1400 | K204: =IF(B204>$N$2,0,VLOOKUP('Total income package'!$B$3,'Location specific data'!$A$3:$AO$135,34,FALSE))*$D$2*20 -> 0 | L204: =IF(B204>$N$2,0,VLOOKUP('Total income package'!$B$3,'Location specific data'!$A$3:$AO$135,35,FALSE))*$E$2*20 -> 0 | M204: =IF(B204>$N$2,0,VLOOKUP('Total income package'!$B$3,'Location specific data'!$A$3:$AO$135,36,FALSE))*$F$2*20 -> 0 | N204: =IF(B204>$N$2,0,VLOOKUP('Total income package'!$B$3,'Location specific data'!$A$3:$AO$135,37,FALSE))*($G$2+$H$2)*20 -> 600 | O204: =I204*SUM($C$2:$H$2) -> 1100 | P204: =B204*0.05 -> 414.58333 | Q204: =I204*3 -> 1650 | R204: =IF(MIN(O204,P204)<Q204,MIN(O204,P204),Q204) -> 414.58333 | S204: =IF(AND('Total income package'!$A$8=TRUE,OR(F204="Yes",G204="Yes",H204="Yes")),SUM(J204:N204)-R204,0) -> 1585.4167
A205: 100000 | B205: =A205/12 -> 8333.3333 | C205: ='Total income package'!$D$80 -> 0 | D205: =B205+C205 -> 8333.3333 | E205: =D205/$K$2 -> 2.5853154 | F205: =IF(AND(B205<$N$2,SUM($C$2:$F$2)>0),"Yes","No") -> Yes | G205: =IF(B205<$M$2,"Yes","No") -> No | H205: =IF(OR('TANF-VIEW'!L209>0,'TANF-VIEW'!T209>0),"Yes","No") -> No | I205: =IF(B205>=$N$2,0,IF(E205>3.5,375*SUM($C$2:$H$2),IF(E205>3,325*SUM($C$2:$H$2),IF(E205>2.5,275*SUM($C$2:$H$2),IF(E205>2,225*SUM($C$2:$H$2),IF(E205>1.5,175*SUM($C$2:$H$2),IF(E205>1,125*SUM($C$2:$H$2),IF(E205>0,5*SUM($C$2:$H$2),0)))))))) -> 550 | J205: =(IF(B205>$N$2,0,VLOOKUP('Total income package'!$B$3,'Location specific data'!$A$3:$AO$135,33,FALSE))*$C$2)*20 -> 1400 | K205: =IF(B205>$N$2,0,VLOOKUP('Total income package'!$B$3,'Location specific data'!$A$3:$AO$135,34,FALSE))*$D$2*20 -> 0 | L205: =IF(B205>$N$2,0,VLOOKUP('Total income package'!$B$3,'Location specific data'!$A$3:$AO$135,35,FALSE))*$E$2*20 -> 0 | M205: =IF(B205>$N$2,0,VLOOKUP('Total income package'!$B$3,'Location specific data'!$A$3:$AO$135,36,FALSE))*$F$2*20 -> 0 | N205: =IF(B205>$N$2,0,VLOOKUP('Total income package'!$B$3,'Location specific data'!$A$3:$AO$135,37,FALSE))*($G$2+$H$2)*20 -> 600 | O205: =I205*SUM($C$2:$H$2) -> 1100 | P205: =B205*0.07 -> 583.33333 | Q205: =I205*3 -> 1650 | R205: =IF(MIN(O205,P205)<Q205,MIN(O205,P205),Q205) -> 583.33333 | S205: =IF(AND('Total income package'!$A$8=TRUE,OR(F205="Yes",G205="Yes",H205="Yes")),SUM(J205:N205)-R205,0) -> 1416.6667
A207: Exact income-start
B208: ='Total income package'!$B$90 -> 1423 | C208: ='Total income package'!$D$80 -> 0 | D208: =B208+C208 -> 1423 | E208: =D208/$K$2 -> 0.44146846 | F208: =IF(AND(B208<$N$2,SUM($C$2:$F$2)>0),"Yes","No") -> Yes | G208: =IF(B208<$M$2,"Yes","No") -> Yes | H208: =IF(OR('TANF-VIEW'!L212>0,'TANF-VIEW'!T212>0),"Yes","No") -> No | I208: =IF(B208>=$N$2,0,IF(E208>3.5,375*SUM($C$2:$H$2),IF(E208>3,325*SUM($C$2:$H$2),IF(E208>2.5,275*SUM($C$2:$H$2),IF(E208>2,225*SUM($C$2:$H$2),IF(E208>1.5,175*SUM($C$2:$H$2),IF(E208>1,125*SUM($C$2:$H$2),IF(E208>0,5*SUM($C$2:$H$2),0)))))))) -> 10 | J208: =(IF(B208>$N$2,0,VLOOKUP('Total income package'!$B$3,'Location specific data'!$A$3:$AO$135,33,FALSE))*$C$2)*20 -> 1400 | K208: =IF(B208>$N$2,0,VLOOKUP('Total income package'!$B$3,'Location specific data'!$A$3:$AO$135,34,FALSE))*$D$2*20 -> 0 | L208: =IF(B208>$N$2,0,VLOOKUP('Total income package'!$B$3,'Location specific data'!$A$3:$AO$135,35,FALSE))*$E$2*20 -> 0 | M208: =IF(B208>$N$2,0,VLOOKUP('Total income package'!$B$3,'Location specific data'!$A$3:$AO$135,36,FALSE))*$F$2*20 -> 0 | N208: =IF(B208>$N$2,0,VLOOKUP('Total income package'!$B$3,'Location specific data'!$A$3:$AO$135,37,FALSE))*($G$2+$H$2)*20 -> 600 | O208: =I208*SUM($C$2:$H$2) -> 20 | P208: =B208*0.05 -> 71.15 | Q208: =I208*3 -> 30 | R208: =IF(MIN(O208,P208)<Q208,MIN(O208,P208),Q208) -> 20 | S208: =IF(AND('Total income package'!$A$8=TRUE,OR(F208="Yes",G208="Yes",H208="Yes")),SUM(J208:N208)-R208,0) -> 1980
A209: Exact income-new
B210: ='Total income package'!$B$91 -> 3000 | C210: ='Total income package'!$D$80 -> 0 | D210: =B210+C210 -> 3000 | E210: =D210/$K$2 -> 0.93071355 | F210: =IF(AND(B210<$N$2,SUM($C$2:$F$2)>0),"Yes","No") -> Yes | G210: =IF(B210<$M$2,"Yes","No") -> Yes | H210: =IF(OR('TANF-VIEW'!L214>0,'TANF-VIEW'!T214>0),"Yes","No") -> No | I210: =IF(B210>=$N$2,0,IF(E210>3.5,375*SUM($C$2:$H$2),IF(E210>3,325*SUM($C$2:$H$2),IF(E210>2.5,275*SUM($C$2:$H$2),IF(E210>2,225*SUM($C$2:$H$2),IF(E210>1.5,175*SUM($C$2:$H$2),IF(E210>1,125*SUM($C$2:$H$2),IF(E210>0,5*SUM($C$2:$H$2),0)))))))) -> 10 | J210: =(IF(B210>$N$2,0,VLOOKUP('Total income package'!$B$3,'Location specific data'!$A$3:$AO$135,33,FALSE))*$C$2)*20 -> 1400 | K210: =IF(B210>$N$2,0,VLOOKUP('Total income package'!$B$3,'Location specific data'!$A$3:$AO$135,34,FALSE))*$D$2*20 -> 0 | L210: =IF(B210>$N$2,0,VLOOKUP('Total income package'!$B$3,'Location specific data'!$A$3:$AO$135,35,FALSE))*$E$2*20 -> 0 | M210: =IF(B210>$N$2,0,VLOOKUP('Total income package'!$B$3,'Location specific data'!$A$3:$AO$135,36,FALSE))*$F$2*20 -> 0 | N210: =IF(B210>$N$2,0,VLOOKUP('Total income package'!$B$3,'Location specific data'!$A$3:$AO$135,37,FALSE))*($G$2+$H$2)*20 -> 600 | O210: =I210*SUM($C$2:$H$2) -> 20 | P210: =B210*0.05 -> 150 | Q210: =I210*3 -> 30 | R210: =IF(MIN(O210,P210)<Q210,MIN(O210,P210),Q210) -> 20 | S210: =IF(AND('Total income package'!$A$8=TRUE,OR(F210="Yes",G210="Yes",H210="Yes")),SUM(J210:N210)-R210,0) -> 1980

Sheet EITC
A1: Location | B1: Number in Household | C1: Number adults | D1: Number of children | E1: Filing status | F1: AGI must be below | G1: Max credit amount | H1: Phase in | I1: Phase out | J1: Max credit starts at | K1: Phase-out starts at | M1: EITC does not count SSI/SSDI as earned income
A2: ='Total income package'!B3 -> Buckingham | B2: ='Total income package'!B32 -> 5 | C2: ='Total income package'!B30 -> 3 | D2: ='Total income package'!B31 -> 2 | E2: ='Total income package'!B72 -> Married filing jointly | F2: =IF($E$2="Married filing jointly",VLOOKUP($D$2,'EITC Rates'!$A$17:$G$24,2,FALSE),VLOOKUP($D$2,'EITC Rates'!$A$6:$G$13,2,FALSE)) -> 64430 | G2: =IF($E$2="Married filing jointly",VLOOKUP($D$2,'EITC Rates'!$A$17:$G$24,3,FALSE),VLOOKUP($D$2,'EITC Rates'!$A$6:$G$13,3,FALSE)) -> 7316 | H2: =IF($E$2="Married filing jointly",VLOOKUP($D$2,'EITC Rates'!$A$17:$G$24,4,FALSE),VLOOKUP($D$2,'EITC Rates'!$A$6:$G$13,4,FALSE)) -> 0.4 | I2: =IF($E$2="Married filing jointly",VLOOKUP($D$2,'EITC Rates'!$A$17:$G$24,5,FALSE),VLOOKUP($D$2,'EITC Rates'!$A$6:$G$13,5,FALSE)) -> 0.2106 | J2: =IF($E$2="Married filing jointly",VLOOKUP($D$2,'EITC Rates'!$A$17:$G$24,6,FALSE),VLOOKUP($D$2,'EITC Rates'!$A$6:$G$13,6,FALSE)) -> 18290 | K2: =IF($E$2="Married filing jointly",VLOOKUP($D$2,'EITC Rates'!$A$17:$G$24,7,FALSE),VLOOKUP($D$2,'EITC Rates'!$A$6:$G$13,7,FALSE)) -> 31160
A4: Annual earned income | B4: Monthly earned income | C4: Calculated Federal EITC w/ 2026 rates *Off by between $5- $10 from P596 | D4: VA EITC 20% of Federal EITC | E4: Combined Federal & VA EITC (Annual) | G4: Beginning with tax year 2025 (returns due May 2026), the refundable Virginia Earned Income Tax Credit will increase to 20% of your federal Earned Income Tax Credit.
A5: 0 | B5: =A5/12 -> 0 | C5: 0 | D5: =C5*0.2 -> 0 | E5: =IF('Total income package'!$A$10=TRUE,SUM(EITC!C5:D5),0) -> 0
A6: 500 | B6: =A6/12 -> 41.666667 | C6: =MAX(0,IF(A6>$F$2,0,IF(AND(A6<$F$2,A6>=$K$2),$G$2-((A6-$K$2-1)*$I$2),IF(AND(A6<$K$2,A6>=$J$2),$G$2,IF(A6<$J$2,A6*$H$2,0))))) -> 200 | D6: =C6*0.2 -> 40 | E6: =IF('Total income package'!$A$10=TRUE,SUM(EITC!C6:D6),0) -> 240
A7: 1000 | B7: =A7/12 -> 83.333333 | C7: =MAX(0,IF(A7>$F$2,0,IF(AND(A7<$F$2,A7>=$K$2),$G$2-((A7-$K$2-1)*$I$2),IF(AND(A7<$K$2,A7>=$J$2),$G$2,IF(A7<$J$2,A7*$H$2,0))))) -> 400 | D7: =C7*0.2 -> 80 | E7: =IF('Total income package'!$A$10=TRUE,SUM(EITC!C7:D7),0) -> 480
A8: 1500 | B8: =A8/12 -> 125 | C8: =MAX(0,IF(A8>$F$2,0,IF(AND(A8<$F$2,A8>=$K$2),$G$2-((A8-$K$2-1)*$I$2),IF(AND(A8<$K$2,A8>=$J$2),$G$2,IF(A8<$J$2,A8*$H$2,0))))) -> 600 | D8: =C8*0.2 -> 120 | E8: =IF('Total income package'!$A$10=TRUE,SUM(EITC!C8:D8),0) -> 720
A9: 2000 | B9: =A9/12 -> 166.66667 | C9: =MAX(0,IF(A9>$F$2,0,IF(AND(A9<$F$2,A9>=$K$2),$G$2-((A9-$K$2-1)*$I$2),IF(AND(A9<$K$2,A9>=$J$2),$G$2,IF(A9<$J$2,A9*$H$2,0))))) -> 800 | D9: =C9*0.2 -> 160 | E9: =IF('Total income package'!$A$10=TRUE,SUM(EITC!C9:D9),0) -> 960
A10: 2500 | B10: =A10/12 -> 208.33333 | C10: =MAX(0,IF(A10>$F$2,0,IF(AND(A10<$F$2,A10>=$K$2),$G$2-((A10-$K$2-1)*$I$2),IF(AND(A10<$K$2,A10>=$J$2),$G$2,IF(A10<$J$2,A10*$H$2,0))))) -> 1000 | D10: =C10*0.2 -> 200 | E10: =IF('Total income package'!$A$10=TRUE,SUM(EITC!C10:D10),0) -> 1200
A11: 3000 | B11: =A11/12 -> 250 | C11: =MAX(0,IF(A11>$F$2,0,IF(AND(A11<$F$2,A11>=$K$2),$G$2-((A11-$K$2-1)*$I$2),IF(AND(A11<$K$2,A11>=$J$2),$G$2,IF(A11<$J$2,A11*$H$2,0))))) -> 1200 | D11: =C11*0.2 -> 240 | E11: =IF('Total income package'!$A$10=TRUE,SUM(EITC!C11:D11),0) -> 1440
A12: 3500 | B12: =A12/12 -> 291.66667 | C12: =MAX(0,IF(A12>$F$2,0,IF(AND(A12<$F$2,A12>=$K$2),$G$2-((A12-$K$2-1)*$I$2),IF(AND(A12<$K$2,A12>=$J$2),$G$2,IF(A12<$J$2,A12*$H$2,0))))) -> 1400 | D12: =C12*0.2 -> 280 | E12: =IF('Total income package'!$A$10=TRUE,SUM(EITC!C12:D12),0) -> 1680
A13: 4000 | B13: =A13/12 -> 333.33333 | C13: =MAX(0,IF(A13>$F$2,0,IF(AND(A13<$F$2,A13>=$K$2),$G$2-((A13-$K$2-1)*$I$2),IF(AND(A13<$K$2,A13>=$J$2),$G$2,IF(A13<$J$2,A13*$H$2,0))))) -> 1600 | D13: =C13*0.2 -> 320 | E13: =IF('Total income package'!$A$10=TRUE,SUM(EITC!C13:D13),0) -> 1920
A14: 4500 | B14: =A14/12 -> 375 | C14: =MAX(0,IF(A14>$F$2,0,IF(AND(A14<$F$2,A14>=$K$2),$G$2-((A14-$K$2-1)*$I$2),IF(AND(A14<$K$2,A14>=$J$2),$G$2,IF(A14<$J$2,A14*$H$2,0))))) -> 1800 | D14: =C14*0.2 -> 360 | E14: =IF('Total income package'!$A$10=TRUE,SUM(EITC!C14:D14),0) -> 2160
A15: 5000 | B15: =A15/12 -> 416.66667 | C15: =MAX(0,IF(A15>$F$2,0,IF(AND(A15<$F$2,A15>=$K$2),$G$2-((A15-$K$2-1)*$I$2),IF(AND(A15<$K$2,A15>=$J$2),$G$2,IF(A15<$J$2,A15*$H$2,0))))) -> 2000 | D15: =C15*0.2 -> 400 | E15: =IF('Total income package'!$A$10=TRUE,SUM(EITC!C15:D15),0) -> 2400
A16: 5500 | B16: =A16/12 -> 458.33333 | C16: =MAX(0,IF(A16>$F$2,0,IF(AND(A16<$F$2,A16>=$K$2),$G$2-((A16-$K$2-1)*$I$2),IF(AND(A16<$K$2,A16>=$J$2),$G$2,IF(A16<$J$2,A16*$H$2,0))))) -> 2200 | D16: =C16*0.2 -> 440 | E16: =IF('Total income package'!$A$10=TRUE,SUM(EITC!C16:D16),0) -> 2640
A17: 6000 | B17: =A17/12 -> 500 | C17: =MAX(0,IF(A17>$F$2,0,IF(AND(A17<$F$2,A17>=$K$2),$G$2-((A17-$K$2-1)*$I$2),IF(AND(A17<$K$2,A17>=$J$2),$G$2,IF(A17<$J$2,A17*$H$2,0))))) -> 2400 | D17: =C17*0.2 -> 480 | E17: =IF('Total income package'!$A$10=TRUE,SUM(EITC!C17:D17),0) -> 2880
... A205: 100000 | B205: =A205/12 -> 8333.3333 | C205: =MAX(0,IF(A205>$F$2,0,IF(AND(A205<$F$2,A205>=$K$2),$G$2-((A205-$K$2-1)*$I$2),IF(AND(A205<$K$2,A205>=$J$2),$G$2,IF(A205<$J$2,A205*$H$2,0))))) -> 0 | D205: =C205*0.2 -> 0 | E205: =IF('Total income package'!$A$10=TRUE,SUM(EITC!C205:D205),0) -> 0
A207: Exact income-start | E207: Fed & VA EITC | K207: =1770/12 -> 147.5
A208: =B208*12 -> 17076 | B208: ='Total income package'!$B$90 -> 1423 | C208: =MAX(0,IF(A208>$F$2,0,IF(AND(A208<$F$2,A208>=$K$2),$G$2-((A208-$K$2-1)*$I$2),IF(AND(A208<$K$2,A208>=$J$2),$G$2,IF(A208<$J$2,A208*$H$2,0))))) -> 6830.4 | D208: =C208*0.15 -> 1024.56 | E208: =IF('Total income package'!$A$10=TRUE,C208+D208,0) -> 7854.96 | G208: =C208/12 -> 569.2 | H208: =E208/12 -> 654.58
A209: Exact income-new
A210: =B210*12 -> 36000 | B210: ='Total income package'!$B$91 -> 3000 | C210: =MAX(0,IF(A210>$F$2,0,IF(AND(A210<$F$2,A210>=$K$2),$G$2-((A210-$K$2-1)*$I$2),IF(AND(A210<$K$2,A210>=$J$2),$G$2,IF(A210<$J$2,A210*$H$2,0))))) -> 6296.9066 | D210: =C210*0.15 -> 944.53599 | E210: =IF('Total income package'!$A$10=TRUE,C210+D210,0) -> 7241.4426

Sheet Health insurance subsidy 
A1: Location | B1: Number in Household | C1: Number of adults | D1: Number of children | F1: =K2*1.38 -> 4448.2 | M1: Bottom | N1: Top | O1: Initial % | P1: Final %
A2: ='Total income package'!B3 -> Buckingham | B2: ='Total income package'!B32 -> 5 | C2: ='Total income package'!B30 -> 3 | D2: ='Total income package'!B31 -> 2 | J2: FPL 2024 Monthly | K2: =VLOOKUP(B2,'Program specific data'!A6:D13,3,FALSE) -> 3223.3333 | L2: <150 FPL | M2: 0 | N2: =K2*1.49 -> 4802.7667 | O2: 0 | P2: 0
A3: Age of adult(s): | C3: Cost of SLCSP | E3: (from PRD Technical Manual) | L3: 150-199 | M3: =K2*1.5 -> 4835 | N3: =K2*1.99 -> 6414.4333 | O3: 0 | P3: 0.02
A4: Adult 1 | B4: ='Total income package'!B37 -> 34 | C4: =IFERROR(VLOOKUP($A$2,'SLCSP premiums'!$A$4:$AV$137,HLOOKUP(B4,'SLCSP premiums'!$B$2:$AV$3,2,FALSE),FALSE),0) -> 469 | E4: Formula used= Individual contribution to premium = | L4: 200-249 | M4: =K2*2 -> 6446.6667 | N4: =K2*2.49 -> 8026.1 | O4: 0.02 | P4: 0.04
A5: Adult 2 | B5: ='Total income package'!B38 -> 28 | C5: =IFERROR(VLOOKUP($A$2,'SLCSP premiums'!$A$4:$AV$137,HLOOKUP(B5,'SLCSP premiums'!$B$2:$AV$3,2,FALSE),FALSE),0) -> 420 | E5: MAGI * (𝐼𝑛𝑖𝑡𝑖𝑎𝑙 % +(𝑀𝐴𝐺𝐼−𝑀𝑎𝑥 𝑝𝑟𝑒𝑣𝑖𝑜𝑢𝑠 𝐹𝑃𝐿 𝑡𝑜𝑝)∗ | L5: 250-299 | M5: =K2*2.5 -> 8058.3333 | N5: =K2*2.99 -> 9637.7667 | O5: 0.04 | P5: 0.06
A6: Adult 3 | B6: ='Total income package'!B39 -> 80 | C6: =IFERROR(VLOOKUP($A$2,'SLCSP premiums'!$A$4:$AV$137,HLOOKUP(B6,'SLCSP premiums'!$B$2:$AV$3,2,FALSE),FALSE),0) -> 0 | L6: 300-399 | M6: =K2*3 -> 9670 | N6: =K2*3.99 -> 12861.1 | O6: 0.06 | P6: 0.085
A7: Adult 4 | B7: ='Total income package'!B40 -> 0 | C7: =IFERROR(VLOOKUP($A$2,'SLCSP premiums'!$A$4:$AV$137,HLOOKUP(B7,'SLCSP premiums'!$B$2:$AV$3,2,FALSE),FALSE),0) -> 0 | L7: 400+ | M7: =K2*4 -> 12893.333 | N7: =500000/12 -> 41666.667 | O7: 0.085 | P7: 0.085
A8: Adult 5 | B8: ='Total income package'!B41 -> 0 | C8: =IFERROR(VLOOKUP($A$2,'SLCSP premiums'!$A$4:$AV$137,HLOOKUP(B8,'SLCSP premiums'!$B$2:$AV$3,2,FALSE),FALSE),0) -> 0
A9: Adult 6 | B9: ='Total income package'!B42 -> 0 | C9: =IFERROR(VLOOKUP($A$2,'SLCSP premiums'!$A$4:$AV$137,HLOOKUP(B9,'SLCSP premiums'!$B$2:$AV$3,2,FALSE),FALSE),0) -> 0
A10: Adult 7 | B10: ='Total income package'!B43 -> 0 | C10: =IFERROR(VLOOKUP($A$2,'SLCSP premiums'!$A$4:$AV$137,HLOOKUP(B10,'SLCSP premiums'!$B$2:$AV$3,2,FALSE),FALSE),0) -> 0
A11: Adult 8 | B11: ='Total income package'!B44 -> 0 | C11: =IFERROR(VLOOKUP($A$2,'SLCSP premiums'!$A$4:$AV$137,HLOOKUP(B11,'SLCSP premiums'!$B$2:$AV$3,2,FALSE),FALSE),0) -> 0
A12: SLCSP-adults | C12: =SUM(C4:C11) -> 889
A13: # Children | B13: =D2 -> 2 | C13: =IFERROR(VLOOKUP($A$2,'SLCSP premiums'!A4:BE137,HLOOKUP(B13,'SLCSP premiums'!$B$2:$BE$3,2,FALSE),FALSE),0) -> 375
A14: NOTE: Medicaid calculated from 2024 FPL percentage-subsidies calculated from 2024 FPL for 2025 plan year.
D15: 2024 figures used (from https://www.healthcare.gov/glossary/federal-poverty-level-fpl/) | K15: Adult only until children no longer eligible for MA
A16: Annual earned income | B16: Monthly | C16: 0.0839 | D16: % FPL | E16: Income %-initial | F16: Income%-final | G16: Bottom income of FPL range | H16: Top income of FPL range | I16: Top income previous FPL | J16: Calculated individual contribution to premium | K16: SLCSP (from https://enroll.marketplace.virginia.gov/hix/preeligibility#/) | L16: Value of Marketplace subsidy (0 if eligible for Medicaid) | M16: Figures from https://enroll.marketplace.virginia.gov to check | N16: Annual Value Marketplace subsidies | O16: Adult eligible for MA? | P16: Children eligible MA?
A17: 0 | B17: =A17/12 -> 0 | C17: =B17*0.0839 -> 0 | D17: =B17/$K$2 -> 0 | E17: =IF($D$17>3.99,0.085,IF($D$17>2.99,0.06,IF($D$17>1.99,0.02,IF($D$17>1.49,0,0)))) -> 0 | F17: =IF(D17>3.99,0.085,IF(D17>2.99,0.085,IF(D17>2.49,0.06,IF(D17>1.99,0.04,IF(D17>1.49,0.02,0))))) -> 0 | G17: =IF(D17>3.99,$M$7,IF(D17>2.99,$M$6,IF(D17>2.49,$M$5,IF(D17>1.99,$M$4,IF(D17>1.49,$M$3,0))))) -> 0 | H17: =IF(D17>3.99,$N$7,IF(D17>2.99,$N$6,IF(D17>2.49,$N$5,IF(D17>1.99,$N$4,IF(D17>1.49,$N$3,IF(D17>=0,$N$2,0)))))) -> 4802.7667 | I17: =IF(D17>3.99,$N$6,IF(D17>2.99,$N$5,IF(D17>2.49,$N$4,IF(D17>1.99,$N$3,IF(D17>1.49,$N$2,IF(D17>=0,0)))))) -> 0 | J17: =B17*(E17+(B17-I17)*(F17-E17)/(H17-I17)) -> 0 | K17: =SUM(IF(O17="Yes",0,$C$12),IF(P17="Yes",0,$C$13)) -> 0 | L17: =MAX(0,K17-J17) -> 0 | N17: =MAX(0,L17*12) -> 0 | O17: =Medicaid!G9 -> Yes | P17: =Medicaid!K9 -> Yes
A18: 500 | B18: =A18/12 -> 41.666667 | C18: =B18*0.0839 -> 3.4958333 | D18: =B18/$K$2 -> 0.012926577 | E18: =IF($D$17>3.99,0.085,IF($D$17>2.99,0.06,IF($D$17>1.99,0.02,IF($D$17>1.49,0,0)))) -> 0 | F18: =IF(D18>3.99,0.085,IF(D18>2.99,0.085,IF(D18>2.49,0.06,IF(D18>1.99,0.04,IF(D18>1.49,0.02,0))))) -> 0 | G18: =IF(D18>3.99,$M$7,IF(D18>2.99,$M$6,IF(D18>2.49,$M$5,IF(D18>1.99,$M$4,IF(D18>1.49,$M$3,0))))) -> 0 | H18: =IF(D18>3.99,$N$7,IF(D18>2.99,$N$6,IF(D18>2.49,$N$5,IF(D18>1.99,$N$4,IF(D18>1.49,$N$3,IF(D18>=0,$N$2,0)))))) -> 4802.7667 | I18: =IF(D18>3.99,$N$6,IF(D18>2.99,$N$5,IF(D18>2.49,$N$4,IF(D18>1.99,$N$3,IF(D18>1.49,$N$2,IF(D18>=0,0)))))) -> 0 | J18: =B18*(E18+(B18-I18)*(F18-E18)/(H18-I18)) -> 0 | K18: =SUM(IF(O18="Yes",0,$C$12),IF(P18="Yes",0,$C$13)) -> 0 | L18: =MAX(0,K18-J18) -> 0 | N18: =MAX(0,L18*12) -> 0 | O18: =Medicaid!G10 -> Yes | P18: =Medicaid!K10 -> Yes
A19: 1000 | B19: =A19/12 -> 83.333333 | C19: =B19*0.0839 -> 6.9916667 | D19: =B19/$K$2 -> 0.025853154 | E19: =IF(D19>3.99,0.085,IF(D19>2.99,0.06,IF(D19>1.99,0.02,IF(D19>1.49,0,0)))) -> 0 | F19: =IF(D19>3.99,0.085,IF(D19>2.99,0.085,IF(D19>2.49,0.06,IF(D19>1.99,0.04,IF(D19>1.49,0.02,0))))) -> 0 | G19: =IF(D19>3.99,$M$7,IF(D19>2.99,$M$6,IF(D19>2.49,$M$5,IF(D19>1.99,$M$4,IF(D19>1.49,$M$3,0))))) -> 0 | H19: =IF(D19>3.99,$N$7,IF(D19>2.99,$N$6,IF(D19>2.49,$N$5,IF(D19>1.99,$N$4,IF(D19>1.49,$N$3,IF(D19>=0,$N$2,0)))))) -> 4802.7667 | I19: =IF(D19>3.99,$N$6,IF(D19>2.99,$N$5,IF(D19>2.49,$N$4,IF(D19>1.99,$N$3,IF(D19>1.49,$N$2,IF(D19>=0,0)))))) -> 0 | J19: =B19*(E19+(B19-I19)*(F19-E19)/(H19-I19)) -> 0 | K19: =SUM(IF(O19="Yes",0,$C$12),IF(P19="Yes",0,$C$13)) -> 0 | L19: =MAX(0,K19-J19) -> 0 | N19: =MAX(0,L19*12) -> 0 | O19: =Medicaid!G11 -> Yes | P19: =Medicaid!K11 -> Yes
A20: 1500 | B20: =A20/12 -> 125 | C20: =B20*0.0839 -> 10.4875 | D20: =B20/$K$2 -> 0.038779731 | E20: =IF(D20>3.99,0.085,IF(D20>2.99,0.06,IF(D20>1.99,0.02,IF(D20>1.49,0,0)))) -> 0 | F20: =IF(D20>3.99,0.085,IF(D20>2.99,0.085,IF(D20>2.49,0.06,IF(D20>1.99,0.04,IF(D20>1.49,0.02,0))))) -> 0 | G20: =IF(D20>3.99,$M$7,IF(D20>2.99,$M$6,IF(D20>2.49,$M$5,IF(D20>1.99,$M$4,IF(D20>1.49,$M$3,0))))) -> 0 | H20: =IF(D20>3.99,$N$7,IF(D20>2.99,$N$6,IF(D20>2.49,$N$5,IF(D20>1.99,$N$4,IF(D20>1.49,$N$3,IF(D20>=0,$N$2,0)))))) -> 4802.7667 | I20: =IF(D20>3.99,$N$6,IF(D20>2.99,$N$5,IF(D20>2.49,$N$4,IF(D20>1.99,$N$3,IF(D20>1.49,$N$2,IF(D20>=0,0)))))) -> 0 | J20: =B20*(E20+(B20-I20)*(F20-E20)/(H20-I20)) -> 0 | K20: =SUM(IF(O20="Yes",0,$C$12),IF(P20="Yes",0,$C$13)) -> 0 | L20: =MAX(0,K20-J20) -> 0 | N20: =MAX(0,L20*12) -> 0 | O20: =Medicaid!G12 -> Yes | P20: =Medicaid!K12 -> Yes
A21: 2000 | B21: =A21/12 -> 166.66667 | C21: =B21*0.0839 -> 13.983333 | D21: =B21/$K$2 -> 0.051706308 | E21: =IF(D21>3.99,0.085,IF(D21>2.99,0.06,IF(D21>1.99,0.02,IF(D21>1.49,0,0)))) -> 0 | F21: =IF(D21>3.99,0.085,IF(D21>2.99,0.085,IF(D21>2.49,0.06,IF(D21>1.99,0.04,IF(D21>1.49,0.02,0))))) -> 0 | G21: =IF(D21>3.99,$M$7,IF(D21>2.99,$M$6,IF(D21>2.49,$M$5,IF(D21>1.99,$M$4,IF(D21>1.49,$M$3,0))))) -> 0 | H21: =IF(D21>3.99,$N$7,IF(D21>2.99,$N$6,IF(D21>2.49,$N$5,IF(D21>1.99,$N$4,IF(D21>1.49,$N$3,IF(D21>=0,$N$2,0)))))) -> 4802.7667 | I21: =IF(D21>3.99,$N$6,IF(D21>2.99,$N$5,IF(D21>2.49,$N$4,IF(D21>1.99,$N$3,IF(D21>1.49,$N$2,IF(D21>=0,0)))))) -> 0 | J21: =B21*(E21+(B21-I21)*(F21-E21)/(H21-I21)) -> 0 | K21: =SUM(IF(O21="Yes",0,$C$12),IF(P21="Yes",0,$C$13)) -> 0 | L21: =MAX(0,K21-J21) -> 0 | N21: =MAX(0,L21*12) -> 0 | O21: =Medicaid!G13 -> Yes | P21: =Medicaid!K13 -> Yes
A22: 2500 | B22: =A22/12 -> 208.33333 | C22: =B22*0.0839 -> 17.479167 | D22: =B22/$K$2 -> 0.064632885 | E22: =IF(D22>3.99,0.085,IF(D22>2.99,0.06,IF(D22>1.99,0.02,IF(D22>1.49,0,0)))) -> 0 | F22: =IF(D22>3.99,0.085,IF(D22>2.99,0.085,IF(D22>2.49,0.06,IF(D22>1.99,0.04,IF(D22>1.49,0.02,0))))) -> 0 | G22: =IF(D22>3.99,$M$7,IF(D22>2.99,$M$6,IF(D22>2.49,$M$5,IF(D22>1.99,$M$4,IF(D22>1.49,$M$3,0))))) -> 0 | H22: =IF(D22>3.99,$N$7,IF(D22>2.99,$N$6,IF(D22>2.49,$N$5,IF(D22>1.99,$N$4,IF(D22>1.49,$N$3,IF(D22>=0,$N$2,0)))))) -> 4802.7667 | I22: =IF(D22>3.99,$N$6,IF(D22>2.99,$N$5,IF(D22>2.49,$N$4,IF(D22>1.99,$N$3,IF(D22>1.49,$N$2,IF(D22>=0,0)))))) -> 0 | J22: =B22*(E22+(B22-I22)*(F22-E22)/(H22-I22)) -> 0 | K22: =SUM(IF(O22="Yes",0,$C$12),IF(P22="Yes",0,$C$13)) -> 0 | L22: =MAX(0,K22-J22) -> 0 | N22: =MAX(0,L22*12) -> 0 | O22: =Medicaid!G14 -> Yes | P22: =Medicaid!K14 -> Yes
A23: 3000 | B23: =A23/12 -> 250 | C23: =B23*0.0839 -> 20.975 | D23: =B23/$K$2 -> 0.077559462 | E23: =IF(D23>3.99,0.085,IF(D23>2.99,0.06,IF(D23>1.99,0.02,IF(D23>1.49,0,0)))) -> 0 | F23: =IF(D23>3.99,0.085,IF(D23>2.99,0.085,IF(D23>2.49,0.06,IF(D23>1.99,0.04,IF(D23>1.49,0.02,0))))) -> 0 | G23: =IF(D23>3.99,$M$7,IF(D23>2.99,$M$6,IF(D23>2.49,$M$5,IF(D23>1.99,$M$4,IF(D23>1.49,$M$3,0))))) -> 0 | H23: =IF(D23>3.99,$N$7,IF(D23>2.99,$N$6,IF(D23>2.49,$N$5,IF(D23>1.99,$N$4,IF(D23>1.49,$N$3,IF(D23>=0,$N$2,0)))))) -> 4802.7667 | I23: =IF(D23>3.99,$N$6,IF(D23>2.99,$N$5,IF(D23>2.49,$N$4,IF(D23>1.99,$N$3,IF(D23>1.49,$N$2,IF(D23>=0,0)))))) -> 0 | J23: =B23*(E23+(B23-I23)*(F23-E23)/(H23-I23)) -> 0 | K23: =SUM(IF(O23="Yes",0,$C$12),IF(P23="Yes",0,$C$13)) -> 0 | L23: =MAX(0,K23-J23) -> 0 | N23: =MAX(0,L23*12) -> 0 | O23: =Medicaid!G15 -> Yes | P23: =Medicaid!K15 -> Yes
A24: 3500 | B24: =A24/12 -> 291.66667 | C24: =B24*0.0839 -> 24.470833 | D24: =B24/$K$2 -> 0.090486039 | E24: =IF(D24>3.99,0.085,IF(D24>2.99,0.06,IF(D24>1.99,0.02,IF(D24>1.49,0,0)))) -> 0 | F24: =IF(D24>3.99,0.085,IF(D24>2.99,0.085,IF(D24>2.49,0.06,IF(D24>1.99,0.04,IF(D24>1.49,0.02,0))))) -> 0 | G24: =IF(D24>3.99,$M$7,IF(D24>2.99,$M$6,IF(D24>2.49,$M$5,IF(D24>1.99,$M$4,IF(D24>1.49,$M$3,0))))) -> 0 | H24: =IF(D24>3.99,$N$7,IF(D24>2.99,$N$6,IF(D24>2.49,$N$5,IF(D24>1.99,$N$4,IF(D24>1.49,$N$3,IF(D24>=0,$N$2,0)))))) -> 4802.7667 | I24: =IF(D24>3.99,$N$6,IF(D24>2.99,$N$5,IF(D24>2.49,$N$4,IF(D24>1.99,$N$3,IF(D24>1.49,$N$2,IF(D24>=0,0)))))) -> 0 | J24: =B24*(E24+(B24-I24)*(F24-E24)/(H24-I24)) -> 0 | K24: =SUM(IF(O24="Yes",0,$C$12),IF(P24="Yes",0,$C$13)) -> 0 | L24: =MAX(0,K24-J24) -> 0 | N24: =MAX(0,L24*12) -> 0 | O24: =Medicaid!G16 -> Yes | P24: =Medicaid!K16 -> Yes
A25: 4000 | B25: =A25/12 -> 333.33333 | C25: =B25*0.0839 -> 27.966667 | D25: =B25/$K$2 -> 0.10341262 | E25: =IF(D25>3.99,0.085,IF(D25>2.99,0.06,IF(D25>1.99,0.02,IF(D25>1.49,0,0)))) -> 0 | F25: =IF(D25>3.99,0.085,IF(D25>2.99,0.085,IF(D25>2.49,0.06,IF(D25>1.99,0.04,IF(D25>1.49,0.02,0))))) -> 0 | G25: =IF(D25>3.99,$M$7,IF(D25>2.99,$M$6,IF(D25>2.49,$M$5,IF(D25>1.99,$M$4,IF(D25>1.49,$M$3,0))))) -> 0 | H25: =IF(D25>3.99,$N$7,IF(D25>2.99,$N$6,IF(D25>2.49,$N$5,IF(D25>1.99,$N$4,IF(D25>1.49,$N$3,IF(D25>=0,$N$2,0)))))) -> 4802.7667 | I25: =IF(D25>3.99,$N$6,IF(D25>2.99,$N$5,IF(D25>2.49,$N$4,IF(D25>1.99,$N$3,IF(D25>1.49,$N$2,IF(D25>=0,0)))))) -> 0 | J25: =B25*(E25+(B25-I25)*(F25-E25)/(H25-I25)) -> 0 | K25: =SUM(IF(O25="Yes",0,$C$12),IF(P25="Yes",0,$C$13)) -> 0 | L25: =MAX(0,K25-J25) -> 0 | N25: =MAX(0,L25*12) -> 0 | O25: =Medicaid!G17 -> Yes | P25: =Medicaid!K17 -> Yes
A26: 4500 | B26: =A26/12 -> 375 | C26: =B26*0.0839 -> 31.4625 | D26: =B26/$K$2 -> 0.11633919 | E26: =IF(D26>3.99,0.085,IF(D26>2.99,0.06,IF(D26>1.99,0.02,IF(D26>1.49,0,0)))) -> 0 | F26: =IF(D26>3.99,0.085,IF(D26>2.99,0.085,IF(D26>2.49,0.06,IF(D26>1.99,0.04,IF(D26>1.49,0.02,0))))) -> 0 | G26: =IF(D26>3.99,$M$7,IF(D26>2.99,$M$6,IF(D26>2.49,$M$5,IF(D26>1.99,$M$4,IF(D26>1.49,$M$3,0))))) -> 0 | H26: =IF(D26>3.99,$N$7,IF(D26>2.99,$N$6,IF(D26>2.49,$N$5,IF(D26>1.99,$N$4,IF(D26>1.49,$N$3,IF(D26>=0,$N$2,0)))))) -> 4802.7667 | I26: =IF(D26>3.99,$N$6,IF(D26>2.99,$N$5,IF(D26>2.49,$N$4,IF(D26>1.99,$N$3,IF(D26>1.49,$N$2,IF(D26>=0,0)))))) -> 0 | J26: =B26*(E26+(B26-I26)*(F26-E26)/(H26-I26)) -> 0 | K26: =SUM(IF(O26="Yes",0,$C$12),IF(P26="Yes",0,$C$13)) -> 0 | L26: =MAX(0,K26-J26) -> 0 | N26: =MAX(0,L26*12) -> 0 | O26: =Medicaid!G18 -> Yes | P26: =Medicaid!K18 -> Yes
A27: 5000 | B27: =A27/12 -> 416.66667 | C27: =B27*0.0839 -> 34.958333 | D27: =B27/$K$2 -> 0.12926577 | E27: =IF(D27>3.99,0.085,IF(D27>2.99,0.06,IF(D27>1.99,0.02,IF(D27>1.49,0,0)))) -> 0 | F27: =IF(D27>3.99,0.085,IF(D27>2.99,0.085,IF(D27>2.49,0.06,IF(D27>1.99,0.04,IF(D27>1.49,0.02,0))))) -> 0 | G27: =IF(D27>3.99,$M$7,IF(D27>2.99,$M$6,IF(D27>2.49,$M$5,IF(D27>1.99,$M$4,IF(D27>1.49,$M$3,0))))) -> 0 | H27: =IF(D27>3.99,$N$7,IF(D27>2.99,$N$6,IF(D27>2.49,$N$5,IF(D27>1.99,$N$4,IF(D27>1.49,$N$3,IF(D27>=0,$N$2,0)))))) -> 4802.7667 | I27: =IF(D27>3.99,$N$6,IF(D27>2.99,$N$5,IF(D27>2.49,$N$4,IF(D27>1.99,$N$3,IF(D27>1.49,$N$2,IF(D27>=0,0)))))) -> 0 | J27: =B27*(E27+(B27-I27)*(F27-E27)/(H27-I27)) -> 0 | K27: =SUM(IF(O27="Yes",0,$C$12),IF(P27="Yes",0,$C$13)) -> 0 | L27: =MAX(0,K27-J27) -> 0 | N27: =MAX(0,L27*12) -> 0 | O27: =Medicaid!G19 -> Yes | P27: =Medicaid!K19 -> Yes
A28: 5500 | B28: =A28/12 -> 458.33333 | C28: =B28*0.0839 -> 38.454167 | D28: =B28/$K$2 -> 0.14219235 | E28: =IF(D28>3.99,0.085,IF(D28>2.99,0.06,IF(D28>1.99,0.02,IF(D28>1.49,0,0)))) -> 0 | F28: =IF(D28>3.99,0.085,IF(D28>2.99,0.085,IF(D28>2.49,0.06,IF(D28>1.99,0.04,IF(D28>1.49,0.02,0))))) -> 0 | G28: =IF(D28>3.99,$M$7,IF(D28>2.99,$M$6,IF(D28>2.49,$M$5,IF(D28>1.99,$M$4,IF(D28>1.49,$M$3,0))))) -> 0 | H28: =IF(D28>3.99,$N$7,IF(D28>2.99,$N$6,IF(D28>2.49,$N$5,IF(D28>1.99,$N$4,IF(D28>1.49,$N$3,IF(D28>=0,$N$2,0)))))) -> 4802.7667 | I28: =IF(D28>3.99,$N$6,IF(D28>2.99,$N$5,IF(D28>2.49,$N$4,IF(D28>1.99,$N$3,IF(D28>1.49,$N$2,IF(D28>=0,0)))))) -> 0 | J28: =B28*(E28+(B28-I28)*(F28-E28)/(H28-I28)) -> 0 | K28: =SUM(IF(O28="Yes",0,$C$12),IF(P28="Yes",0,$C$13)) -> 0 | L28: =MAX(0,K28-J28) -> 0 | N28: =MAX(0,L28*12) -> 0 | O28: =Medicaid!G20 -> Yes | P28: =Medicaid!K20 -> Yes
A29: 6000 | B29: =A29/12 -> 500 | C29: =B29*0.0839 -> 41.95 | D29: =B29/$K$2 -> 0.15511892 | E29: =IF(D29>3.99,0.085,IF(D29>2.99,0.06,IF(D29>1.99,0.02,IF(D29>1.49,0,0)))) -> 0 | F29: =IF(D29>3.99,0.085,IF(D29>2.99,0.085,IF(D29>2.49,0.06,IF(D29>1.99,0.04,IF(D29>1.49,0.02,0))))) -> 0 | G29: =IF(D29>3.99,$M$7,IF(D29>2.99,$M$6,IF(D29>2.49,$M$5,IF(D29>1.99,$M$4,IF(D29>1.49,$M$3,0))))) -> 0 | H29: =IF(D29>3.99,$N$7,IF(D29>2.99,$N$6,IF(D29>2.49,$N$5,IF(D29>1.99,$N$4,IF(D29>1.49,$N$3,IF(D29>=0,$N$2,0)))))) -> 4802.7667 | I29: =IF(D29>3.99,$N$6,IF(D29>2.99,$N$5,IF(D29>2.49,$N$4,IF(D29>1.99,$N$3,IF(D29>1.49,$N$2,IF(D29>=0,0)))))) -> 0 | J29: =B29*(E29+(B29-I29)*(F29-E29)/(H29-I29)) -> 0 | K29: =SUM(IF(O29="Yes",0,$C$12),IF(P29="Yes",0,$C$13)) -> 0 | L29: =MAX(0,K29-J29) -> 0 | N29: =MAX(0,L29*12) -> 0 | O29: =Medicaid!G21 -> Yes | P29: =Medicaid!K21 -> Yes
A30: 6500 | B30: =A30/12 -> 541.66667 | C30: =B30*0.0839 -> 45.445833 | D30: =B30/$K$2 -> 0.1680455 | E30: =IF(D30>3.99,0.085,IF(D30>2.99,0.06,IF(D30>1.99,0.02,IF(D30>1.49,0,0)))) -> 0 | F30: =IF(D30>3.99,0.085,IF(D30>2.99,0.085,IF(D30>2.49,0.06,IF(D30>1.99,0.04,IF(D30>1.49,0.02,0))))) -> 0 | G30: =IF(D30>3.99,$M$7,IF(D30>2.99,$M$6,IF(D30>2.49,$M$5,IF(D30>1.99,$M$4,IF(D30>1.49,$M$3,0))))) -> 0 | H30: =IF(D30>3.99,$N$7,IF(D30>2.99,$N$6,IF(D30>2.49,$N$5,IF(D30>1.99,$N$4,IF(D30>1.49,$N$3,IF(D30>=0,$N$2,0)))))) -> 4802.7667 | I30: =IF(D30>3.99,$N$6,IF(D30>2.99,$N$5,IF(D30>2.49,$N$4,IF(D30>1.99,$N$3,IF(D30>1.49,$N$2,IF(D30>=0,0)))))) -> 0 | J30: =B30*(E30+(B30-I30)*(F30-E30)/(H30-I30)) -> 0 | K30: =SUM(IF(O30="Yes",0,$C$12),IF(P30="Yes",0,$C$13)) -> 0 | L30: =MAX(0,K30-J30) -> 0 | N30: =MAX(0,L30*12) -> 0 | O30: =Medicaid!G22 -> Yes | P30: =Medicaid!K22 -> Yes
... A217: 100000 | B217: =A217/12 -> 8333.3333 | C217: =B217*0.0839 -> 699.16667 | D217: =B217/$K$2 -> 2.5853154 | E217: =IF(D217>3.99,0.085,IF(D217>2.99,0.06,IF(D217>1.99,0.02,IF(D217>1.49,0,0)))) -> 0.02 | F217: =IF(D217>3.99,0.085,IF(D217>2.99,0.085,IF(D217>2.49,0.06,IF(D217>1.99,0.04,IF(D217>1.49,0.02,0))))) -> 0.06 | G217: =IF(D217>3.99,$M$7,IF(D217>2.99,$M$6,IF(D217>2.49,$M$5,IF(D217>1.99,$M$4,IF(D217>1.49,$M$3,0))))) -> 8058.3333 | H217: =IF(D217>3.99,$N$7,IF(D217>2.99,$N$6,IF(D217>2.49,$N$5,IF(D217>1.99,$N$4,IF(D217>1.49,$N$3,IF(D217>=0,$N$2,0)))))) -> 9637.7667 | I217: =IF(D217>3.99,$N$6,IF(D217>2.99,$N$5,IF(D217>2.49,$N$4,IF(D217>1.99,$N$3,IF(D217>1.49,$N$2,IF(D217>=0,0)))))) -> 8026.1 | J217: =B217*(E217+(B217-I217)*(F217-E217)/(H217-I217)) -> 230.21027 | K217: =SUM(IF(O217="Yes",0,$C$12),IF(P217="Yes",0,$C$13)) -> 1264 | L217: =MAX(0,K217-J217) -> 1033.7897 | N217: =MAX(0,L217*12) -> 12405.477 | O217: =Medicaid!G209 -> No | P217: =Medicaid!K209 -> No
A219: Exact income-start
B220: ='Total income package'!$B$90 -> 1423 | C220: =B220*0.0839 -> 119.3897 | D220: =B220/$K$2 -> 0.44146846 | E220: =IF(D220>3.99,0.085,IF(D220>2.99,0.06,IF(D220>1.99,0.02,IF(D220>1.49,0,0)))) -> 0 | F220: =IF(D220>3.99,0.085,IF(D220>2.99,0.085,IF(D220>2.49,0.06,IF(D220>1.99,0.04,IF(D220>1.49,0.02,0))))) -> 0 | G220: =IF(D220>3.99,$M$7,IF(D220>2.99,$M$6,IF(D220>2.49,$M$5,IF(D220>1.99,$M$4,IF(D220>1.49,$M$3,0))))) -> 0 | H220: =IF(D220>3.99,$N$7,IF(D220>2.99,$N$6,IF(D220>2.49,$N$5,IF(D220>1.99,$N$4,IF(D220>1.49,$N$3,IF(D220>=0,$N$2,0)))))) -> 4802.7667 | I220: =IF(D220>3.99,$N$6,IF(D220>2.99,$N$5,IF(D220>2.49,$N$4,IF(D220>1.99,$N$3,IF(D220>1.49,$N$2,IF(D220>=0,0)))))) -> 0 | J220: =B220*(E220+(B220-I220)*(F220-E220)/(H220-I220)) -> 0 | K220: =$C$12 -> 889 | L220: =IF(O220="Yes",0,MAX(0,K220-J220)) -> 0 | N220: =MAX(0,L220*12) -> 0 | O220: =Medicaid!G212 -> Yes | P220: =Medicaid!K212 -> Yes
A221: Exact income-new
B222: ='Total income package'!$B$91 -> 3000 | C222: =B222*0.0839 -> 251.7 | D222: =B222/$K$2 -> 0.93071355 | E222: =IF(D222>3.99,0.085,IF(D222>2.99,0.06,IF(D222>1.99,0.02,IF(D222>1.49,0,0)))) -> 0 | F222: =IF(D222>3.99,0.085,IF(D222>2.99,0.085,IF(D222>2.49,0.06,IF(D222>1.99,0.04,IF(D222>1.49,0.02,0))))) -> 0 | G222: =IF(D222>3.99,$M$7,IF(D222>2.99,$M$6,IF(D222>2.49,$M$5,IF(D222>1.99,$M$4,IF(D222>1.49,$M$3,0))))) -> 0 | H222: =IF(D222>3.99,$N$7,IF(D222>2.99,$N$6,IF(D222>2.49,$N$5,IF(D222>1.99,$N$4,IF(D222>1.49,$N$3,IF(D222>=0,$N$2,0)))))) -> 4802.7667 | I222: =IF(D222>3.99,$N$6,IF(D222>2.99,$N$5,IF(D222>2.49,$N$4,IF(D222>1.99,$N$3,IF(D222>1.49,$N$2,IF(D222>=0,0)))))) -> 0 | J222: =B222*(E222+(B222-I222)*(F222-E222)/(H222-I222)) -> 0 | K222: =$C$12 -> 889 | L222: =IF(O222="Yes",0,MAX(0,K222-J222)) -> 0 | N222: =MAX(0,L222*12) -> 0 | O222: =Medicaid!G214 -> Yes | P222: =Medicaid!K214 -> Yes

Sheet Housing Voucher
A1: Location | B1: Number in Household | C1: Number of adults | D1: Number of dependents | E1: # of bedroom(s) adult | F1: # of bedroom(s)dependents | G1: Number of bedrooms needed (from entry on TIP tab) | H1: Elderly (62+) family member? | I1: Disabled family member-adult dependant non-elderly? | J1: Disabled family member-head of family or spouse? | K1: Disabled family member-child? (Use the $480 annual deduction) | L1: 80% area median income/month | N1: Counts social security, SSI/SSDI as income | P1: To be eligible for public housing, an applicant must have an annual income that is no more than the “Lower Income” limit for the jurisdiction.xviii The Lower Income limit is set at 80 percent of area median income, adjusted for smaller and larger families. Public Housing Occupancy Guidebook
A2: ='Total income package'!B3 -> Buckingham | B2: ='Total income package'!B32 -> 5 | C2: ='Total income package'!B30 -> 3 | D2: ='Total income package'!B31 -> 2 | E2: =ROUNDUP(C2/2,0) -> 2 | F2: =ROUNDDOWN(D2/2,0) -> 1 | G2: ='Total income package'!D13 -> 4 | H2: =COUNTIF('Total income package'!B37:B44,">61") -> 1 | I2: ='Total income package'!F59 -> 0 | J2: ='Total income package'!D59 -> 1 | L2: {=_xlfn.IFS($B$2=1,VLOOKUP('Total income package'!$B$3,'Location specific data'!$A$3:$W131,11,FALSE),$B$2=2,VLOOKUP('Total income package'!$B$3,'Location specific data'!$A$3:$W$135,12,FALSE),$B$2=3,VLOOKUP('Total income package'!$B$3,'Location specific data'!$A$3:$W$135,13,FALSE),$B$2=4,VLOOKUP('Total income package'!$B$3,'Location specific data'!$A$3:$W$135,14,FALSE),$B$2=5,VLOOKUP('Total income package'!$B$3,'Location specific data'!$A$3:$W$135,15,FALSE),$B$2=6,VLOOKUP('Total income package'!$B$3,'Location specific data'!$A$3:$W$135,16,FALSE),$B$2=7,VLOOKUP('Total income package'!$B$3,'Location specific data'!$A$3:$W$135,17,FALSE),$B$2=8,VLOOKUP('Total income package'!$B$3,'Location specific data'!$A$3:$W$135,18,FALSE))/12} -> 6075 | N2: Does not count income of children <18 years
A5: Annual earned income (gross) | B5: Monthly earned income (gross) | C5: TANF benefit or VIEW Benefit | D5: Social security income | E5: SSI/SSDI income | F5: Gross Non-excluded Income | G5: Eligible? (<80% Median income) | H5: Dependent deduction $480/dependent annual ($40/dependent per month) # children + adult disabled dependent | I5: Elderly or disabled deduction $400/family annual-one per family ($33.33/month) | J5: Adjusted Monthly Income (Gross income - deductions) | K5: 30% of Adjusted Monthly Income | L5: 10% of Monthly Gross Income | M5: Virginia Minimum Rent | N5: Largest amount to use for TTP | O5: Fair Market Rate | P5: Housing Choice Voucher Payment Standard | Q5: Voucher amount (Payment standard - TTP) If housing choice voucher selected
A6: 0 | B6: =A6/12 -> 0 | C6: =MAX('TANF-VIEW'!L9,'TANF-VIEW'!T9) -> 385 | D6: ='Total income package'!$D$80 -> 0 | E6: ='Total income package'!$H$61+'Total income package'!$F$66 -> 250 | F6: =B6+C6+D6+E6 -> 635 | G6: =IF(F6<$L$2,"Yes","No") -> Yes | H6: =40*($D$2+$I$2) -> 80 | I6: =IF($H$2+$J$2>0,33.33,0) -> 33.33 | J6: =IF(F6-H6-I6<0,0,F6-H6-I6) -> 521.67 | K6: =J6*0.3 -> 156.501 | L6: =F6*0.1 -> 63.5 | M6: 50 | N6: =MAX(K6:M6) -> 156.501 | O6: {=_xlfn.IFS($G$2=1,VLOOKUP('Total income package'!$B$3,'Location specific data'!$A$3:$W135,20,FALSE),$G$2=2,VLOOKUP('Total income package'!$B$3,'Location specific data'!$A$3:$W$135,21,FALSE),$G$2=3,VLOOKUP('Total income package'!$B$3,'Location specific data'!$A$3:$W$135,22,FALSE),$G$2=4,VLOOKUP('Total income package'!$B$3,'Location specific data'!$A$3:$W$135,23,FALSE),$G$2=5,VLOOKUP('Total income package'!$B$3,'Location specific data'!$A$3:$W$135,24,FALSE))} -> 1342 | P6: {=_xlfn.IFS($G$2=1,VLOOKUP('Total income package'!$B$3,'Location specific data'!$A$3:$AB$135,25,FALSE),$G$2=2,VLOOKUP('Total income package'!$B$3,'Location specific data'!$A$3:$AB$135,26,FALSE),$G$2=3,VLOOKUP('Total income package'!$B$3,'Location specific data'!$A$3:$AB$135,27,FALSE),$G$2=4,VLOOKUP('Total income package'!$B$3,'Location specific data'!$A$3:$AB$135,28,FALSE),$G$2=5,VLOOKUP('Total income package'!$B$3,'Location specific data'!$A$3:$AB$135,29,FALSE))} -> 1494 | Q6: =IF(AND(G6="Yes",'Total income package'!$A$14=TRUE,P6-N6>0),P6-N6,0) -> 1337.499
A7: 500 | B7: =A7/12 -> 41.666667 | C7: =MAX('TANF-VIEW'!L10,'TANF-VIEW'!T10) -> 385 | D7: ='Total income package'!$D$80 -> 0 | E7: ='Total income package'!$H$61+'Total income package'!$F$66 -> 250 | F7: =B7+C7+D7+E7 -> 676.66667 | G7: =IF(F7<$L$2,"Yes","No") -> Yes | H7: =40*($D$2+$I$2) -> 80 | I7: =IF($H$2+$I$2>0,33.33,0) -> 33.33 | J7: =IF(F7-H7-I7<0,0,F7-H7-I7) -> 563.33667 | K7: =J7*0.3 -> 169.001 | L7: =F7*0.1 -> 67.666667 | M7: 50 | N7: =MAX(K7:M7) -> 169.001 | O7: {=_xlfn.IFS($G$2=1,VLOOKUP('Total income package'!$B$3,'Location specific data'!$A$3:$W136,20,FALSE),$G$2=2,VLOOKUP('Total income package'!$B$3,'Location specific data'!$A$3:$W$135,21,FALSE),$G$2=3,VLOOKUP('Total income package'!$B$3,'Location specific data'!$A$3:$W$135,22,FALSE),$G$2=4,VLOOKUP('Total income package'!$B$3,'Location specific data'!$A$3:$W$135,23,FALSE),$G$2=5,VLOOKUP('Total income package'!$B$3,'Location specific data'!$A$3:$W$135,24,FALSE))} -> 1342 | P7: {=_xlfn.IFS($G$2=1,VLOOKUP('Total income package'!$B$3,'Location specific data'!$A$3:$AB$135,25,FALSE),$G$2=2,VLOOKUP('Total income package'!$B$3,'Location specific data'!$A$3:$AB$135,26,FALSE),$G$2=3,VLOOKUP('Total income package'!$B$3,'Location specific data'!$A$3:$AB$135,27,FALSE),$G$2=4,VLOOKUP('Total income package'!$B$3,'Location specific data'!$A$3:$AB$135,28,FALSE),$G$2=5,VLOOKUP('Total income package'!$B$3,'Location specific data'!$A$3:$AB$135,29,FALSE))} -> 1494 | Q7: =IF(AND(G7="Yes",'Total income package'!$A$14=TRUE,P7-N7>0),P7-N7,0) -> 1324.999
A8: 1000 | B8: =A8/12 -> 83.333333 | C8: =MAX('TANF-VIEW'!L11,'TANF-VIEW'!T11) -> 385 | D8: ='Total income package'!$D$80 -> 0 | E8: ='Total income package'!$H$61+'Total income package'!$F$66 -> 250 | F8: =B8+C8+D8+E8 -> 718.33333 | G8: =IF(F8<$L$2,"Yes","No") -> Yes | H8: =40*($D$2+$I$2) -> 80 | I8: =IF($H$2+$I$2>0,33.33,0) -> 33.33 | J8: =IF(F8-H8-I8<0,0,F8-H8-I8) -> 605.00333 | K8: =J8*0.3 -> 181.501 | L8: =F8*0.1 -> 71.833333 | M8: 50 | N8: =MAX(K8:M8) -> 181.501 | O8: {=_xlfn.IFS($G$2=1,VLOOKUP('Total income package'!$B$3,'Location specific data'!$A$3:$W137,20,FALSE),$G$2=2,VLOOKUP('Total income package'!$B$3,'Location specific data'!$A$3:$W$135,21,FALSE),$G$2=3,VLOOKUP('Total income package'!$B$3,'Location specific data'!$A$3:$W$135,22,FALSE),$G$2=4,VLOOKUP('Total income package'!$B$3,'Location specific data'!$A$3:$W$135,23,FALSE),$G$2=5,VLOOKUP('Total income package'!$B$3,'Location specific data'!$A$3:$W$135,24,FALSE))} -> 1342 | P8: {=_xlfn.IFS($G$2=1,VLOOKUP('Total income package'!$B$3,'Location specific data'!$A$3:$AB$135,25,FALSE),$G$2=2,VLOOKUP('Total income package'!$B$3,'Location specific data'!$A$3:$AB$135,26,FALSE),$G$2=3,VLOOKUP('Total income package'!$B$3,'Location specific data'!$A$3:$AB$135,27,FALSE),$G$2=4,VLOOKUP('Total income package'!$B$3,'Location specific data'!$A$3:$AB$135,28,FALSE),$G$2=5,VLOOKUP('Total income package'!$B$3,'Location specific data'!$A$3:$AB$135,29,FALSE))} -> 1494 | Q8: =IF(AND(G8="Yes",'Total income package'!$A$14=TRUE,P8-N8>0),P8-N8,0) -> 1312.499
A9: 1500 | B9: =A9/12 -> 125 | C9: =MAX('TANF-VIEW'!L12,'TANF-VIEW'!T12) -> 385 | D9: ='Total income package'!$D$80 -> 0 | E9: ='Total income package'!$H$61+'Total income package'!$F$66 -> 250 | F9: =B9+C9+D9+E9 -> 760 | G9: =IF(F9<$L$2,"Yes","No") -> Yes | H9: =40*($D$2+$I$2) -> 80 | I9: =IF($H$2+$I$2>0,33.33,0) -> 33.33 | J9: =IF(F9-H9-I9<0,0,F9-H9-I9) -> 646.67 | K9: =J9*0.3 -> 194.001 | L9: =F9*0.1 -> 76 | M9: 50 | N9: =MAX(K9:M9) -> 194.001 | O9: {=_xlfn.IFS($G$2=1,VLOOKUP('Total income package'!$B$3,'Location specific data'!$A$3:$W138,20,FALSE),$G$2=2,VLOOKUP('Total income package'!$B$3,'Location specific data'!$A$3:$W$135,21,FALSE),$G$2=3,VLOOKUP('Total income package'!$B$3,'Location specific data'!$A$3:$W$135,22,FALSE),$G$2=4,VLOOKUP('Total income package'!$B$3,'Location specific data'!$A$3:$W$135,23,FALSE),$G$2=5,VLOOKUP('Total income package'!$B$3,'Location specific data'!$A$3:$W$135,24,FALSE))} -> 1342 | P9: {=_xlfn.IFS($G$2=1,VLOOKUP('Total income package'!$B$3,'Location specific data'!$A$3:$AB$135,25,FALSE),$G$2=2,VLOOKUP('Total income package'!$B$3,'Location specific data'!$A$3:$AB$135,26,FALSE),$G$2=3,VLOOKUP('Total income package'!$B$3,'Location specific data'!$A$3:$AB$135,27,FALSE),$G$2=4,VLOOKUP('Total income package'!$B$3,'Location specific data'!$A$3:$AB$135,28,FALSE),$G$2=5,VLOOKUP('Total income package'!$B$3,'Location specific data'!$A$3:$AB$135,29,FALSE))} -> 1494 | Q9: =IF(AND(G9="Yes",'Total income package'!$A$14=TRUE,P9-N9>0),P9-N9,0) -> 1299.999
A10: 2000 | B10: =A10/12 -> 166.66667 | C10: =MAX('TANF-VIEW'!L13,'TANF-VIEW'!T13) -> 385 | D10: ='Total income package'!$D$80 -> 0 | E10: ='Total income package'!$H$61+'Total income package'!$F$66 -> 250 | F10: =B10+C10+D10+E10 -> 801.66667 | G10: =IF(F10<$L$2,"Yes","No") -> Yes | H10: =40*($D$2+$I$2) -> 80 | I10: =IF($H$2+$I$2>0,33.33,0) -> 33.33 | J10: =IF(F10-H10-I10<0,0,F10-H10-I10) -> 688.33667 | K10: =J10*0.3 -> 206.501 | L10: =F10*0.1 -> 80.166667 | M10: 50 | N10: =MAX(K10:M10) -> 206.501 | O10: {=_xlfn.IFS($G$2=1,VLOOKUP('Total income package'!$B$3,'Location specific data'!$A$3:$W139,20,FALSE),$G$2=2,VLOOKUP('Total income package'!$B$3,'Location specific data'!$A$3:$W$135,21,FALSE),$G$2=3,VLOOKUP('Total income package'!$B$3,'Location specific data'!$A$3:$W$135,22,FALSE),$G$2=4,VLOOKUP('Total income package'!$B$3,'Location specific data'!$A$3:$W$135,23,FALSE),$G$2=5,VLOOKUP('Total income package'!$B$3,'Location specific data'!$A$3:$W$135,24,FALSE))} -> 1342 | P10: {=_xlfn.IFS($G$2=1,VLOOKUP('Total income package'!$B$3,'Location specific data'!$A$3:$AB$135,25,FALSE),$G$2=2,VLOOKUP('Total income package'!$B$3,'Location specific data'!$A$3:$AB$135,26,FALSE),$G$2=3,VLOOKUP('Total income package'!$B$3,'Location specific data'!$A$3:$AB$135,27,FALSE),$G$2=4,VLOOKUP('Total income package'!$B$3,'Location specific data'!$A$3:$AB$135,28,FALSE),$G$2=5,VLOOKUP('Total income package'!$B$3,'Location specific data'!$A$3:$AB$135,29,FALSE))} -> 1494 | Q10: =IF(AND(G10="Yes",'Total income package'!$A$14=TRUE,P10-N10>0),P10-N10,0) -> 1287.499
A11: 2500 | B11: =A11/12 -> 208.33333 | C11: =MAX('TANF-VIEW'!L14,'TANF-VIEW'!T14) -> 385 | D11: ='Total income package'!$D$80 -> 0 | E11: ='Total income package'!$H$61+'Total income package'!$F$66 -> 250 | F11: =B11+C11+D11+E11 -> 843.33333 | G11: =IF(F11<$L$2,"Yes","No") -> Yes | H11: =40*($D$2+$I$2) -> 80 | I11: =IF($H$2+$I$2>0,33.33,0) -> 33.33 | J11: =IF(F11-H11-I11<0,0,F11-H11-I11) -> 730.00333 | K11: =J11*0.3 -> 219.001 | L11: =F11*0.1 -> 84.333333 | M11: 50 | N11: =MAX(K11:M11) -> 219.001 | O11: {=_xlfn.IFS($G$2=1,VLOOKUP('Total income package'!$B$3,'Location specific data'!$A$3:$W140,20,FALSE),$G$2=2,VLOOKUP('Total income package'!$B$3,'Location specific data'!$A$3:$W$135,21,FALSE),$G$2=3,VLOOKUP('Total income package'!$B$3,'Location specific data'!$A$3:$W$135,22,FALSE),$G$2=4,VLOOKUP('Total income package'!$B$3,'Location specific data'!$A$3:$W$135,23,FALSE),$G$2=5,VLOOKUP('Total income package'!$B$3,'Location specific data'!$A$3:$W$135,24,FALSE))} -> 1342 | P11: {=_xlfn.IFS($G$2=1,VLOOKUP('Total income package'!$B$3,'Location specific data'!$A$3:$AB$135,25,FALSE),$G$2=2,VLOOKUP('Total income package'!$B$3,'Location specific data'!$A$3:$AB$135,26,FALSE),$G$2=3,VLOOKUP('Total income package'!$B$3,'Location specific data'!$A$3:$AB$135,27,FALSE),$G$2=4,VLOOKUP('Total income package'!$B$3,'Location specific data'!$A$3:$AB$135,28,FALSE),$G$2=5,VLOOKUP('Total income package'!$B$3,'Location specific data'!$A$3:$AB$135,29,FALSE))} -> 1494 | Q11: =IF(AND(G11="Yes",'Total income package'!$A$14=TRUE,P11-N11>0),P11-N11,0) -> 1274.999
A12: 3000 | B12: =A12/12 -> 250 | C12: =MAX('TANF-VIEW'!L15,'TANF-VIEW'!T15) -> 352.2 | D12: ='Total income package'!$D$80 -> 0 | E12: ='Total income package'!$H$61+'Total income package'!$F$66 -> 250 | F12: =B12+C12+D12+E12 -> 852.2 | G12: =IF(F12<$L$2,"Yes","No") -> Yes | H12: =40*($D$2+$I$2) -> 80 | I12: =IF($H$2+$I$2>0,33.33,0) -> 33.33 | J12: =IF(F12-H12-I12<0,0,F12-H12-I12) -> 738.87 | K12: =J12*0.3 -> 221.661 | L12: =F12*0.1 -> 85.22 | M12: 50 | N12: =MAX(K12:M12) -> 221.661 | O12: {=_xlfn.IFS($G$2=1,VLOOKUP('Total income package'!$B$3,'Location specific data'!$A$3:$W141,20,FALSE),$G$2=2,VLOOKUP('Total income package'!$B$3,'Location specific data'!$A$3:$W$135,21,FALSE),$G$2=3,VLOOKUP('Total income package'!$B$3,'Location specific data'!$A$3:$W$135,22,FALSE),$G$2=4,VLOOKUP('Total income package'!$B$3,'Location specific data'!$A$3:$W$135,23,FALSE),$G$2=5,VLOOKUP('Total income package'!$B$3,'Location specific data'!$A$3:$W$135,24,FALSE))} -> 1342 | P12: {=_xlfn.IFS($G$2=1,VLOOKUP('Total income package'!$B$3,'Location specific data'!$A$3:$AB$135,25,FALSE),$G$2=2,VLOOKUP('Total income package'!$B$3,'Location specific data'!$A$3:$AB$135,26,FALSE),$G$2=3,VLOOKUP('Total income package'!$B$3,'Location specific data'!$A$3:$AB$135,27,FALSE),$G$2=4,VLOOKUP('Total income package'!$B$3,'Location specific data'!$A$3:$AB$135,28,FALSE),$G$2=5,VLOOKUP('Total income package'!$B$3,'Location specific data'!$A$3:$AB$135,29,FALSE))} -> 1494 | Q12: =IF(AND(G12="Yes",'Total income package'!$A$14=TRUE,P12-N12>0),P12-N12,0) -> 1272.339
A13: 3500 | B13: =A13/12 -> 291.66667 | C13: =MAX('TANF-VIEW'!L16,'TANF-VIEW'!T16) -> 318.86667 | D13: ='Total income package'!$D$80 -> 0 | E13: ='Total income package'!$H$61+'Total income package'!$F$66 -> 250 | F13: =B13+C13+D13+E13 -> 860.53333 | G13: =IF(F13<$L$2,"Yes","No") -> Yes | H13: =40*($D$2+$I$2) -> 80 | I13: =IF($H$2+$I$2>0,33.33,0) -> 33.33 | J13: =IF(F13-H13-I13<0,0,F13-H13-I13) -> 747.20333 | K13: =J13*0.3 -> 224.161 | L13: =F13*0.1 -> 86.053333 | M13: 50 | N13: =MAX(K13:M13) -> 224.161 | O13: {=_xlfn.IFS($G$2=1,VLOOKUP('Total income package'!$B$3,'Location specific data'!$A$3:$W142,20,FALSE),$G$2=2,VLOOKUP('Total income package'!$B$3,'Location specific data'!$A$3:$W$135,21,FALSE),$G$2=3,VLOOKUP('Total income package'!$B$3,'Location specific data'!$A$3:$W$135,22,FALSE),$G$2=4,VLOOKUP('Total income package'!$B$3,'Location specific data'!$A$3:$W$135,23,FALSE),$G$2=5,VLOOKUP('Total income package'!$B$3,'Location specific data'!$A$3:$W$135,24,FALSE))} -> 1342 | P13: {=_xlfn.IFS($G$2=1,VLOOKUP('Total income package'!$B$3,'Location specific data'!$A$3:$AB$135,25,FALSE),$G$2=2,VLOOKUP('Total income package'!$B$3,'Location specific data'!$A$3:$AB$135,26,FALSE),$G$2=3,VLOOKUP('Total income package'!$B$3,'Location specific data'!$A$3:$AB$135,27,FALSE),$G$2=4,VLOOKUP('Total income package'!$B$3,'Location specific data'!$A$3:$AB$135,28,FALSE),$G$2=5,VLOOKUP('Total income package'!$B$3,'Location specific data'!$A$3:$AB$135,29,FALSE))} -> 1494 | Q13: =IF(AND(G13="Yes",'Total income package'!$A$14=TRUE,P13-N13>0),P13-N13,0) -> 1269.839
A14: 4000 | B14: =A14/12 -> 333.33333 | C14: =MAX('TANF-VIEW'!L17,'TANF-VIEW'!T17) -> 285.53333 | D14: ='Total income package'!$D$80 -> 0 | E14: ='Total income package'!$H$61+'Total income package'!$F$66 -> 250 | F14: =B14+C14+D14+E14 -> 868.86667 | G14: =IF(F14<$L$2,"Yes","No") -> Yes | H14: =40*($D$2+$I$2) -> 80 | I14: =IF($H$2+$I$2>0,33.33,0) -> 33.33 | J14: =IF(F14-H14-I14<0,0,F14-H14-I14) -> 755.53667 | K14: =J14*0.3 -> 226.661 | L14: =F14*0.1 -> 86.886667 | M14: 50 | N14: =MAX(K14:M14) -> 226.661 | O14: {=_xlfn.IFS($G$2=1,VLOOKUP('Total income package'!$B$3,'Location specific data'!$A$3:$W143,20,FALSE),$G$2=2,VLOOKUP('Total income package'!$B$3,'Location specific data'!$A$3:$W$135,21,FALSE),$G$2=3,VLOOKUP('Total income package'!$B$3,'Location specific data'!$A$3:$W$135,22,FALSE),$G$2=4,VLOOKUP('Total income package'!$B$3,'Location specific data'!$A$3:$W$135,23,FALSE),$G$2=5,VLOOKUP('Total income package'!$B$3,'Location specific data'!$A$3:$W$135,24,FALSE))} -> 1342 | P14: {=_xlfn.IFS($G$2=1,VLOOKUP('Total income package'!$B$3,'Location specific data'!$A$3:$AB$135,25,FALSE),$G$2=2,VLOOKUP('Total income package'!$B$3,'Location specific data'!$A$3:$AB$135,26,FALSE),$G$2=3,VLOOKUP('Total income package'!$B$3,'Location specific data'!$A$3:$AB$135,27,FALSE),$G$2=4,VLOOKUP('Total income package'!$B$3,'Location specific data'!$A$3:$AB$135,28,FALSE),$G$2=5,VLOOKUP('Total income package'!$B$3,'Location specific data'!$A$3:$AB$135,29,FALSE))} -> 1494 | Q14: =IF(AND(G14="Yes",'Total income package'!$A$14=TRUE,P14-N14>0),P14-N14,0) -> 1267.339
A15: 4500 | B15: =A15/12 -> 375 | C15: =MAX('TANF-VIEW'!L18,'TANF-VIEW'!T18) -> 252.2 | D15: ='Total income package'!$D$80 -> 0 | E15: ='Total income package'!$H$61+'Total income package'!$F$66 -> 250 | F15: =B15+C15+D15+E15 -> 877.2 | G15: =IF(F15<$L$2,"Yes","No") -> Yes | H15: =40*($D$2+$I$2) -> 80 | I15: =IF($H$2+$I$2>0,33.33,0) -> 33.33 | J15: =IF(F15-H15-I15<0,0,F15-H15-I15) -> 763.87 | K15: =J15*0.3 -> 229.161 | L15: =F15*0.1 -> 87.72 | M15: 50 | N15: =MAX(K15:M15) -> 229.161 | O15: {=_xlfn.IFS($G$2=1,VLOOKUP('Total income package'!$B$3,'Location specific data'!$A$3:$W144,20,FALSE),$G$2=2,VLOOKUP('Total income package'!$B$3,'Location specific data'!$A$3:$W$135,21,FALSE),$G$2=3,VLOOKUP('Total income package'!$B$3,'Location specific data'!$A$3:$W$135,22,FALSE),$G$2=4,VLOOKUP('Total income package'!$B$3,'Location specific data'!$A$3:$W$135,23,FALSE),$G$2=5,VLOOKUP('Total income package'!$B$3,'Location specific data'!$A$3:$W$135,24,FALSE))} -> 1342 | P15: {=_xlfn.IFS($G$2=1,VLOOKUP('Total income package'!$B$3,'Location specific data'!$A$3:$AB$135,25,FALSE),$G$2=2,VLOOKUP('Total income package'!$B$3,'Location specific data'!$A$3:$AB$135,26,FALSE),$G$2=3,VLOOKUP('Total income package'!$B$3,'Location specific data'!$A$3:$AB$135,27,FALSE),$G$2=4,VLOOKUP('Total income package'!$B$3,'Location specific data'!$A$3:$AB$135,28,FALSE),$G$2=5,VLOOKUP('Total income package'!$B$3,'Location specific data'!$A$3:$AB$135,29,FALSE))} -> 1494 | Q15: =IF(AND(G15="Yes",'Total income package'!$A$14=TRUE,P15-N15>0),P15-N15,0) -> 1264.839
A16: 5000 | B16: =A16/12 -> 416.66667 | C16: =MAX('TANF-VIEW'!L19,'TANF-VIEW'!T19) -> 218.86667 | D16: ='Total income package'!$D$80 -> 0 | E16: ='Total income package'!$H$61+'Total income package'!$F$66 -> 250 | F16: =B16+C16+D16+E16 -> 885.53333 | G16: =IF(F16<$L$2,"Yes","No") -> Yes | H16: =40*($D$2+$I$2) -> 80 | I16: =IF($H$2+$I$2>0,33.33,0) -> 33.33 | J16: =IF(F16-H16-I16<0,0,F16-H16-I16) -> 772.20333 | K16: =J16*0.3 -> 231.661 | L16: =F16*0.1 -> 88.553333 | M16: 50 | N16: =MAX(K16:M16) -> 231.661 | O16: {=_xlfn.IFS($G$2=1,VLOOKUP('Total income package'!$B$3,'Location specific data'!$A$3:$W145,20,FALSE),$G$2=2,VLOOKUP('Total income package'!$B$3,'Location specific data'!$A$3:$W$135,21,FALSE),$G$2=3,VLOOKUP('Total income package'!$B$3,'Location specific data'!$A$3:$W$135,22,FALSE),$G$2=4,VLOOKUP('Total income package'!$B$3,'Location specific data'!$A$3:$W$135,23,FALSE),$G$2=5,VLOOKUP('Total income package'!$B$3,'Location specific data'!$A$3:$W$135,24,FALSE))} -> 1342 | P16: {=_xlfn.IFS($G$2=1,VLOOKUP('Total income package'!$B$3,'Location specific data'!$A$3:$AB$135,25,FALSE),$G$2=2,VLOOKUP('Total income package'!$B$3,'Location specific data'!$A$3:$AB$135,26,FALSE),$G$2=3,VLOOKUP('Total income package'!$B$3,'Location specific data'!$A$3:$AB$135,27,FALSE),$G$2=4,VLOOKUP('Total income package'!$B$3,'Location specific data'!$A$3:$AB$135,28,FALSE),$G$2=5,VLOOKUP('Total income package'!$B$3,'Location specific data'!$A$3:$AB$135,29,FALSE))} -> 1494 | Q16: =IF(AND(G16="Yes",'Total income package'!$A$14=TRUE,P16-N16>0),P16-N16,0) -> 1262.339
A17: 5500 | B17: =A17/12 -> 458.33333 | C17: =MAX('TANF-VIEW'!L20,'TANF-VIEW'!T20) -> 185.53333 | D17: ='Total income package'!$D$80 -> 0 | E17: ='Total income package'!$H$61+'Total income package'!$F$66 -> 250 | F17: =B17+C17+D17+E17 -> 893.86667 | G17: =IF(F17<$L$2,"Yes","No") -> Yes | H17: =40*($D$2+$I$2) -> 80 | I17: =IF($H$2+$I$2>0,33.33,0) -> 33.33 | J17: =IF(F17-H17-I17<0,0,F17-H17-I17) -> 780.53667 | K17: =J17*0.3 -> 234.161 | L17: =F17*0.1 -> 89.386667 | M17: 50 | N17: =MAX(K17:M17) -> 234.161 | O17: {=_xlfn.IFS($G$2=1,VLOOKUP('Total income package'!$B$3,'Location specific data'!$A$3:$W146,20,FALSE),$G$2=2,VLOOKUP('Total income package'!$B$3,'Location specific data'!$A$3:$W$135,21,FALSE),$G$2=3,VLOOKUP('Total income package'!$B$3,'Location specific data'!$A$3:$W$135,22,FALSE),$G$2=4,VLOOKUP('Total income package'!$B$3,'Location specific data'!$A$3:$W$135,23,FALSE),$G$2=5,VLOOKUP('Total income package'!$B$3,'Location specific data'!$A$3:$W$135,24,FALSE))} -> 1342 | P17: {=_xlfn.IFS($G$2=1,VLOOKUP('Total income package'!$B$3,'Location specific data'!$A$3:$AB$135,25,FALSE),$G$2=2,VLOOKUP('Total income package'!$B$3,'Location specific data'!$A$3:$AB$135,26,FALSE),$G$2=3,VLOOKUP('Total income package'!$B$3,'Location specific data'!$A$3:$AB$135,27,FALSE),$G$2=4,VLOOKUP('Total income package'!$B$3,'Location specific data'!$A$3:$AB$135,28,FALSE),$G$2=5,VLOOKUP('Total income package'!$B$3,'Location specific data'!$A$3:$AB$135,29,FALSE))} -> 1494 | Q17: =IF(AND(G17="Yes",'Total income package'!$A$14=TRUE,P17-N17>0),P17-N17,0) -> 1259.839
A18: 6000 | B18: =A18/12 -> 500 | C18: =MAX('TANF-VIEW'!L21,'TANF-VIEW'!T21) -> 152.2 | D18: ='Total income package'!$D$80 -> 0 | E18: ='Total income package'!$H$61+'Total income package'!$F$66 -> 250 | F18: =B18+C18+D18+E18 -> 902.2 | G18: =IF(F18<$L$2,"Yes","No") -> Yes | H18: =40*($D$2+$I$2) -> 80 | I18: =IF($H$2+$I$2>0,33.33,0) -> 33.33 | J18: =IF(F18-H18-I18<0,0,F18-H18-I18) -> 788.87 | K18: =J18*0.3 -> 236.661 | L18: =F18*0.1 -> 90.22 | M18: 50 | N18: =MAX(K18:M18) -> 236.661 | O18: {=_xlfn.IFS($G$2=1,VLOOKUP('Total income package'!$B$3,'Location specific data'!$A$3:$W147,20,FALSE),$G$2=2,VLOOKUP('Total income package'!$B$3,'Location specific data'!$A$3:$W$135,21,FALSE),$G$2=3,VLOOKUP('Total income package'!$B$3,'Location specific data'!$A$3:$W$135,22,FALSE),$G$2=4,VLOOKUP('Total income package'!$B$3,'Location specific data'!$A$3:$W$135,23,FALSE),$G$2=5,VLOOKUP('Total income package'!$B$3,'Location specific data'!$A$3:$W$135,24,FALSE))} -> 1342 | P18: {=_xlfn.IFS($G$2=1,VLOOKUP('Total income package'!$B$3,'Location specific data'!$A$3:$AB$135,25,FALSE),$G$2=2,VLOOKUP('Total income package'!$B$3,'Location specific data'!$A$3:$AB$135,26,FALSE),$G$2=3,VLOOKUP('Total income package'!$B$3,'Location specific data'!$A$3:$AB$135,27,FALSE),$G$2=4,VLOOKUP('Total income package'!$B$3,'Location specific data'!$A$3:$AB$135,28,FALSE),$G$2=5,VLOOKUP('Total income package'!$B$3,'Location specific data'!$A$3:$AB$135,29,FALSE))} -> 1494 | Q18: =IF(AND(G18="Yes",'Total income package'!$A$14=TRUE,P18-N18>0),P18-N18,0) -> 1257.339
... A206: 100000 | B206: =A206/12 -> 8333.3333 | C206: =MAX('TANF-VIEW'!L209,'TANF-VIEW'!T209) -> 0 | D206: ='Total income package'!$D$80 -> 0 | E206: ='Total income package'!$H$61+'Total income package'!$F$66 -> 250 | F206: =B206+C206+D206+E206 -> 8583.3333 | G206: =IF(F206<$L$2,"Yes","No") -> No | H206: =40*($D$2+$I$2) -> 80 | I206: =IF($H$2+$I$2>0,33.33,0) -> 33.33 | J206: =IF(F206-H206-I206<0,0,F206-H206-I206) -> 8470.0033 | K206: =J206*0.3 -> 2541.001 | L206: =F206*0.1 -> 858.33333 | M206: 50 | N206: =MAX(K206:M206) -> 2541.001 | O206: {=_xlfn.IFS($G$2=1,VLOOKUP('Total income package'!$B$3,'Location specific data'!$A$3:$W335,20,FALSE),$G$2=2,VLOOKUP('Total income package'!$B$3,'Location specific data'!$A$3:$W$135,21,FALSE),$G$2=3,VLOOKUP('Total income package'!$B$3,'Location specific data'!$A$3:$W$135,22,FALSE),$G$2=4,VLOOKUP('Total income package'!$B$3,'Location specific data'!$A$3:$W$135,23,FALSE),$G$2=5,VLOOKUP('Total income package'!$B$3,'Location specific data'!$A$3:$W$135,24,FALSE))} -> 1342 | P206: {=_xlfn.IFS($G$2=1,VLOOKUP('Total income package'!$B$3,'Location specific data'!$A$3:$AB$135,25,FALSE),$G$2=2,VLOOKUP('Total income package'!$B$3,'Location specific data'!$A$3:$AB$135,26,FALSE),$G$2=3,VLOOKUP('Total income package'!$B$3,'Location specific data'!$A$3:$AB$135,27,FALSE),$G$2=4,VLOOKUP('Total income package'!$B$3,'Location specific data'!$A$3:$AB$135,28,FALSE),$G$2=5,VLOOKUP('Total income package'!$B$3,'Location specific data'!$A$3:$AB$135,29,FALSE))} -> 1494 | Q206: =IF(AND(G206="Yes",'Total income package'!$A$14=TRUE,P206-N206>0),P206-N206,0) -> 0
A208: Exact income-start
B209: ='Total income package'!B90 -> 1423 | C209: =MAX('TANF-VIEW'!L212,'TANF-VIEW'!T212) -> 0 | D209: ='Total income package'!$D$80 -> 0 | E209: ='Total income package'!$H$61+'Total income package'!$F$66 -> 250 | F209: =B209+C209+D209+E209 -> 1673 | G209: =IF(F209<$L$2,"Yes","No") -> Yes | H209: =40*($D$2+$I$2) -> 80 | I209: =IF($H$2+$I$2>0,33.33,0) -> 33.33 | J209: =IF(F209-H209-I209<0,0,F209-H209-I209) -> 1559.67 | K209: =J209*0.3 -> 467.901 | L209: =F209*0.1 -> 167.3 | M209: 50 | N209: =MAX(K209:M209) -> 467.901 | O209: {=_xlfn.IFS($G$2=1,VLOOKUP('Total income package'!$B$3,'Location specific data'!$A$3:$W338,20,FALSE),$G$2=2,VLOOKUP('Total income package'!$B$3,'Location specific data'!$A$3:$W$135,21,FALSE),$G$2=3,VLOOKUP('Total income package'!$B$3,'Location specific data'!$A$3:$W$135,22,FALSE),$G$2=4,VLOOKUP('Total income package'!$B$3,'Location specific data'!$A$3:$W$135,23,FALSE),$G$2=5,VLOOKUP('Total income package'!$B$3,'Location specific data'!$A$3:$W$135,24,FALSE))} -> 1342 | P209: {=_xlfn.IFS($G$2=1,VLOOKUP('Total income package'!$B$3,'Location specific data'!$A$3:$AB$135,25,FALSE),$G$2=2,VLOOKUP('Total income package'!$B$3,'Location specific data'!$A$3:$AB$135,26,FALSE),$G$2=3,VLOOKUP('Total income package'!$B$3,'Location specific data'!$A$3:$AB$135,27,FALSE),$G$2=4,VLOOKUP('Total income package'!$B$3,'Location specific data'!$A$3:$AB$135,28,FALSE),$G$2=5,VLOOKUP('Total income package'!$B$3,'Location specific data'!$A$3:$AB$135,29,FALSE))} -> 1494 | Q209: =IF(AND(G209="Yes",'Total income package'!$A$14=TRUE,P209-N209>0),P209-N209,0) -> 1026.099
A210: Exact income-new | C210: ``
B211: ='Total income package'!B91 -> 3000 | C211: =MAX('TANF-VIEW'!L214,'TANF-VIEW'!T214) -> 0 | D211: ='Total income package'!$D$80 -> 0 | E211: ='Total income package'!$H$61+'Total income package'!$F$66 -> 250 | F211: =B211+C211+D211+E211 -> 3250 | G211: =IF(F211<$L$2,"Yes","No") -> Yes | H211: =40*($D$2+$I$2) -> 80 | I211: =IF($H$2+$I$2>0,33.33,0) -> 33.33 | J211: =IF(F211-H211-I211<0,0,F211-H211-I211) -> 3136.67 | K211: =J211*0.3 -> 941.001 | L211: =F211*0.1 -> 325 | M211: 50 | N211: =MAX(K211:M211) -> 941.001 | O211: {=_xlfn.IFS($G$2=1,VLOOKUP('Total income package'!$B$3,'Location specific data'!$A$3:$W340,20,FALSE),$G$2=2,VLOOKUP('Total income package'!$B$3,'Location specific data'!$A$3:$W$135,21,FALSE),$G$2=3,VLOOKUP('Total income package'!$B$3,'Location specific data'!$A$3:$W$135,22,FALSE),$G$2=4,VLOOKUP('Total income package'!$B$3,'Location specific data'!$A$3:$W$135,23,FALSE),$G$2=5,VLOOKUP('Total income package'!$B$3,'Location specific data'!$A$3:$W$135,24,FALSE))} -> 1342 | P211: {=_xlfn.IFS($G$2=1,VLOOKUP('Total income package'!$B$3,'Location specific data'!$A$3:$AB$135,25,FALSE),$G$2=2,VLOOKUP('Total income package'!$B$3,'Location specific data'!$A$3:$AB$135,26,FALSE),$G$2=3,VLOOKUP('Total income package'!$B$3,'Location specific data'!$A$3:$AB$135,27,FALSE),$G$2=4,VLOOKUP('Total income package'!$B$3,'Location specific data'!$A$3:$AB$135,28,FALSE),$G$2=5,VLOOKUP('Total income package'!$B$3,'Location specific data'!$A$3:$AB$135,29,FALSE))} -> 1494 | Q211: =IF(AND(G211="Yes",'Total income package'!$A$14=TRUE,P211-N211>0),P211-N211,0) -> 552.999

Sheet Medicaid
A1: Location | B1: Number in Household | C1: Number of adults | D1: How many adults >65 years | E1: How many adults gtting SSI | F1: Number of children | G1: Number of disabled children getting SSI | H1: 5% FPL | I1: LIFC Eligible Limit | J1: MAGI Adult 133% FPL | K1: 143% FPL | L1: 200% FPL | M1: Adults-non-expansion, non-disabled, <65, no disabilities | P1: Child Medicaid spending | R1: Aged, blind, disabled (ABD) are considered Medically Needy If get SSI and meet Medicaid resource requirements
A2: ='Total income package'!B3 -> Buckingham | B2: ='Total income package'!B32 -> 5 | C2: ='Total income package'!B30 -> 3 | D2: =COUNTIF('Total income package'!B37:B44,">64") -> 1 | E2: ='Total income package'!F61 -> 1 | F2: ='Total income package'!B31 -> 2 | G2: ='Total income package'!D66 -> 1 | H2: =VLOOKUP(Medicaid!B2,'Program specific data'!A5:J13,7,FALSE) -> 162 | I2: =IF(A3=1,VLOOKUP(B2,'Program specific data'!A124:D131,2),IF(A3=2,VLOOKUP(B2,'Program specific data'!A124:D131,3),VLOOKUP(B2,'Program specific data'!A124:D131,4))) -> 896 | J2: =VLOOKUP(B2,'Program specific data'!A5:N13,6,FALSE) -> 4288 | K2: =VLOOKUP(B2,'Program specific data'!A5:M13,11,FALSE) -> 4610 | L2: =VLOOKUP(B2,'Program specific data'!A5:N13,13,FALSE) -> 6275 | M2: =C2*'Program specific data'!C148 -> 1551.75 | P2: =F2*'Program specific data'!C152 -> 637 | R2: MAGI not used for SSI recipients, ABDs
A3: =VLOOKUP('Total income package'!B3,'Location specific data'!A3:AL135,38,FALSE) -> 1 | D3: Number of Mdicaid eligible adults | E3: Number of adults NOT getting SSI
D4: =C2-D2 -> 2 | E4: =C2-E2 -> 2
D5: Number of Mdicaid eligible aged adults
A8: Annual earned income | B8: Monthly earned income | C8: Social security income | D8: Gross HH income | E8: HH Income Monthly earned income - 5% FPL disregard | F8: Adult - Eligible? (LIFC) Must have children in household | G8: MAGI adult 138% FPL (133% + 5%) (No children) | H8: Receiving SSI (categorically needy) | I8: Non-MAGI adult (ABD or receiving SSI) | J8: Child <19 eligible <148%? (143% + 5%) | K8: FAMIS eligible? 205% FPL (200% FPL + 5%) | L8: Adult - Medicaid Value (Monthly) | M8: Child - Medicaid Value (Monthly) | N8: Total Medicaid Value
A9: 0 | B9: =A9/12 -> 0 | C9: ='Total income package'!$D$80 -> 0 | D9: =B9+C9 -> 0 | E9: =IF(D9-$H$2<0,0,D9-$H$2) -> 0 | F9: =IF(E9<$I$2,"Yes","No") -> Yes | G9: =IF(E9<$J$2,"Yes","No") -> Yes | I9: =IF($E$2>0,"Yes","No") -> Yes | J9: =IF(E9<$K$2,"Yes","No") -> Yes | K9: =IF(E9<$L$2,"Yes","No") -> Yes | L9: =IF(AND('Total income package'!$A$16=TRUE,E9<$J$2),$M$2,0) -> 1551.75 | M9: =IF(AND('Total income package'!$A$16=TRUE,E9<$L$2),$P$2,0) -> 637 | N9: =L9+M9 -> 2188.75
A10: 500 | B10: =A10/12 -> 41.666667 | C10: ='Total income package'!$D$80 -> 0 | D10: =B10+C10 -> 41.666667 | E10: =IF(D10-$H$2<0,0,D10-$H$2) -> 0 | F10: =IF(E10<$I$2,"Yes","No") -> Yes | G10: =IF(E10<$J$2,"Yes","No") -> Yes | I10: =IF($E$2>0,"Yes","No") -> Yes | J10: =IF(E10<$K$2,"Yes","No") -> Yes | K10: =IF(E10<$L$2,"Yes","No") -> Yes | L10: =IF(AND('Total income package'!$A$16=TRUE,E10<$J$2),$M$2,0) -> 1551.75 | M10: =IF(AND('Total income package'!$A$16=TRUE,E10<$L$2),$P$2,0) -> 637 | N10: =L10+M10 -> 2188.75
A11: 1000 | B11: =A11/12 -> 83.333333 | C11: ='Total income package'!$D$80 -> 0 | D11: =B11+C11 -> 83.333333 | E11: =IF(D11-$H$2<0,0,D11-$H$2) -> 0 | F11: =IF(E11<$I$2,"Yes","No") -> Yes | G11: =IF(E11<$J$2,"Yes","No") -> Yes | I11: =IF($E$2>0,"Yes","No") -> Yes | J11: =IF(E11<$K$2,"Yes","No") -> Yes | K11: =IF(E11<$L$2,"Yes","No") -> Yes | L11: =IF(AND('Total income package'!$A$16=TRUE,E11<$J$2),$M$2,0) -> 1551.75 | M11: =IF(AND('Total income package'!$A$16=TRUE,E11<$L$2),$P$2,0) -> 637 | N11: =L11+M11 -> 2188.75
A12: 1500 | B12: =A12/12 -> 125 | C12: ='Total income package'!$D$80 -> 0 | D12: =B12+C12 -> 125 | E12: =IF(D12-$H$2<0,0,D12-$H$2) -> 0 | F12: =IF(E12<$I$2,"Yes","No") -> Yes | G12: =IF(E12<$J$2,"Yes","No") -> Yes | I12: =IF($E$2>0,"Yes","No") -> Yes | J12: =IF(E12<$K$2,"Yes","No") -> Yes | K12: =IF(E12<$L$2,"Yes","No") -> Yes | L12: =IF(AND('Total income package'!$A$16=TRUE,E12<$J$2),$M$2,0) -> 1551.75 | M12: =IF(AND('Total income package'!$A$16=TRUE,E12<$L$2),$P$2,0) -> 637 | N12: =L12+M12 -> 2188.75
A13: 2000 | B13: =A13/12 -> 166.66667 | C13: ='Total income package'!$D$80 -> 0 | D13: =B13+C13 -> 166.66667 | E13: =IF(D13-$H$2<0,0,D13-$H$2) -> 4.6666667 | F13: =IF(E13<$I$2,"Yes","No") -> Yes | G13: =IF(E13<$J$2,"Yes","No") -> Yes | I13: =IF($E$2>0,"Yes","No") -> Yes | J13: =IF(E13<$K$2,"Yes","No") -> Yes | K13: =IF(E13<$L$2,"Yes","No") -> Yes | L13: =IF(AND('Total income package'!$A$16=TRUE,E13<$J$2),$M$2,0) -> 1551.75 | M13: =IF(AND('Total income package'!$A$16=TRUE,E13<$L$2),$P$2,0) -> 637 | N13: =L13+M13 -> 2188.75
A14: 2500 | B14: =A14/12 -> 208.33333 | C14: ='Total income package'!$D$80 -> 0 | D14: =B14+C14 -> 208.33333 | E14: =IF(D14-$H$2<0,0,D14-$H$2) -> 46.333333 | F14: =IF(E14<$I$2,"Yes","No") -> Yes | G14: =IF(E14<$J$2,"Yes","No") -> Yes | I14: =IF($E$2>0,"Yes","No") -> Yes | J14: =IF(E14<$K$2,"Yes","No") -> Yes | K14: =IF(E14<$L$2,"Yes","No") -> Yes | L14: =IF(AND('Total income package'!$A$16=TRUE,E14<$J$2),$M$2,0) -> 1551.75 | M14: =IF(AND('Total income package'!$A$16=TRUE,E14<$L$2),$P$2,0) -> 637 | N14: =L14+M14 -> 2188.75
A15: 3000 | B15: =A15/12 -> 250 | C15: ='Total income package'!$D$80 -> 0 | D15: =B15+C15 -> 250 | E15: =IF(D15-$H$2<0,0,D15-$H$2) -> 88 | F15: =IF(E15<$I$2,"Yes","No") -> Yes | G15: =IF(E15<$J$2,"Yes","No") -> Yes | I15: =IF($E$2>0,"Yes","No") -> Yes | J15: =IF(E15<$K$2,"Yes","No") -> Yes | K15: =IF(E15<$L$2,"Yes","No") -> Yes | L15: =IF(AND('Total income package'!$A$16=TRUE,E15<$J$2),$M$2,0) -> 1551.75 | M15: =IF(AND('Total income package'!$A$16=TRUE,E15<$L$2),$P$2,0) -> 637 | N15: =L15+M15 -> 2188.75
A16: 3500 | B16: =A16/12 -> 291.66667 | C16: ='Total income package'!$D$80 -> 0 | D16: =B16+C16 -> 291.66667 | E16: =IF(D16-$H$2<0,0,D16-$H$2) -> 129.66667 | F16: =IF(E16<$I$2,"Yes","No") -> Yes | G16: =IF(E16<$J$2,"Yes","No") -> Yes | I16: =IF($E$2>0,"Yes","No") -> Yes | J16: =IF(E16<$K$2,"Yes","No") -> Yes | K16: =IF(E16<$L$2,"Yes","No") -> Yes | L16: =IF(AND('Total income package'!$A$16=TRUE,E16<$J$2),$M$2,0) -> 1551.75 | M16: =IF(AND('Total income package'!$A$16=TRUE,E16<$L$2),$P$2,0) -> 637 | N16: =L16+M16 -> 2188.75
A17: 4000 | B17: =A17/12 -> 333.33333 | C17: ='Total income package'!$D$80 -> 0 | D17: =B17+C17 -> 333.33333 | E17: =IF(D17-$H$2<0,0,D17-$H$2) -> 171.33333 | F17: =IF(E17<$I$2,"Yes","No") -> Yes | G17: =IF(E17<$J$2,"Yes","No") -> Yes | I17: =IF($E$2>0,"Yes","No") -> Yes | J17: =IF(E17<$K$2,"Yes","No") -> Yes | K17: =IF(E17<$L$2,"Yes","No") -> Yes | L17: =IF(AND('Total income package'!$A$16=TRUE,E17<$J$2),$M$2,0) -> 1551.75 | M17: =IF(AND('Total income package'!$A$16=TRUE,E17<$L$2),$P$2,0) -> 637 | N17: =L17+M17 -> 2188.75
A18: 4500 | B18: =A18/12 -> 375 | C18: ='Total income package'!$D$80 -> 0 | D18: =B18+C18 -> 375 | E18: =IF(D18-$H$2<0,0,D18-$H$2) -> 213 | F18: =IF(E18<$I$2,"Yes","No") -> Yes | G18: =IF(E18<$J$2,"Yes","No") -> Yes | I18: =IF($E$2>0,"Yes","No") -> Yes | J18: =IF(E18<$K$2,"Yes","No") -> Yes | K18: =IF(E18<$L$2,"Yes","No") -> Yes | L18: =IF(AND('Total income package'!$A$16=TRUE,E18<$J$2),$M$2,0) -> 1551.75 | M18: =IF(AND('Total income package'!$A$16=TRUE,E18<$L$2),$P$2,0) -> 637 | N18: =L18+M18 -> 2188.75
A19: 5000 | B19: =A19/12 -> 416.66667 | C19: ='Total income package'!$D$80 -> 0 | D19: =B19+C19 -> 416.66667 | E19: =IF(D19-$H$2<0,0,D19-$H$2) -> 254.66667 | F19: =IF(E19<$I$2,"Yes","No") -> Yes | G19: =IF(E19<$J$2,"Yes","No") -> Yes | I19: =IF($E$2>0,"Yes","No") -> Yes | J19: =IF(E19<$K$2,"Yes","No") -> Yes | K19: =IF(E19<$L$2,"Yes","No") -> Yes | L19: =IF(AND('Total income package'!$A$16=TRUE,E19<$J$2),$M$2,0) -> 1551.75 | M19: =IF(AND('Total income package'!$A$16=TRUE,E19<$L$2),$P$2,0) -> 637 | N19: =L19+M19 -> 2188.75
A20: 5500 | B20: =A20/12 -> 458.33333 | C20: ='Total income package'!$D$80 -> 0 | D20: =B20+C20 -> 458.33333 | E20: =IF(D20-$H$2<0,0,D20-$H$2) -> 296.33333 | F20: =IF(E20<$I$2,"Yes","No") -> Yes | G20: =IF(E20<$J$2,"Yes","No") -> Yes | I20: =IF($E$2>0,"Yes","No") -> Yes | J20: =IF(E20<$K$2,"Yes","No") -> Yes | K20: =IF(E20<$L$2,"Yes","No") -> Yes | L20: =IF(AND('Total income package'!$A$16=TRUE,E20<$J$2),$M$2,0) -> 1551.75 | M20: =IF(AND('Total income package'!$A$16=TRUE,E20<$L$2),$P$2,0) -> 637 | N20: =L20+M20 -> 2188.75
... A209: 100000 | B209: =A209/12 -> 8333.3333 | C209: ='Total income package'!$D$80 -> 0 | D209: =B209+C209 -> 8333.3333 | E209: =IF(D209-$H$2<0,0,D209-$H$2) -> 8171.3333 | F209: =IF(E209<$I$2,"Yes","No") -> No | G209: =IF(E209<$J$2,"Yes","No") -> No | I209: =IF($E$2>0,"Yes","No") -> Yes | J209: =IF(E209<$K$2,"Yes","No") -> No | K209: =IF(E209<$L$2,"Yes","No") -> No | L209: =IF(AND('Total income package'!$A$16=TRUE,E209<$J$2),$M$2,0) -> 0 | M209: =IF(AND('Total income package'!$A$16=TRUE,E209<$L$2),$P$2,0) -> 0 | N209: =L209+M209 -> 0
C210: ='Total income package'!$D$80 -> 0 | D210: =B210+C210 -> 0 | I210: =IF($E$2>0,"Yes","No") -> Yes
A211: Exact income-start | C211: ='Total income package'!$D$80 -> 0 | D211: =B211+C211 -> 0 | I211: =IF($E$2>0,"Yes","No") -> Yes
B212: ='Total income package'!$B$90 -> 1423 | C212: ='Total income package'!$D$80 -> 0 | D212: =B212+C212 -> 1423 | E212: =IF(B212-$H$2<0,0,B212-$H$2) -> 1261 | F212: =IF(E212<$I$2,"Yes","No") -> No | G212: =IF(E212<$J$2,"Yes","No") -> Yes | I212: =IF($E$2>0,"Yes","No") -> Yes | J212: =IF(E212<$K$2,"Yes","No") -> Yes | K212: =IF(E212<$L$2,"Yes","No") -> Yes | L212: =IF(AND('Total income package'!$A$16=TRUE,E212<$J$2),$M$2,0) -> 1551.75 | M212: =IF(AND('Total income package'!$A$16=TRUE,E212<$L$2),$P$2,0) -> 637 | N212: =L212+M212 -> 2188.75
A213: Exact income-new | C213: ='Total income package'!$D$80 -> 0 | D213: =B213+C213 -> 0 | I213: =IF($E$2>0,"Yes","No") -> Yes
B214: ='Total income package'!$B$91 -> 3000 | C214: ='Total income package'!$D$80 -> 0 | D214: =B214+C214 -> 3000 | E214: =IF(B214-$H$2<0,0,B214-$H$2) -> 2838 | F214: =IF(E214<$I$2,"Yes","No") -> No | G214: =IF(E214<$J$2,"Yes","No") -> Yes | I214: =IF($E$2>0,"Yes","No") -> Yes | J214: =IF(E214<$K$2,"Yes","No") -> Yes | K214: =IF(E214<$L$2,"Yes","No") -> Yes | L214: =IF(AND('Total income package'!$A$16=TRUE,E214<$J$2),$M$2,0) -> 1551.75 | M214: =IF(AND('Total income package'!$A$16=TRUE,E214<$L$2),$P$2,0) -> 637 | N214: =L214+M214 -> 2188.75

Sheet SNAP
B1: Location | C1: Number in Household | D1: Any elderly (60+)? | E1: Any disabled? (Adult or child) | F1: Non-categorically eligible 130% FPL | G1: Broad-based catagorical eligibility <200% FPL | H1: Standard deduction | I1: Utility (standard or entry) | J1: At least one elderly (60+) or disabled 100% FPL (Net income limit) | K1: Max Snap Benefit | L1: Max shelter deduction | Q1: =869-139 -> 730
B2: ='Total income package'!B3 -> Buckingham | C2: ='Total income package'!B32 -> 5 | D2: =COUNTIF('Total income package'!B37:B44,">59") -> 1 | E2: ='Total income package'!F59+'Total income package'!D59+'Total income package'!H59+'Total income package'!D64 -> 3 | F2: =VLOOKUP($C$2,'Program specific data'!$A$85:$D$92,3) -> 4079.4 | G2: =VLOOKUP($C$2,'Program specific data'!$A$85:$D$92,2) -> 6276 | H2: =VLOOKUP($C$2,'Program specific data'!$A$72:$B$79,2) -> 261 | I2: =IF('Total income package'!B70="Standard Utility Allowance (SUA)",VLOOKUP($C$2,'Program specific data'!$A$72:$C$79,3),'Total income package'!D70) -> 700 | J2: =VLOOKUP($C$2,'Program specific data'!$A$85:$D$92,4) -> 3138 | K2: =VLOOKUP($C$2,'Program specific data'!A97:B104,2) -> 1183 | L2: 712
B5: Annual earned income (gross) | C5: TANF or TANF/VIEW | D5: Monthly earned income | E5: Social Security income | F5: SSI income | G5: Monthly income (gross) | H5: Eligible for SNAP Gross income 200% | I5: Earned income deduction | J5: Standard deduction | K5: Adjusted monthly net income | L5: Utiility costs (SUA or manually entered costs) | M5: Qualified shelter costs | N5: Total shelter costs | O5: Eligible by Elderly/disabled 100% FPL | P5: 1/2 adjusted net income | Q5: Shelter deduction (If > 1/2 adjusted net income not >$712) | R5: Shelter deduction if elderly/disabled (full amount over 1/2 adjusted net income | S5: Adjusted monthly (including applicable shelter deduction) | T5: 30% of adjusted net monthly | U5: Monthly SNAP Benefit | V5: Monthly SNAP Benefit (Using minimum benefit amount)
B6: 0 | C6: =MAX('TANF-VIEW'!L9,'TANF-VIEW'!T9) -> 385 | D6: =B6/12 -> 0 | E6: ='Total income package'!$D$80 -> 0 | F6: ='Total income package'!$H$61+'Total income package'!$F$66 -> 250 | G6: =D6+C6+E6+F6 -> 635 | H6: =IF(G6<$G$2,"Yes","No") -> Yes | I6: =D6*0.2 -> 0 | J6: =$H$2 -> 261 | K6: =IF(G6-I6-J6>0,G6-I6-J6,0) -> 374 | L6: =$I$2 -> 700 | M6: ='Total income package'!$B$69 -> 500 | N6: =L6+M6 -> 1200 | O6: =IF(AND($D$2+$E$2>0,K6<$J$2),"Yes","No") -> Yes | P6: =K6/2 -> 187 | Q6: =IF(AND(D$2+$E$2=0,N6<$L$2,N6-P6>0),N6-P6,IF(AND(D$2+$E$2=0,N6>$L$2),$L$2,0)) -> 0 | R6: =IF(AND(D$2+$E$2>0,N6-SNAP!P6>0),N6-SNAP!P6,0) -> 1013 | S6: =IF(AND($D$2+$E$2>0,K6-R6>0),K6-R6,IF(AND($D$2+$E$2=0,K6-Q6>0),K6-Q6,0)) -> 0 | T6: =S6*0.3 -> 0 | U6: =IF(AND('Total income package'!$A$18=TRUE,OR(H6="Yes",O6="Yes"),G6<$G$2,$K$2-T6>10),ROUNDDOWN($K$2-T6,0),0) -> 1183 | V6: =IF(AND(C2<3,U6>10,U6<24),24,U6) -> 1183
B7: 500 | C7: =MAX('TANF-VIEW'!L10,'TANF-VIEW'!T10) -> 385 | D7: =B7/12 -> 41.666667 | E7: ='Total income package'!$D$80 -> 0 | F7: ='Total income package'!$H$61+'Total income package'!$F$66 -> 250 | G7: =D7+C7+E7+F7 -> 676.66667 | H7: =IF(G7<$G$2,"Yes","No") -> Yes | I7: =D7*0.2 -> 8.3333333 | J7: =$H$2 -> 261 | K7: =IF(G7-I7-J7>0,G7-I7-J7,0) -> 407.33333 | L7: =$I$2 -> 700 | M7: ='Total income package'!$B$69 -> 500 | N7: =L7+M7 -> 1200 | O7: =IF(AND($D$2+$E$2>0,K7<$J$2),"Yes","No") -> Yes | P7: =K7/2 -> 203.66667 | Q7: =IF(AND(D$2+$E$2=0,N7<$L$2,N7-P7>0),N7-P7,IF(AND(D$2+$E$2=0,N7>$L$2),$L$2,0)) -> 0 | R7: =IF(AND(D$2+$E$2>0,N7-SNAP!P7>0),N7-SNAP!P7,0) -> 996.33333 | S7: =IF(AND($D$2+$E$2>0,K7-R7>0),K7-R7,IF(AND($D$2+$E$2=0,K7-Q7>0),K7-Q7,0)) -> 0 | T7: =S7*0.3 -> 0 | U7: =IF(AND('Total income package'!$A$18=TRUE,OR(H7="Yes",O7="Yes"),G7<$G$2,$K$2-T7>10),ROUNDDOWN($K$2-T7,0),0) -> 1183 | V7: =IF(AND(C3<3,U7>10,U7<24),24,U7) -> 1183
B8: 1000 | C8: =MAX('TANF-VIEW'!L11,'TANF-VIEW'!T11) -> 385 | D8: =B8/12 -> 83.333333 | E8: ='Total income package'!$D$80 -> 0 | F8: ='Total income package'!$H$61+'Total income package'!$F$66 -> 250 | G8: =D8+C8+E8+F8 -> 718.33333 | H8: =IF(G8<$G$2,"Yes","No") -> Yes | I8: =D8*0.2 -> 16.666667 | J8: =$H$2 -> 261 | K8: =IF(G8-I8-J8>0,G8-I8-J8,0) -> 440.66667 | L8: =$I$2 -> 700 | M8: ='Total income package'!$B$69 -> 500 | N8: =L8+M8 -> 1200 | O8: =IF(AND($D$2+$E$2>0,K8<$J$2),"Yes","No") -> Yes | P8: =K8/2 -> 220.33333 | Q8: =IF(AND(D$2+$E$2=0,N8<$L$2,N8-P8>0),N8-P8,IF(AND(D$2+$E$2=0,N8>$L$2),$L$2,0)) -> 0 | R8: =IF(AND(D$2+$E$2>0,N8-SNAP!P8>0),N8-SNAP!P8,0) -> 979.66667 | S8: =IF(AND($D$2+$E$2>0,K8-R8>0),K8-R8,IF(AND($D$2+$E$2=0,K8-Q8>0),K8-Q8,0)) -> 0 | T8: =S8*0.3 -> 0 | U8: =IF(AND('Total income package'!$A$18=TRUE,OR(H8="Yes",O8="Yes"),G8<$G$2,$K$2-T8>10),ROUNDDOWN($K$2-T8,0),0) -> 1183 | V8: =IF(AND(C4<3,U8>10,U8<24),24,U8) -> 1183
B9: 1500 | C9: =MAX('TANF-VIEW'!L12,'TANF-VIEW'!T12) -> 385 | D9: =B9/12 -> 125 | E9: ='Total income package'!$D$80 -> 0 | F9: ='Total income package'!$H$61+'Total income package'!$F$66 -> 250 | G9: =D9+C9+E9+F9 -> 760 | H9: =IF(G9<$G$2,"Yes","No") -> Yes | I9: =D9*0.2 -> 25 | J9: =$H$2 -> 261 | K9: =IF(G9-I9-J9>0,G9-I9-J9,0) -> 474 | L9: =$I$2 -> 700 | M9: ='Total income package'!$B$69 -> 500 | N9: =L9+M9 -> 1200 | O9: =IF(AND($D$2+$E$2>0,K9<$J$2),"Yes","No") -> Yes | P9: =K9/2 -> 237 | Q9: =IF(AND(D$2+$E$2=0,N9<$L$2,N9-P9>0),N9-P9,IF(AND(D$2+$E$2=0,N9>$L$2),$L$2,0)) -> 0 | R9: =IF(AND(D$2+$E$2>0,N9-SNAP!P9>0),N9-SNAP!P9,0) -> 963 | S9: =IF(AND($D$2+$E$2>0,K9-R9>0),K9-R9,IF(AND($D$2+$E$2=0,K9-Q9>0),K9-Q9,0)) -> 0 | T9: =S9*0.3 -> 0 | U9: =IF(AND('Total income package'!$A$18=TRUE,OR(H9="Yes",O9="Yes"),G9<$G$2,$K$2-T9>10),ROUNDDOWN($K$2-T9,0),0) -> 1183 | V9: =IF(AND(C5<3,U9>10,U9<24),24,U9) -> 1183
B10: 2000 | C10: =MAX('TANF-VIEW'!L13,'TANF-VIEW'!T13) -> 385 | D10: =B10/12 -> 166.66667 | E10: ='Total income package'!$D$80 -> 0 | F10: ='Total income package'!$H$61+'Total income package'!$F$66 -> 250 | G10: =D10+C10+E10+F10 -> 801.66667 | H10: =IF(G10<$G$2,"Yes","No") -> Yes | I10: =D10*0.2 -> 33.333333 | J10: =$H$2 -> 261 | K10: =IF(G10-I10-J10>0,G10-I10-J10,0) -> 507.33333 | L10: =$I$2 -> 700 | M10: ='Total income package'!$B$69 -> 500 | N10: =L10+M10 -> 1200 | O10: =IF(AND($D$2+$E$2>0,K10<$J$2),"Yes","No") -> Yes | P10: =K10/2 -> 253.66667 | Q10: =IF(AND(D$2+$E$2=0,N10<$L$2,N10-P10>0),N10-P10,IF(AND(D$2+$E$2=0,N10>$L$2),$L$2,0)) -> 0 | R10: =IF(AND(D$2+$E$2>0,N10-SNAP!P10>0),N10-SNAP!P10,0) -> 946.33333 | S10: =IF(AND($D$2+$E$2>0,K10-R10>0),K10-R10,IF(AND($D$2+$E$2=0,K10-Q10>0),K10-Q10,0)) -> 0 | T10: =S10*0.3 -> 0 | U10: =IF(AND('Total income package'!$A$18=TRUE,OR(H10="Yes",O10="Yes"),G10<$G$2,$K$2-T10>10),ROUNDDOWN($K$2-T10,0),0) -> 1183 | V10: =IF(AND(C6<3,U10>10,U10<24),24,U10) -> 1183
B11: 2500 | C11: =MAX('TANF-VIEW'!L14,'TANF-VIEW'!T14) -> 385 | D11: =B11/12 -> 208.33333 | E11: ='Total income package'!$D$80 -> 0 | F11: ='Total income package'!$H$61+'Total income package'!$F$66 -> 250 | G11: =D11+C11+E11+F11 -> 843.33333 | H11: =IF(G11<$G$2,"Yes","No") -> Yes | I11: =D11*0.2 -> 41.666667 | J11: =$H$2 -> 261 | K11: =IF(G11-I11-J11>0,G11-I11-J11,0) -> 540.66667 | L11: =$I$2 -> 700 | M11: ='Total income package'!$B$69 -> 500 | N11: =L11+M11 -> 1200 | O11: =IF(AND($D$2+$E$2>0,K11<$J$2),"Yes","No") -> Yes | P11: =K11/2 -> 270.33333 | Q11: =IF(AND(D$2+$E$2=0,N11<$L$2,N11-P11>0),N11-P11,IF(AND(D$2+$E$2=0,N11>$L$2),$L$2,0)) -> 0 | R11: =IF(AND(D$2+$E$2>0,N11-SNAP!P11>0),N11-SNAP!P11,0) -> 929.66667 | S11: =IF(AND($D$2+$E$2>0,K11-R11>0),K11-R11,IF(AND($D$2+$E$2=0,K11-Q11>0),K11-Q11,0)) -> 0 | T11: =S11*0.3 -> 0 | U11: =IF(AND('Total income package'!$A$18=TRUE,OR(H11="Yes",O11="Yes"),G11<$G$2,$K$2-T11>10),ROUNDDOWN($K$2-T11,0),0) -> 1183 | V11: =IF(AND(C7<3,U11>10,U11<24),24,U11) -> 1183
B12: 3000 | C12: =MAX('TANF-VIEW'!L15,'TANF-VIEW'!T15) -> 352.2 | D12: =B12/12 -> 250 | E12: ='Total income package'!$D$80 -> 0 | F12: ='Total income package'!$H$61+'Total income package'!$F$66 -> 250 | G12: =D12+C12+E12+F12 -> 852.2 | H12: =IF(G12<$G$2,"Yes","No") -> Yes | I12: =D12*0.2 -> 50 | J12: =$H$2 -> 261 | K12: =IF(G12-I12-J12>0,G12-I12-J12,0) -> 541.2 | L12: =$I$2 -> 700 | M12: ='Total income package'!$B$69 -> 500 | N12: =L12+M12 -> 1200 | O12: =IF(AND($D$2+$E$2>0,K12<$J$2),"Yes","No") -> Yes | P12: =K12/2 -> 270.6 | Q12: =IF(AND(D$2+$E$2=0,N12<$L$2,N12-P12>0),N12-P12,IF(AND(D$2+$E$2=0,N12>$L$2),$L$2,0)) -> 0 | R12: =IF(AND(D$2+$E$2>0,N12-SNAP!P12>0),N12-SNAP!P12,0) -> 929.4 | S12: =IF(AND($D$2+$E$2>0,K12-R12>0),K12-R12,IF(AND($D$2+$E$2=0,K12-Q12>0),K12-Q12,0)) -> 0 | T12: =S12*0.3 -> 0 | U12: =IF(AND('Total income package'!$A$18=TRUE,OR(H12="Yes",O12="Yes"),G12<$G$2,$K$2-T12>10),ROUNDDOWN($K$2-T12,0),0) -> 1183 | V12: =IF(AND(C8<3,U12>10,U12<24),24,U12) -> 1183
B13: 3500 | C13: =MAX('TANF-VIEW'!L16,'TANF-VIEW'!T16) -> 318.86667 | D13: =B13/12 -> 291.66667 | E13: ='Total income package'!$D$80 -> 0 | F13: ='Total income package'!$H$61+'Total income package'!$F$66 -> 250 | G13: =D13+C13+E13+F13 -> 860.53333 | H13: =IF(G13<$G$2,"Yes","No") -> Yes | I13: =D13*0.2 -> 58.333333 | J13: =$H$2 -> 261 | K13: =IF(G13-I13-J13>0,G13-I13-J13,0) -> 541.2 | L13: =$I$2 -> 700 | M13: ='Total income package'!$B$69 -> 500 | N13: =L13+M13 -> 1200 | O13: =IF(AND($D$2+$E$2>0,K13<$J$2),"Yes","No") -> Yes | P13: =K13/2 -> 270.6 | Q13: =IF(AND(D$2+$E$2=0,N13<$L$2,N13-P13>0),N13-P13,IF(AND(D$2+$E$2=0,N13>$L$2),$L$2,0)) -> 0 | R13: =IF(AND(D$2+$E$2>0,N13-SNAP!P13>0),N13-SNAP!P13,0) -> 929.4 | S13: =IF(AND($D$2+$E$2>0,K13-R13>0),K13-R13,IF(AND($D$2+$E$2=0,K13-Q13>0),K13-Q13,0)) -> 0 | T13: =S13*0.3 -> 0 | U13: =IF(AND('Total income package'!$A$18=TRUE,OR(H13="Yes",O13="Yes"),G13<$G$2,$K$2-T13>10),ROUNDDOWN($K$2-T13,0),0) -> 1183 | V13: =IF(AND(C9<3,U13>10,U13<24),24,U13) -> 1183
B14: 4000 | C14: =MAX('TANF-VIEW'!L17,'TANF-VIEW'!T17) -> 285.53333 | D14: =B14/12 -> 333.33333 | E14: ='Total income package'!$D$80 -> 0 | F14: ='Total income package'!$H$61+'Total income package'!$F$66 -> 250 | G14: =D14+C14+E14+F14 -> 868.86667 | H14: =IF(G14<$G$2,"Yes","No") -> Yes | I14: =D14*0.2 -> 66.666667 | J14: =$H$2 -> 261 | K14: =IF(G14-I14-J14>0,G14-I14-J14,0) -> 541.2 | L14: =$I$2 -> 700 | M14: ='Total income package'!$B$69 -> 500 | N14: =L14+M14 -> 1200 | O14: =IF(AND($D$2+$E$2>0,K14<$J$2),"Yes","No") -> Yes | P14: =K14/2 -> 270.6 | Q14: =IF(AND(D$2+$E$2=0,N14<$L$2,N14-P14>0),N14-P14,IF(AND(D$2+$E$2=0,N14>$L$2),$L$2,0)) -> 0 | R14: =IF(AND(D$2+$E$2>0,N14-SNAP!P14>0),N14-SNAP!P14,0) -> 929.4 | S14: =IF(AND($D$2+$E$2>0,K14-R14>0),K14-R14,IF(AND($D$2+$E$2=0,K14-Q14>0),K14-Q14,0)) -> 0 | T14: =S14*0.3 -> 0 | U14: =IF(AND('Total income package'!$A$18=TRUE,OR(H14="Yes",O14="Yes"),G14<$G$2,$K$2-T14>10),ROUNDDOWN($K$2-T14,0),0) -> 1183 | V14: =IF(AND(C10<3,U14>10,U14<24),24,U14) -> 1183
B15: 4500 | C15: =MAX('TANF-VIEW'!L18,'TANF-VIEW'!T18) -> 252.2 | D15: =B15/12 -> 375 | E15: ='Total income package'!$D$80 -> 0 | F15: ='Total income package'!$H$61+'Total income package'!$F$66 -> 250 | G15: =D15+C15+E15+F15 -> 877.2 | H15: =IF(G15<$G$2,"Yes","No") -> Yes | I15: =D15*0.2 -> 75 | J15: =$H$2 -> 261 | K15: =IF(G15-I15-J15>0,G15-I15-J15,0) -> 541.2 | L15: =$I$2 -> 700 | M15: ='Total income package'!$B$69 -> 500 | N15: =L15+M15 -> 1200 | O15: =IF(AND($D$2+$E$2>0,K15<$J$2),"Yes","No") -> Yes | P15: =K15/2 -> 270.6 | Q15: =IF(AND(D$2+$E$2=0,N15<$L$2,N15-P15>0),N15-P15,IF(AND(D$2+$E$2=0,N15>$L$2),$L$2,0)) -> 0 | R15: =IF(AND(D$2+$E$2>0,N15-SNAP!P15>0),N15-SNAP!P15,0) -> 929.4 | S15: =IF(AND($D$2+$E$2>0,K15-R15>0),K15-R15,IF(AND($D$2+$E$2=0,K15-Q15>0),K15-Q15,0)) -> 0 | T15: =S15*0.3 -> 0 | U15: =IF(AND('Total income package'!$A$18=TRUE,OR(H15="Yes",O15="Yes"),G15<$G$2,$K$2-T15>10),ROUNDDOWN($K$2-T15,0),0) -> 1183 | V15: =IF(AND(C11<3,U15>10,U15<24),24,U15) -> 1183
B16: 5000 | C16: =MAX('TANF-VIEW'!L19,'TANF-VIEW'!T19) -> 218.86667 | D16: =B16/12 -> 416.66667 | E16: ='Total income package'!$D$80 -> 0 | F16: ='Total income package'!$H$61+'Total income package'!$F$66 -> 250 | G16: =D16+C16+E16+F16 -> 885.53333 | H16: =IF(G16<$G$2,"Yes","No") -> Yes | I16: =D16*0.2 -> 83.333333 | J16: =$H$2 -> 261 | K16: =IF(G16-I16-J16>0,G16-I16-J16,0) -> 541.2 | L16: =$I$2 -> 700 | M16: ='Total income package'!$B$69 -> 500 | N16: =L16+M16 -> 1200 | O16: =IF(AND($D$2+$E$2>0,K16<$J$2),"Yes","No") -> Yes | P16: =K16/2 -> 270.6 | Q16: =IF(AND(D$2+$E$2=0,N16<$L$2,N16-P16>0),N16-P16,IF(AND(D$2+$E$2=0,N16>$L$2),$L$2,0)) -> 0 | R16: =IF(AND(D$2+$E$2>0,N16-SNAP!P16>0),N16-SNAP!P16,0) -> 929.4 | S16: =IF(AND($D$2+$E$2>0,K16-R16>0),K16-R16,IF(AND($D$2+$E$2=0,K16-Q16>0),K16-Q16,0)) -> 0 | T16: =S16*0.3 -> 0 | U16: =IF(AND('Total income package'!$A$18=TRUE,OR(H16="Yes",O16="Yes"),G16<$G$2,$K$2-T16>10),ROUNDDOWN($K$2-T16,0),0) -> 1183 | V16: =IF(AND(C12<3,U16>10,U16<24),24,U16) -> 1183
B17: 5500 | C17: =MAX('TANF-VIEW'!L20,'TANF-VIEW'!T20) -> 185.53333 | D17: =B17/12 -> 458.33333 | E17: ='Total income package'!$D$80 -> 0 | F17: ='Total income package'!$H$61+'Total income package'!$F$66 -> 250 | G17: =D17+C17+E17+F17 -> 893.86667 | H17: =IF(G17<$G$2,"Yes","No") -> Yes | I17: =D17*0.2 -> 91.666667 | J17: =$H$2 -> 261 | K17: =IF(G17-I17-J17>0,G17-I17-J17,0) -> 541.2 | L17: =$I$2 -> 700 | M17: ='Total income package'!$B$69 -> 500 | N17: =L17+M17 -> 1200 | O17: =IF(AND($D$2+$E$2>0,K17<$J$2),"Yes","No") -> Yes | P17: =K17/2 -> 270.6 | Q17: =IF(AND(D$2+$E$2=0,N17<$L$2,N17-P17>0),N17-P17,IF(AND(D$2+$E$2=0,N17>$L$2),$L$2,0)) -> 0 | R17: =IF(AND(D$2+$E$2>0,N17-SNAP!P17>0),N17-SNAP!P17,0) -> 929.4 | S17: =IF(AND($D$2+$E$2>0,K17-R17>0),K17-R17,IF(AND($D$2+$E$2=0,K17-Q17>0),K17-Q17,0)) -> 0 | T17: =S17*0.3 -> 0 | U17: =IF(AND('Total income package'!$A$18=TRUE,OR(H17="Yes",O17="Yes"),G17<$G$2,$K$2-T17>10),ROUNDDOWN($K$2-T17,0),0) -> 1183 | V17: =IF(AND(C13<3,U17>10,U17<24),24,U17) -> 1183
... B206: 100000 | C206: =MAX('TANF-VIEW'!L209,'TANF-VIEW'!T209) -> 0 | D206: =B206/12 -> 8333.3333 | E206: ='Total income package'!$D$80 -> 0 | F206: ='Total income package'!$H$61+'Total income package'!$F$66 -> 250 | G206: =D206+C206+E206+F206 -> 8583.3333 | H206: =IF(G206<$G$2,"Yes","No") -> No | I206: =D206*0.2 -> 1666.6667 | J206: =$H$2 -> 261 | K206: =IF(G206-I206-J206>0,G206-I206-J206,0) -> 6655.6667 | L206: =$I$2 -> 700 | M206: ='Total income package'!$B$69 -> 500 | N206: =L206+M206 -> 1200 | O206: =IF(AND($D$2+$E$2>0,K206<$J$2),"Yes","No") -> No | P206: =K206/2 -> 3327.8333 | Q206: =IF(AND(D$2+$E$2=0,N206<$L$2,N206-P206>0),N206-P206,IF(AND(D$2+$E$2=0,N206>$L$2),$L$2,0)) -> 0 | R206: =IF(AND(D$2+$E$2>0,N206-SNAP!P206>0),N206-SNAP!P206,0) -> 0 | S206: =IF(AND($D$2+$E$2>0,K206-R206>0),K206-R206,IF(AND($D$2+$E$2=0,K206-Q206>0),K206-Q206,0)) -> 6655.6667 | T206: =S206*0.3 -> 1996.7 | U206: =IF(AND('Total income package'!$A$18=TRUE,OR(H206="Yes",O206="Yes"),G206<$G$2,$K$2-T206>10),ROUNDDOWN($K$2-T206,0),0) -> 0 | V206: =IF(AND(C202<3,U206>10,U206<24),24,U206) -> 0
B209: Exact income-start | C209: =MAX('TANF-VIEW'!L212,'TANF-VIEW'!T212) -> 0 | D209: ='Total income package'!$B$90 -> 1423 | E209: ='Total income package'!$D$80+'Total income package'!$D$86 -> 0 | F209: ='Total income package'!$H$61+'Total income package'!$F$66 -> 250 | G209: =D209+C209+E209+F209 -> 1673 | H209: =IF(G209<$G$2,"Yes","No") -> Yes | I209: =D209*0.2 -> 284.6 | J209: =$H$2 -> 261 | K209: =IF(G209-I209-J209>0,G209-I209-J209,0) -> 1127.4 | L209: =$I$2 -> 700 | M209: ='Total income package'!$B$69 -> 500 | N209: =L209+M209 -> 1200 | O209: =IF(AND($D$2+$E$2>0,K209<$J$2),"Yes","No") -> Yes | P209: =K209/2 -> 563.7 | Q209: =IF(AND(D$2+$E$2=0,N209<$L$2,N209-P209>0),N209-P209,IF(AND(D$2+$E$2=0,N209>$L$2),$L$2,0)) -> 0 | R209: =IF(AND(D$2+$E$2>0,N209-SNAP!P209>0),N209-SNAP!P209,0) -> 636.3 | S209: =IF(AND($D$2+$E$2>0,K209-R209>0),K209-R209,IF(AND($D$2+$E$2=0,K209-Q209>0),K209-Q209,0)) -> 491.1 | T209: =S209*0.3 -> 147.33 | U209: =IF(AND('Total income package'!$A$18=TRUE,OR(H209="Yes",O209="Yes"),G209<$G$2,$K$2-T209>10),ROUNDDOWN($K$2-T209,0),0) -> 1035 | V209: =IF(AND(C205<3,U209>10,U209<24),24,U209) -> 1035
B211: Exact income-new | C211: =MAX('TANF-VIEW'!L214,'TANF-VIEW'!T214) -> 0 | D211: ='Total income package'!$B$91 -> 3000 | E211: ='Total income package'!$D$80+'Total income package'!$D$86 -> 0 | F211: ='Total income package'!$H$61+'Total income package'!$F$66 -> 250 | G211: =D211+C211+E211+F211 -> 3250 | H211: =IF(G211<$G$2,"Yes","No") -> Yes | I211: =D211*0.2 -> 600 | J211: =$H$2 -> 261 | K211: =IF(G211-I211-J211>0,G211-I211-J211,0) -> 2389 | L211: =$I$2 -> 700 | M211: ='Total income package'!$B$69 -> 500 | N211: =L211+M211 -> 1200 | O211: =IF(AND($D$2+$E$2>0,K211<$J$2),"Yes","No") -> Yes | P211: =K211/2 -> 1194.5 | Q211: =IF(AND(D$2+$E$2=0,N211<$L$2,N211-P211>0),N211-P211,IF(AND(D$2+$E$2=0,N211>$L$2),$L$2,0)) -> 0 | R211: =IF(AND(D$2+$E$2>0,N211-SNAP!P211>0),N211-SNAP!P211,0) -> 5.5 | S211: =IF(AND($D$2+$E$2>0,K211-R211>0),K211-R211,IF(AND($D$2+$E$2=0,K211-Q211>0),K211-Q211,0)) -> 2383.5 | T211: =S211*0.3 -> 715.05 | U211: =IF(AND('Total income package'!$A$18=TRUE,OR(H211="Yes",O211="Yes"),G211<$G$2,$K$2-T211>10),ROUNDDOWN($K$2-T211,0),0) -> 467 | V211: =IF(AND(C207<3,U211>10,U211<24),24,U211) -> 467

Sheet SSDI
A1: Location | B1: Number in Household | W1: Notes:
A2: ='Total income package'!B3 -> Buckingham | B2: ='Total income package'!B32 -> 5
W3: Define unearned income: excludes SNAP, EITC, housing vouchers
W4: Does not take into account Virginia auxiliary program
A5: Annual earned income | B5: Monthly earned income | V5: connect U.income to other programs
A6: 0 | B6: 0 | V6: TANF is counted as income (unearned)
A7: 500 | B7: =A7/12 -> 41.666667
A8: 1000 | B8: =A8/12 -> 83.333333
A9: 1500 | B9: =A9/12 -> 125 | V9: TANF
A10: 2000 | B10: =A10/12 -> 166.66667
A11: 2500 | B11: =A11/12 -> 208.33333
A12: 3000 | B12: =A12/12 -> 250
A13: 3500 | B13: =A13/12 -> 291.66667
A14: 4000 | B14: =A14/12 -> 333.33333
A15: 4500 | B15: =A15/12 -> 375
A16: 5000 | B16: =A16/12 -> 416.66667
A17: 5500 | B17: =A17/12 -> 458.33333
A18: 6000 | B18: =A18/12 -> 500
A19: 6500 | B19: =A19/12 -> 541.66667
A20: 7000 | B20: =A20/12 -> 583.33333
A21: 7500 | B21: =A21/12 -> 625
... A206: 100000 | B206: =A206/12 -> 8333.3333
A208: Exact income-start
B209: ='Total income package'!$B$90 -> 1423
A210: Exact income-new
B211: ='Total income package'!$B$91 -> 3000

Sheet SSI
A1: Location | B1: Number in Household | L1: SSI Calculator | W1: Notes:
A2: ='Total income package'!B3 -> Buckingham | B2: ='Total income package'!B32 -> 5
L3: Spouse income | W3: Define unearned income: excludes SNAP, EITC, housing vouchers
K4: adult disab. | L4: Age | M4: E.income | N4: U.income | O4: C.income | P4: Couple rate | Q4: Eligible | W4: Does not take into account Virginia auxiliary program
A5: Annual earned income | B5: Monthly earned income | C5: Social security benefit | D5: Monthly income (earned + SS) | E5: Monthly income - $20 | F5: Earned income - $65 | G5: 1/2 of earned income - $65 | H5: Countble income | K5: 1 | L5: 60 | M5: 200 | N5: 100 | O5: =M5+N5-487*N9 -> -187 | P5: =IF(L5>=65, 1, IF(AND(K5=1, M5+N5<2020), 1, IF(O5<487, 0, 1))) -> 1 | Q5: =IF(N5>987, FALSE, AND(M5+N5<2020, OR(K5=1, L5>=65))) -> TRUE | V5: connect U.income to other programs
A6: 0 | B6: 0 | C6: ='Total income package'!$D$80 -> 0 | D6: =B6+C6 -> 0 | E6: =D6-20 -> -20 | F6: =IF(B6-65<0,0,B6-65) -> 0 | G6: =IF(F6/2<0,0,F6/2) -> 0 | H6: =G6+C6 -> 0 | V6: TANF is counted as income (unearned)
A7: 500 | B7: =A7/12 -> 41.666667 | C7: ='Total income package'!$D$80 -> 0 | D7: =B7+C7 -> 41.666667 | E7: =D7-20 -> 21.666667 | F7: =IF(B7-65<0,0,B7-65) -> 0 | G7: =IF(F7/2<0,0,F7/2) -> 0 | H7: =G7+C7 -> 0 | K7: Individual input
A8: 1000 | B8: =A8/12 -> 83.333333 | C8: ='Total income package'!$D$80 -> 0 | D8: =B8+C8 -> 83.333333 | E8: =D8-20 -> 63.333333 | F8: =IF(B8-65<0,0,B8-65) -> 18.333333 | G8: =IF(F8/2<0,0,F8/2) -> 9.1666667 | H8: =G8+C8 -> 9.1666667 | K8: adult disab. | L8: Age | M8: E.children | N8: I.children | O8: E.income | P8: U.income | Q8: C.income | R8: SSI adult | S8: Eligible
A9: 1500 | B9: =A9/12 -> 125 | C9: ='Total income package'!$D$80 -> 0 | D9: =B9+C9 -> 125 | E9: =D9-20 -> 105 | F9: =IF(B9-65<0,0,B9-65) -> 60 | G9: =IF(F9/2<0,0,F9/2) -> 30 | H9: =G9+C9 -> 30 | K9: 1 | L9: 55 | M9: 1 | N9: 1 | O9: 400 | P9: 100 | Q9: =K13+L13 -> 447.5 | R9: =IF(OR(K9=1,L9>=65),MAX(0,IF(AND(P5=0,M13>=2020),0,IF(AND(P5=1,M13>=2985),0,IF(P5=0,967-(K13+L13),1450-(K13+L13))))),0) -> 1002.5 | S9: =IF(P9>987, FALSE, AND(OR(K9=1, L9>=65), O9+P9<2020)) -> TRUE | V9: TANF
A10: 2000 | B10: =A10/12 -> 166.66667 | C10: ='Total income package'!$D$80 -> 0 | D10: =B10+C10 -> 166.66667 | E10: =D10-20 -> 146.66667 | F10: =IF(B10-65<0,0,B10-65) -> 101.66667 | G10: =IF(F10/2<0,0,F10/2) -> 50.833333 | H10: =G10+C10 -> 50.833333
A11: 2500 | B11: =A11/12 -> 208.33333 | C11: ='Total income package'!$D$80 -> 0 | D11: =B11+C11 -> 208.33333 | E11: =D11-20 -> 188.33333 | F11: =IF(B11-65<0,0,B11-65) -> 143.33333 | G11: =IF(F11/2<0,0,F11/2) -> 71.666667 | H11: =G11+C11 -> 71.666667 | K11: Adjusted variables
A12: 3000 | B12: =A12/12 -> 250 | C12: ='Total income package'!$D$80 -> 0 | D12: =B12+C12 -> 250 | E12: =D12-20 -> 230 | F12: =IF(B12-65<0,0,B12-65) -> 185 | G12: =IF(F12/2<0,0,F12/2) -> 92.5 | H12: =G12+C12 -> 92.5 | K12: adj.E | L12: adj.U | M12: TT income
A13: 3500 | B13: =A13/12 -> 291.66667 | C13: ='Total income package'!$D$80 -> 0 | D13: =B13+C13 -> 291.66667 | E13: =D13-20 -> 271.66667 | F13: =IF(B13-65<0,0,B13-65) -> 226.66667 | G13: =IF(F13/2<0,0,F13/2) -> 113.33333 | H13: =G13+C13 -> 113.33333 | K13: =MAX(0, IF(P5=1, (O9+M5-65)/2, (O9-65)/2)) -> 267.5 | L13: =MAX(0, IF(P5=1, P9+N5-20, P9-20)) -> 180 | M13: =IF(P5=1,(M5+N5)+(O9+P9),(O9+P9)) -> 800
A14: 4000 | B14: =A14/12 -> 333.33333 | C14: ='Total income package'!$D$80 -> 0 | D14: =B14+C14 -> 333.33333 | E14: =D14-20 -> 313.33333 | F14: =IF(B14-65<0,0,B14-65) -> 268.33333 | G14: =IF(F14/2<0,0,F14/2) -> 134.16667 | H14: =G14+C14 -> 134.16667
A15: 4500 | B15: =A15/12 -> 375 | C15: ='Total income package'!$D$80 -> 0 | D15: =B15+C15 -> 375 | E15: =D15-20 -> 355 | F15: =IF(B15-65<0,0,B15-65) -> 310 | G15: =IF(F15/2<0,0,F15/2) -> 155 | H15: =G15+C15 -> 155 | K15: Parental deeming
A16: 5000 | B16: =A16/12 -> 416.66667 | C16: ='Total income package'!$D$80 -> 0 | D16: =B16+C16 -> 416.66667 | E16: =D16-20 -> 396.66667 | F16: =IF(B16-65<0,0,B16-65) -> 351.66667 | G16: =IF(F16/2<0,0,F16/2) -> 175.83333 | H16: =G16+C16 -> 175.83333 | K16: d.adj.U | L16: d.adj.E | M16: c.alln. & adj.U | N16: d.adj.E | O16: p.alln | P16: parents.home
A17: 5500 | B17: =A17/12 -> 458.33333 | C17: ='Total income package'!$D$80 -> 0 | D17: =B17+C17 -> 458.33333 | E17: =D17-20 -> 438.33333 | F17: =IF(B17-65<0,0,B17-65) -> 393.33333 | G17: =IF(F17/2<0,0,F17/2) -> 196.66667 | H17: =G17+C17 -> 196.66667 | K17: =IF(AND(Q5=FALSE, S9=FALSE), N5+P9-20, IF(Q5=FALSE, N5-20, IF(S9=1, P9-20, 0))) -> 0 | L17: =IF(AND(Q5=FALSE, S9=FALSE), M5+O9, IF(Q5=FALSE, M5, IF(S9=1, O9, 0))) -> 0 | M17: =K17-483*N9 -> -483 | N17: =MAX(IF(M17<0,(L17+M17-65)/2,(L17-65)/2),0) -> 0 | O17: =IF(P17=1,967,IF(P17=2,1450,0)) -> 0 | P17: =COUNTIF(Q5,FALSE) + COUNTIF(S9,FALSE) -> 0
A18: 6000 | B18: =A18/12 -> 500 | C18: ='Total income package'!$D$80 -> 0 | D18: =B18+C18 -> 500 | E18: =D18-20 -> 480 | F18: =IF(B18-65<0,0,B18-65) -> 435 | G18: =IF(F18/2<0,0,F18/2) -> 217.5 | H18: =G18+C18 -> 217.5
A19: 6500 | B19: =A19/12 -> 541.66667 | C19: ='Total income package'!$D$80 -> 0 | D19: =B19+C19 -> 541.66667 | E19: =D19-20 -> 521.66667 | F19: =IF(B19-65<0,0,B19-65) -> 476.66667 | G19: =IF(F19/2<0,0,F19/2) -> 238.33333 | H19: =G19+C19 -> 238.33333 | K19: SSI children
A20: 7000 | B20: =A20/12 -> 583.33333 | C20: ='Total income package'!$D$80 -> 0 | D20: =B20+C20 -> 583.33333 | E20: =D20-20 -> 563.33333 | F20: =IF(B20-65<0,0,B20-65) -> 518.33333 | G20: =IF(F20/2<0,0,F20/2) -> 259.16667 | H20: =G20+C20 -> 259.16667 | K20: d.income | L20: SSI per children
A21: 7500 | B21: =A21/12 -> 625 | C21: ='Total income package'!$D$80 -> 0 | D21: =B21+C21 -> 625 | E21: =D21-20 -> 605 | F21: =IF(B21-65<0,0,B21-65) -> 560 | G21: =IF(F21/2<0,0,F21/2) -> 280 | H21: =G21+C21 -> 280 | K21: =IF(M9=0, 0, IF(M17<=0, (N17-O17)/M9, IF(M17>0, (N17+M17-O17)/M9, 0))) -> 0 | L21: =IF(M9=0, 0, IF(AND(Q5=TRUE, S9=TRUE), 967, IF(K21>967, 0, IF(K21<0, 967, 967-K21)))) -> 967
A22: 8000 | B22: =A22/12 -> 666.66667 | C22: ='Total income package'!$D$80 -> 0 | D22: =B22+C22 -> 666.66667 | E22: =D22-20 -> 646.66667 | F22: =IF(B22-65<0,0,B22-65) -> 601.66667 | G22: =IF(F22/2<0,0,F22/2) -> 300.83333 | H22: =G22+C22 -> 300.83333
A23: 8500 | B23: =A23/12 -> 708.33333 | C23: ='Total income package'!$D$80 -> 0 | D23: =B23+C23 -> 708.33333 | E23: =D23-20 -> 688.33333 | F23: =IF(B23-65<0,0,B23-65) -> 643.33333 | G23: =IF(F23/2<0,0,F23/2) -> 321.66667 | H23: =G23+C23 -> 321.66667 | K23: Household SSI
A24: 9000 | B24: =A24/12 -> 750 | C24: ='Total income package'!$D$80 -> 0 | D24: =B24+C24 -> 750 | E24: =D24-20 -> 730 | F24: =IF(B24-65<0,0,B24-65) -> 685 | G24: =IF(F24/2<0,0,F24/2) -> 342.5 | H24: =G24+C24 -> 342.5 | K24: =L21*M9+R9 -> 1969.5
A25: 9500 | B25: =A25/12 -> 791.66667 | C25: ='Total income package'!$D$80 -> 0 | D25: =B25+C25 -> 791.66667 | E25: =D25-20 -> 771.66667 | F25: =IF(B25-65<0,0,B25-65) -> 726.66667 | G25: =IF(F25/2<0,0,F25/2) -> 363.33333 | H25: =G25+C25 -> 363.33333
A26: 10000 | B26: =A26/12 -> 833.33333 | C26: ='Total income package'!$D$80 -> 0 | D26: =B26+C26 -> 833.33333 | E26: =D26-20 -> 813.33333 | F26: =IF(B26-65<0,0,B26-65) -> 768.33333 | G26: =IF(F26/2<0,0,F26/2) -> 384.16667 | H26: =G26+C26 -> 384.16667 | K26: Sources
A27: 10500 | B27: =A27/12 -> 875 | C27: ='Total income package'!$D$80 -> 0 | D27: =B27+C27 -> 875 | E27: =D27-20 -> 855 | F27: =IF(B27-65<0,0,B27-65) -> 810 | G27: =IF(F27/2<0,0,F27/2) -> 405 | H27: =G27+C27 -> 405 | K27: SSI spouse: https://secure.ssa.gov/poms.nsf/lnx/0501320400
A28: 11000 | B28: =A28/12 -> 916.66667 | C28: ='Total income package'!$D$80 -> 0 | D28: =B28+C28 -> 916.66667 | E28: =D28-20 -> 896.66667 | F28: =IF(B28-65<0,0,B28-65) -> 851.66667 | G28: =IF(F28/2<0,0,F28/2) -> 425.83333 | H28: =G28+C28 -> 425.83333 | K28: SSI children: https://secure.ssa.gov/poms.NSF/LNX/0501320500
A29: 11500 | B29: =A29/12 -> 958.33333 | C29: ='Total income package'!$D$80 -> 0 | D29: =B29+C29 -> 958.33333 | E29: =D29-20 -> 938.33333 | F29: =IF(B29-65<0,0,B29-65) -> 893.33333 | G29: =IF(F29/2<0,0,F29/2) -> 446.66667 | H29: =G29+C29 -> 446.66667 | K29: SSI general: https://www.ssa.gov/ssi/text-income-ussi.htm
A30: 12000 | B30: =A30/12 -> 1000 | C30: ='Total income package'!$D$80 -> 0 | D30: =B30+C30 -> 1000 | E30: =D30-20 -> 980 | F30: =IF(B30-65<0,0,B30-65) -> 935 | G30: =IF(F30/2<0,0,F30/2) -> 467.5 | H30: =G30+C30 -> 467.5 | K30: SSI info:https://www.ssa.gov/pubs/EN-05-11000.pdf
A31: 12500 | B31: =A31/12 -> 1041.6667 | C31: ='Total income package'!$D$80 -> 0 | D31: =B31+C31 -> 1041.6667 | E31: =D31-20 -> 1021.6667 | F31: =IF(B31-65<0,0,B31-65) -> 976.66667 | G31: =IF(F31/2<0,0,F31/2) -> 488.33333 | H31: =G31+C31 -> 488.33333
A32: 13000 | B32: =A32/12 -> 1083.3333 | C32: ='Total income package'!$D$80 -> 0 | D32: =B32+C32 -> 1083.3333 | E32: =D32-20 -> 1063.3333 | F32: =IF(B32-65<0,0,B32-65) -> 1018.3333 | G32: =IF(F32/2<0,0,F32/2) -> 509.16667 | H32: =G32+C32 -> 509.16667
A33: 13500 | B33: =A33/12 -> 1125 | C33: ='Total income package'!$D$80 -> 0 | D33: =B33+C33 -> 1125 | E33: =D33-20 -> 1105 | F33: =IF(B33-65<0,0,B33-65) -> 1060 | G33: =IF(F33/2<0,0,F33/2) -> 530 | H33: =G33+C33 -> 530
A34: 14000 | B34: =A34/12 -> 1166.6667 | C34: ='Total income package'!$D$80 -> 0 | D34: =B34+C34 -> 1166.6667 | E34: =D34-20 -> 1146.6667 | F34: =IF(B34-65<0,0,B34-65) -> 1101.6667 | G34: =IF(F34/2<0,0,F34/2) -> 550.83333 | H34: =G34+C34 -> 550.83333
A35: 14500 | B35: =A35/12 -> 1208.3333 | C35: ='Total income package'!$D$80 -> 0 | D35: =B35+C35 -> 1208.3333 | E35: =D35-20 -> 1188.3333 | F35: =IF(B35-65<0,0,B35-65) -> 1143.3333 | G35: =IF(F35/2<0,0,F35/2) -> 571.66667 | H35: =G35+C35 -> 571.66667
A36: 15000 | B36: =A36/12 -> 1250 | C36: ='Total income package'!$D$80 -> 0 | D36: =B36+C36 -> 1250 | E36: =D36-20 -> 1230 | F36: =IF(B36-65<0,0,B36-65) -> 1185 | G36: =IF(F36/2<0,0,F36/2) -> 592.5 | H36: =G36+C36 -> 592.5
A37: 15500 | B37: =A37/12 -> 1291.6667 | C37: ='Total income package'!$D$80 -> 0 | D37: =B37+C37 -> 1291.6667 | E37: =D37-20 -> 1271.6667 | F37: =IF(B37-65<0,0,B37-65) -> 1226.6667 | G37: =IF(F37/2<0,0,F37/2) -> 613.33333 | H37: =G37+C37 -> 613.33333
A38: 16000 | B38: =A38/12 -> 1333.3333 | C38: ='Total income package'!$D$80 -> 0 | D38: =B38+C38 -> 1333.3333 | E38: =D38-20 -> 1313.3333 | F38: =IF(B38-65<0,0,B38-65) -> 1268.3333 | G38: =IF(F38/2<0,0,F38/2) -> 634.16667 | H38: =G38+C38 -> 634.16667
A39: 16500 | B39: =A39/12 -> 1375 | C39: ='Total income package'!$D$80 -> 0 | D39: =B39+C39 -> 1375 | E39: =D39-20 -> 1355 | F39: =IF(B39-65<0,0,B39-65) -> 1310 | G39: =IF(F39/2<0,0,F39/2) -> 655 | H39: =G39+C39 -> 655
A40: 17000 | B40: =A40/12 -> 1416.6667 | C40: ='Total income package'!$D$80 -> 0 | D40: =B40+C40 -> 1416.6667 | E40: =D40-20 -> 1396.6667 | F40: =IF(B40-65<0,0,B40-65) -> 1351.6667 | G40: =IF(F40/2<0,0,F40/2) -> 675.83333 | H40: =G40+C40 -> 675.83333
A41: 17500 | B41: =A41/12 -> 1458.3333 | C41: ='Total income package'!$D$80 -> 0 | D41: =B41+C41 -> 1458.3333 | E41: =D41-20 -> 1438.3333 | F41: =IF(B41-65<0,0,B41-65) -> 1393.3333 | G41: =IF(F41/2<0,0,F41/2) -> 696.66667 | H41: =G41+C41 -> 696.66667
A42: 18000 | B42: =A42/12 -> 1500 | C42: ='Total income package'!$D$80 -> 0 | D42: =B42+C42 -> 1500 | E42: =D42-20 -> 1480 | F42: =IF(B42-65<0,0,B42-65) -> 1435 | G42: =IF(F42/2<0,0,F42/2) -> 717.5 | H42: =G42+C42 -> 717.5
... A206: 100000 | B206: =A206/12 -> 8333.3333 | C206: ='Total income package'!$D$80 -> 0 | D206: =B206+C206 -> 8333.3333 | E206: =D206-20 -> 8313.3333 | F206: =IF(B206-65<0,0,B206-65) -> 8268.3333 | G206: =IF(F206/2<0,0,F206/2) -> 4134.1667 | H206: =G206+C206 -> 4134.1667
A208: Exact income-start
B209: ='Total income package'!$B$90 -> 1423 | C209: ='Total income package'!$D$80 -> 0 | D209: =B209+C209 -> 1423 | E209: =D209-20 -> 1403 | F209: =IF(B209-65<0,0,B209-65) -> 1358 | G209: =IF(F209/2<0,0,F209/2) -> 679 | H209: =G209+C209 -> 679
A210: Exact income-new
B211: ='Total income package'!$B$91 -> 3000 | C211: ='Total income package'!$D$80 -> 0 | D211: =B211+C211 -> 3000 | E211: =D211-20 -> 2980 | F211: =IF(B211-65<0,0,B211-65) -> 2935 | G211: =IF(F211/2<0,0,F211/2) -> 1467.5 | H211: =G211+C211 -> 1467.5

Sheet Program specific data
A3: HHS Poverty Guidelines for 2026
A4: Family/household size | B4: Yearly | C4: Monthly | D4: 150% of FPL (Monthly) | E4: 185% (Monthly) | F4: 133% FPL Monthly) | G4: 5% FPL (Monthly) | H4: 100% FPL-For Medicaid-round-up (Monthly) | I4: 109% FPL-For Medicaid-round-up (Monthly) | J4: 133%+5% FPL (138% FPL) (Monthly) | K4: 143% FPL (Monthly) | L4: 148% FPL (Monthly) | M4: 200% FPL (Monthly) Plan First | N4: 205% FPL | O4: 160% FPL | P4: 250% FPL | Q4: 80% Monthly
A5: 0 | B5: 0 | C5: 0 | D5: =C5*1.5 -> 0 | E5: =C5*1.85 -> 0 | F5: =ROUNDUP(C5*1.33,0) -> 0 | G5: =ROUNDUP(C5*0.05,0) -> 0 | H5: =ROUNDUP(C5,0) -> 0 | I5: =ROUNDUP(C5*1.09,0) -> 0 | J5: =ROUNDUP((B5*0.05)+(B5*1.33),0)/12 -> 0 | K5: =ROUNDUP(C5*1.43,0) -> 0 | L5: =ROUNDUP(C5*1.48,0) -> 0 | M5: =ROUNDUP(C5*2.05,0) -> 0 | N5: =ROUNDUP(C5*2.05,0) -> 0 | O5: =C5*1.6 -> 0 | P5: =C5*2.5 -> 0
A6: 1 | B6: 15960 | C6: =B6/12 -> 1330 | D6: =C6*1.5 -> 1995 | E6: =C6*1.85 -> 2460.5 | F6: =ROUNDUP(C6*1.33,0) -> 1769 | G6: =ROUNDUP(C6*0.05,0) -> 67 | H6: =ROUNDUP(C6,0) -> 1330 | I6: =ROUNDUP(C6*1.09,0) -> 1450 | J6: =ROUNDUP((B6*0.05)+(B6*1.33),0)/12 -> 1835.4167 | K6: =ROUNDUP(C6*1.43,0) -> 1902 | L6: =ROUNDUP(C6*1.48,0) -> 1969 | M6: 2609 | N6: =ROUNDUP(C6*2.05,0) -> 2727 | O6: =C6*1.6 -> 2128 | P6: =C6*2.5 -> 3325 | Q6: =C6*0.8 -> 1064
A7: 2 | B7: 21640 | C7: =B7/12 -> 1803.3333 | D7: =C7*1.5 -> 2705 | E7: =C7*1.85 -> 3336.1667 | F7: =ROUNDUP(C7*1.33,0) -> 2399 | G7: =ROUNDUP(C7*0.05,0) -> 91 | H7: =ROUNDUP(C7,0) -> 1804 | I7: =ROUNDUP(C7*1.09,0) -> 1966 | J7: =ROUNDUP((B7*0.05)+(B7*1.33),0)/12 -> 2488.6667 | K7: =ROUNDUP(C7*1.43,0) -> 2579 | L7: =ROUNDUP(C7*1.48,0) -> 2669 | M7: 3525 | N7: =ROUNDUP(C7*2.05,0) -> 3697 | O7: =C7*1.6 -> 2885.3333 | P7: =C7*2.5 -> 4508.3333 | Q7: =C7*0.8 -> 1442.6667
A8: 3 | B8: 27320 | C8: =B8/12 -> 2276.6667 | D8: =C8*1.5 -> 3415 | E8: =C8*1.85 -> 4211.8333 | F8: =ROUNDUP(C8*1.33,0) -> 3028 | G8: =ROUNDUP(C8*0.05,0) -> 114 | H8: =ROUNDUP(C8,0) -> 2277 | I8: =ROUNDUP(C8*1.09,0) -> 2482 | J8: =ROUNDUP((B8*0.05)+(B8*1.33),0)/12 -> 3141.8333 | K8: =ROUNDUP(C8*1.43,0) -> 3256 | L8: =ROUNDUP(C8*1.48,0) -> 3370 | M8: 4442 | N8: =ROUNDUP(C8*2.05,0) -> 4668 | O8: =C8*1.6 -> 3642.6667 | P8: =C8*2.5 -> 5691.6667 | Q8: =C8*0.8 -> 1821.3333
A9: 4 | B9: 33000 | C9: =B9/12 -> 2750 | D9: =C9*1.5 -> 4125 | E9: =C9*1.85 -> 5087.5 | F9: =ROUNDUP(C9*1.33,0) -> 3658 | G9: =ROUNDUP(C9*0.05,0) -> 138 | H9: =ROUNDUP(C9,0) -> 2750 | I9: =ROUNDUP(C9*1.09,0) -> 2998 | J9: =ROUNDUP((B9*0.05)+(B9*1.33),0)/12 -> 3795 | K9: =ROUNDUP(C9*1.43,0) -> 3933 | L9: =ROUNDUP(C9*1.48,0) -> 4070 | M9: 5359 | N9: =ROUNDUP(C9*2.05,0) -> 5638 | O9: =C9*1.6 -> 4400 | P9: =C9*2.5 -> 6875 | Q9: =C9*0.8 -> 2200
A10: 5 | B10: 38680 | C10: =B10/12 -> 3223.3333 | D10: =C10*1.5 -> 4835 | E10: =C10*1.85 -> 5963.1667 | F10: =ROUNDUP(C10*1.33,0) -> 4288 | G10: =ROUNDUP(C10*0.05,0) -> 162 | H10: =ROUNDUP(C10,0) -> 3224 | I10: =ROUNDUP(C10*1.09,0) -> 3514 | J10: =ROUNDUP((B10*0.05)+(B10*1.33),0)/12 -> 4448.25 | K10: =ROUNDUP(C10*1.43,0) -> 4610 | L10: =ROUNDUP(C10*1.48,0) -> 4771 | M10: 6275 | N10: =ROUNDUP(C10*2.05,0) -> 6608 | O10: =C10*1.6 -> 5157.3333 | P10: =C10*2.5 -> 8058.3333 | Q10: =C10*0.8 -> 2578.6667
A11: 6 | B11: 44360 | C11: =B11/12 -> 3696.6667 | D11: =C11*1.5 -> 5545 | E11: =C11*1.85 -> 6838.8333 | F11: =ROUNDUP(C11*1.33,0) -> 4917 | G11: =ROUNDUP(C11*0.05,0) -> 185 | H11: =ROUNDUP(C11,0) -> 3697 | I11: =ROUNDUP(C11*1.09,0) -> 4030 | J11: =ROUNDUP((B11*0.05)+(B11*1.33),0)/12 -> 5101.4167 | K11: =ROUNDUP(C11*1.43,0) -> 5287 | L11: =ROUNDUP(C11*1.48,0) -> 5472 | M11: 7192 | N11: =ROUNDUP(C11*2.05,0) -> 7579 | O11: =C11*1.6 -> 5914.6667 | P11: =C11*2.5 -> 9241.6667 | Q11: =C11*0.8 -> 2957.3333
A12: 7 | B12: 50040 | C12: =B12/12 -> 4170 | D12: =C12*1.5 -> 6255 | E12: =C12*1.85 -> 7714.5 | F12: =ROUNDUP(C12*1.33,0) -> 5547 | G12: =ROUNDUP(C12*0.05,0) -> 209 | H12: =ROUNDUP(C12,0) -> 4170 | I12: =ROUNDUP(C12*1.09,0) -> 4546 | J12: =ROUNDUP((B12*0.05)+(B12*1.33),0)/12 -> 5754.6667 | K12: =ROUNDUP(C12*1.43,0) -> 5964 | L12: =ROUNDUP(C12*1.48,0) -> 6172 | M12: 8109 | N12: =ROUNDUP(C12*2.05,0) -> 8549 | O12: =C12*1.6 -> 6672 | P12: =C12*2.5 -> 10425 | Q12: =C12*0.8 -> 3336
A13: 8 | B13: 55720 | C13: =B13/12 -> 4643.3333 | D13: =C13*1.5 -> 6965 | E13: =C13*1.85 -> 8590.1667 | F13: =ROUNDUP(C13*1.33,0) -> 6176 | G13: =ROUNDUP(C13*0.05,0) -> 233 | H13: =ROUNDUP(C13,0) -> 4644 | I13: =ROUNDUP(C13*1.09,0) -> 5062 | J13: =ROUNDUP((B13*0.05)+(B13*1.33),0)/12 -> 6407.8333 | K13: =ROUNDUP(C13*1.43,0) -> 6640 | L13: =ROUNDUP(C13*1.48,0) -> 6873 | M13: 9025 | N13: =ROUNDUP(C13*2.05,0) -> 9519 | O13: =C13*1.6 -> 7429.3333 | P13: =C13*2.5 -> 11608.333 | Q13: =C13*0.8 -> 3714.6667
A14: For families/households with more than 8 persons, add $5,680 for each additional person.
A15: https://aspe.hhs.gov/topics/poverty-economic-mobility/poverty-guidelines
A17: Childcare subsidies
A18: Virginia State Median Income
A19: Family size | B19: 85% of Monthly State Median Income | C19: Group I 150% FPL | D19: Group II 160% FPL | E19: Group III 185% FPL | F19: Group IV 250% FPL (Fairfax & Alexandria)
A20: 1 | B20: 4936 | C20: =D6 -> 1995 | D20: =O6 -> 2128 | E20: =E6 -> 2460.5 | F20: =P6 -> 3325
A21: 2 | B21: 6455 | C21: =D7 -> 2705 | D21: =O7 -> 2885.3333 | E21: =E7 -> 3336.1667 | F21: =P7 -> 4508.3333
A22: 3 | B22: 7973 | C22: =D8 -> 3415 | D22: =O8 -> 3642.6667 | E22: =E8 -> 4211.8333 | F22: =P8 -> 5691.6667
A23: 4 | B23: 9492 | C23: =D9 -> 4125 | D23: =O9 -> 4400 | E23: =E9 -> 5087.5 | F23: =P9 -> 6875
A24: 5 | B24: 11011 | C24: =D10 -> 4835 | D24: =O10 -> 5157.3333 | E24: =E10 -> 5963.1667 | F24: =P10 -> 8058.3333
A25: 6 | B25: 12529 | C25: =D11 -> 5545 | D25: =O11 -> 5914.6667 | E25: =E11 -> 6838.8333 | F25: =P11 -> 9241.6667
A26: 7 | B26: 12814 | C26: =D12 -> 6255 | D26: =O12 -> 6672 | E26: =E12 -> 7714.5 | F26: =P12 -> 10425
A27: 8 | B27: 13099 | C27: =D13 -> 6965 | D27: =O13 -> 7429.3333 | E27: =E13 -> 8590.1667 | F27: =P13 -> 11608.333
A29: T224 Child Care Subsidy Program Manual_Effective October 1_2024
A30: LIHEAP IM 2024-02 State Median Income Estimates
A33: TANF Standard Deduction*
A34: Assistance Unit Size
A35: 1 | B35: 209 | C35: *Using same standard deduction as SNAP per TANF manual:
A36: 2 | B36: 209 | C36: The standard deduction*, the same amount used in the standard deduction for the SNAP program, and 20% of the remainder is deducted from the gross earnings.**
A37: 3 | B37: 209 | C37: 305.1 pg 2
A38: 4 | B38: 223
A39: 5 | B39: 261
A40: 6 | B40: 299
A41: 7 | B41: 299
A42: 8 | B42: 299
A43: TANF Transmittal 77 10/2023
A44: https://www.dss.virginia.gov/files/division/bp/tanf/manual/Transmittal_77.pdf
A46: Assistance Standards
A47: Assistance Unit Size | B47: Group II | C47: GroupIII
A48: 1 | B48: 262 | C48: 366
A49: 2 | B49: 385 | C49: 489
A50: 3 | B50: 482 | C50: 587
A51: 4 | B51: 577 | C51: 681
A52: 5 | B52: 681 | C52: 811
A53: 6 | B53: 761 | C53: 887
A54: 7 | B54: 851 | C54: 979
A55: 8 | B55: 951 | C55: 1079
A56: MAXIMUM REIMBURSABLE PAYMENT | B56: 723 | C56: 861
A58: TANF Maximum Income
B59: GroupII | C59: GroupIII
A60: 1 | B60: 524 | C60: 730
A61: 2 | B61: 767 | C61: 974
A62: 3 | B62: 966 | C62: 1175
A63: 4 | B63: 1152 | C63: 1361
A64: 5 | B64: 1361 | C64: 1622
A65: 6 | B65: 1522 | C65: 1773
A66: 7 | B66: 1703 | C66: 1960
A67: 8 | B67: 1901 | C67: 2158
A68: https://www.dss.virginia.gov/files/division/bp/tanf/manual/Final_XMTL_74.pdf
B70: SNAP Standard Deduction | C70: SNAP Utilty Standard | D70: SNAP Max Shelter | E70: SNAP Medical standard
A71: Household size
A72: 1 | B72: 209 | C72: 375 | D72: 744 | E72: 200
A73: 2 | B73: 209 | C73: 375 | D73: 744 | E73: 200
A74: 3 | B74: 209 | C74: 375 | D74: 744 | E74: 200
A75: 4 | B75: 223 | C75: 476 | D75: 744 | E75: 200
A76: 5 | B76: 261 | C76: 475 | D76: 744 | E76: 200
A77: 6 | B77: 299 | C77: 476 | D77: 744 | E77: 200
A78: 7 | B78: 299 | C78: 476 | D78: 744 | E78: 200
A79: 8 | B79: 299 | C79: 476 | D79: 744 | E79: 200
A80: https://fns-prod.azureedge.us/sites/default/files/resource-files/snap-cola-fy26memo.pdf
A81: https://fusion.dss.virginia.gov/Portals/%5Bbp%5D/Files/SNAP%20Transmittals%20for%20Manuals/SNAP%20Transmittal%20%2336.pdf
A83: SNAP Poverty Rates (Table 1: SNAP Income Eligibility Limits - Oct. 1, 2025, through Sept. 30, 2026) | D83: ***These njumbers different from FPL***
A84: Household Size | B84: 200% FPL Gross income limit | C84: 130% FPL Gross income limit | D84: 100% FPL Net Income Limit | E84: 165% Gross monthly income (Elderly disabled)
A85: 1 | B85: =D85*2 -> 2610 | C85: =D85*1.3 -> 1696.5 | D85: 1305 | E85: 2152 | G85: =D85*12 -> 15660
A86: 2 | B86: =D86*2 -> 3526 | C86: =D86*1.3 -> 2291.9 | D86: 1763 | E86: =D86*1.65 -> 2908.95 | G86: =D86*12 -> 21156
A87: 3 | B87: =D87*2 -> 4442 | C87: =D87*1.3 -> 2887.3 | D87: 2221 | E87: =D87*1.65 -> 3664.65 | G87: =D87*12 -> 26652
A88: 4 | B88: =D88*2 -> 5360 | C88: =D88*1.3 -> 3484 | D88: 2680 | E88: 4421 | G88: =D88*12 -> 32160
A89: 5 | B89: =D89*2 -> 6276 | C89: =D89*1.3 -> 4079.4 | D89: 3138 | E89: 5177 | G89: =D89*12 -> 37656
A90: 6 | B90: =D90*2 -> 7192 | C90: =D90*1.3 -> 4674.8 | D90: 3596 | E90: 5934 | G90: =D90*12 -> 43152
A91: 7 | B91: =D91*2 -> 8110 | C91: =D91*1.3 -> 5271.5 | D91: 4055 | E91: 6690 | G91: =D91*12 -> 48660
A92: 8 | B92: =D92*2 -> 9026 | C92: =D92*1.3 -> 5866.9 | D92: 4513 | E92: =D92*1.65 -> 7446.45 | G92: =D92*12 -> 54156
A93: https://fns-prod.azureedge.us/sites/default/files/resource-files/snap-cola-fy26memo.pdf
A95: SNAP Maximum Benefit
A96: Household Size | B96: Maximum SNAP Allotments
A97: 1 | B97: 298
A98: 2 | B98: 546
A99: 3 | B99: 785
A100: 4 | B100: 994
A101: 5 | B101: 1183
A102: 6 | B102: 1421
A103: 7 | B103: 1571
A104: 8 | B104: 1789
A105: https://fns-prod.azureedge.us/sites/default/files/resource-files/snap-cola-fy26memo.pdf
A108: WIC Eligibility (Monthly) (Valid until 6/30/2026)
A109: 1 | B109: 2413
A110: 2 | B110: 3261
A111: 3 | B111: 4109
A112: 4 | B112: 4957
A113: 5 | B113: 5805
...

Sheet TANF-VIEW
A1: Location | B1: Number in Household | C1: Number of children in household not qualified for TANF AU d/t SSI/SSDI | D1: Standard deduction | E1: 150% FPL | F1: Max income (TANF) | G1: TANF Standard of Assistance | H1: Poverty level for Household | I1: Max reimbusable payment | K1: TANF disregards SSI (not eligible for AU) income of children <18 yrs if attending secondary school,
A2: ='Total income package'!B3 -> Buckingham | B2: ='Total income package'!B32 -> 5 | C2: ='Total income package'!D66 -> 1 | D2: =VLOOKUP($G$6,'Program specific data'!A35:B42,2) -> 209 | E2: =VLOOKUP(G6,'Program specific data'!A6:D13,3) -> 1803.3333 | F2: =IF(A3=2,VLOOKUP(G6,'Program specific data'!A60:C67,2,FALSE),VLOOKUP(G6,'Program specific data'!A60:C67,3,FALSE)) -> 767 | G2: =IF(A3=2,VLOOKUP(G6,'Program specific data'!A48:C55,2,FALSE),VLOOKUP(G6,'Program specific data'!A48:C55,3,FALSE)) -> 385 | H2: =VLOOKUP(G6,'Program specific data'!A6:C13,3,FALSE) -> 1803.3333 | I2: =IF(A3=2,'Program specific data'!B56,'Program specific data'!C56) -> 723 | K2: A recipient of SSI is not eligible for inclusion in the assistance unit. An SSI recipient is an individual who is entitled to SSI benefits regardless of whether the benefit is currently being received.
A3: =VLOOKUP('Total income package'!B3,'Location specific data'!A3:B135,2,FALSE) -> 2 | B3: Number Adults | C3: Number adults qualified for TANF AU as a child caretaker | K3: Social Security is counted
B4: ='Total income package'!B30 -> 3 | C4: =(COUNTIF('Total income package'!E37:E44,"Yes")) -> 2
B5: Number children | C5: Caretakers who are disabled receiving SSI | D5: Number of qualified TANF AU parents/caretaker | E5: Number of qualified TANF AU children | G5: Number TANF eligible HH members (Not receiving SSI children and parent/caretakers)
B6: ='Total income package'!B31 -> 2 | C6: ='Total income package'!D61 -> 1 | D6: =C4-C6 -> 1 | E6: =B6-C2 -> 1 | G6: =D6+E6 -> 2
A7: TANF | M7: VIEW
A8: Annual earned income | B8: Monthly earned income | C8: Social Security income (Unearned income) | D8: Total gross countable income | E8: TANF Initial screening (Using max income) | F8: Earned income -standard deduction | G8: 20% of remainder | H8: Countable earned income (Earned income -standard deduction - 20% of remainder) | I8: Total net countable income (Countable earned income + unearned income) | J8: Is countable income < Standard of Assistance? | K8: TANF Monthly payment-not over max reimbursable (SOA - net countable income) | L8: TANF payment if > $9.99 & TANF selected | M8: VIEW eligible using total gross earned income? (Using 100% poverty level) | N8: VIEW eligible using unearned income? (Using UI< SON) | O8: VIEW deficit = SON - UI (if VIEW eligible-not to exceed max reimbursable) | P8: Total net countable income (from TANF) + deficit | Q8: Is total net countable income + deficit < FPL? | R8: How much exceed FPL? | S8: VIEW Monthly Benefit (Net income + benefit not to exceed poverty level) | T8: VIEW payment if > $9.99 & VIEW eligible & TANF/VIEW selected
A9: 0 | B9: 0 | C9: ='Total income package'!$D$80 -> 0 | D9: =B9+C9 -> 0 | E9: =IF(D9<=$F$2,"Yes","No") -> Yes | F9: =IF(B9-$D$2>0,B9-$D$2,0) -> 0 | G9: =F9*0.2 -> 0 | H9: =F9-G9 -> 0 | I9: =C9+H9 -> 0 | J9: =IF(I9<$G$2,"Yes","No") -> Yes | K9: =IF(E9="Yes",MIN(IF($G$2-I9>0,$G$2-I9,0),$I$2),0) -> 385 | L9: =IF('Total income package'!$A$20=TRUE,MIN(IF(K9>9.99,K9,0),$I$2),0) -> 385 | M9: =IF(B9<$H$2,"Yes","No") -> Yes | N9: =IF(C9<$G$2,"Yes","No") -> Yes | O9: =IF(AND(M9="Yes",N9="Yes"),MIN($G$2,$I$2),0) -> 385 | P9: =I9+O9 -> 385 | Q9: =IF(P9<$H$2,"Yes","No") -> Yes | R9: =IF(P9>$H$2,P9-$H$2,0) -> 0 | S9: =IF(P9>$H$2,O9-R9,O9) -> 385 | T9: =IF(AND('Total income package'!$A$22=TRUE,M9="Yes",S9>9.99),MIN(S9,$I$2),0) -> 0
A10: 500 | B10: =A10/12 -> 41.666667 | C10: ='Total income package'!$D$80 -> 0 | D10: =B10+C10 -> 41.666667 | E10: =IF(D10<=$F$2,"Yes","No") -> Yes | F10: =IF(B10-$D$2>0,B10-$D$2,0) -> 0 | G10: =F10*0.2 -> 0 | H10: =F10-G10 -> 0 | I10: =C10+H10 -> 0 | J10: =IF(I10<$G$2,"Yes","No") -> Yes | K10: =IF(E10="Yes",MIN(IF($G$2-I10>0,$G$2-I10,0),$I$2),0) -> 385 | L10: =IF('Total income package'!$A$20=TRUE,MIN(IF(K10>9.99,K10,0),$I$2),0) -> 385 | M10: =IF(B10<$H$2,"Yes","No") -> Yes | N10: =IF(C10<$G$2,"Yes","No") -> Yes | O10: =IF(AND(M10="Yes",N10="Yes"),MIN($G$2,$I$2),0) -> 385 | P10: =I10+O10 -> 385 | Q10: =IF(P10<$H$2,"Yes","No") -> Yes | R10: =IF(P10>$H$2,P10-$H$2,0) -> 0 | S10: =IF(P10>$H$2,O10-R10,O10) -> 385 | T10: =IF(AND('Total income package'!$A$22=TRUE,M10="Yes",S10>9.99),MIN(S10,$I$2),0) -> 0
A11: 1000 | B11: =A11/12 -> 83.333333 | C11: ='Total income package'!$D$80 -> 0 | D11: =B11+C11 -> 83.333333 | E11: =IF(D11<=$F$2,"Yes","No") -> Yes | F11: =IF(B11-$D$2>0,B11-$D$2,0) -> 0 | G11: =F11*0.2 -> 0 | H11: =F11-G11 -> 0 | I11: =C11+H11 -> 0 | J11: =IF(I11<$G$2,"Yes","No") -> Yes | K11: =IF(E11="Yes",MIN(IF($G$2-I11>0,$G$2-I11,0),$I$2),0) -> 385 | L11: =IF('Total income package'!$A$20=TRUE,MIN(IF(K11>9.99,K11,0),$I$2),0) -> 385 | M11: =IF(B11<$H$2,"Yes","No") -> Yes | N11: =IF(C11<$G$2,"Yes","No") -> Yes | O11: =IF(AND(M11="Yes",N11="Yes"),MIN($G$2,$I$2),0) -> 385 | P11: =I11+O11 -> 385 | Q11: =IF(P11<$H$2,"Yes","No") -> Yes | R11: =IF(P11>$H$2,P11-$H$2,0) -> 0 | S11: =IF(P11>$H$2,O11-R11,O11) -> 385 | T11: =IF(AND('Total income package'!$A$22=TRUE,M11="Yes",S11>9.99),MIN(S11,$I$2),0) -> 0
A12: 1500 | B12: =A12/12 -> 125 | C12: ='Total income package'!$D$80 -> 0 | D12: =B12+C12 -> 125 | E12: =IF(D12<=$F$2,"Yes","No") -> Yes | F12: =IF(B12-$D$2>0,B12-$D$2,0) -> 0 | G12: =F12*0.2 -> 0 | H12: =F12-G12 -> 0 | I12: =C12+H12 -> 0 | J12: =IF(I12<$G$2,"Yes","No") -> Yes | K12: =IF(E12="Yes",MIN(IF($G$2-I12>0,$G$2-I12,0),$I$2),0) -> 385 | L12: =IF('Total income package'!$A$20=TRUE,MIN(IF(K12>9.99,K12,0),$I$2),0) -> 385 | M12: =IF(B12<$H$2,"Yes","No") -> Yes | N12: =IF(C12<$G$2,"Yes","No") -> Yes | O12: =IF(AND(M12="Yes",N12="Yes"),MIN($G$2,$I$2),0) -> 385 | P12: =I12+O12 -> 385 | Q12: =IF(P12<$H$2,"Yes","No") -> Yes | R12: =IF(P12>$H$2,P12-$H$2,0) -> 0 | S12: =IF(P12>$H$2,O12-R12,O12) -> 385 | T12: =IF(AND('Total income package'!$A$22=TRUE,M12="Yes",S12>9.99),MIN(S12,$I$2),0) -> 0
A13: 2000 | B13: =A13/12 -> 166.66667 | C13: ='Total income package'!$D$80 -> 0 | D13: =B13+C13 -> 166.66667 | E13: =IF(D13<=$F$2,"Yes","No") -> Yes | F13: =IF(B13-$D$2>0,B13-$D$2,0) -> 0 | G13: =F13*0.2 -> 0 | H13: =F13-G13 -> 0 | I13: =C13+H13 -> 0 | J13: =IF(I13<$G$2,"Yes","No") -> Yes | K13: =IF(E13="Yes",MIN(IF($G$2-I13>0,$G$2-I13,0),$I$2),0) -> 385 | L13: =IF('Total income package'!$A$20=TRUE,MIN(IF(K13>9.99,K13,0),$I$2),0) -> 385 | M13: =IF(B13<$H$2,"Yes","No") -> Yes | N13: =IF(C13<$G$2,"Yes","No") -> Yes | O13: =IF(AND(M13="Yes",N13="Yes"),MIN($G$2,$I$2),0) -> 385 | P13: =I13+O13 -> 385 | Q13: =IF(P13<$H$2,"Yes","No") -> Yes | R13: =IF(P13>$H$2,P13-$H$2,0) -> 0 | S13: =IF(P13>$H$2,O13-R13,O13) -> 385 | T13: =IF(AND('Total income package'!$A$22=TRUE,M13="Yes",S13>9.99),MIN(S13,$I$2),0) -> 0
A14: 2500 | B14: =A14/12 -> 208.33333 | C14: ='Total income package'!$D$80 -> 0 | D14: =B14+C14 -> 208.33333 | E14: =IF(D14<=$F$2,"Yes","No") -> Yes | F14: =IF(B14-$D$2>0,B14-$D$2,0) -> 0 | G14: =F14*0.2 -> 0 | H14: =F14-G14 -> 0 | I14: =C14+H14 -> 0 | J14: =IF(I14<$G$2,"Yes","No") -> Yes | K14: =IF(E14="Yes",MIN(IF($G$2-I14>0,$G$2-I14,0),$I$2),0) -> 385 | L14: =IF('Total income package'!$A$20=TRUE,MIN(IF(K14>9.99,K14,0),$I$2),0) -> 385 | M14: =IF(B14<$H$2,"Yes","No") -> Yes | N14: =IF(C14<$G$2,"Yes","No") -> Yes | O14: =IF(AND(M14="Yes",N14="Yes"),MIN($G$2,$I$2),0) -> 385 | P14: =I14+O14 -> 385 | Q14: =IF(P14<$H$2,"Yes","No") -> Yes | R14: =IF(P14>$H$2,P14-$H$2,0) -> 0 | S14: =IF(P14>$H$2,O14-R14,O14) -> 385 | T14: =IF(AND('Total income package'!$A$22=TRUE,M14="Yes",S14>9.99),MIN(S14,$I$2),0) -> 0
A15: 3000 | B15: =A15/12 -> 250 | C15: ='Total income package'!$D$80 -> 0 | D15: =B15+C15 -> 250 | E15: =IF(D15<=$F$2,"Yes","No") -> Yes | F15: =IF(B15-$D$2>0,B15-$D$2,0) -> 41 | G15: =F15*0.2 -> 8.2 | H15: =F15-G15 -> 32.8 | I15: =C15+H15 -> 32.8 | J15: =IF(I15<$G$2,"Yes","No") -> Yes | K15: =IF(E15="Yes",MIN(IF($G$2-I15>0,$G$2-I15,0),$I$2),0) -> 352.2 | L15: =IF('Total income package'!$A$20=TRUE,MIN(IF(K15>9.99,K15,0),$I$2),0) -> 352.2 | M15: =IF(B15<$H$2,"Yes","No") -> Yes | N15: =IF(C15<$G$2,"Yes","No") -> Yes | O15: =IF(AND(M15="Yes",N15="Yes"),MIN($G$2,$I$2),0) -> 385 | P15: =I15+O15 -> 417.8 | Q15: =IF(P15<$H$2,"Yes","No") -> Yes | R15: =IF(P15>$H$2,P15-$H$2,0) -> 0 | S15: =IF(P15>$H$2,O15-R15,O15) -> 385 | T15: =IF(AND('Total income package'!$A$22=TRUE,M15="Yes",S15>9.99),MIN(S15,$I$2),0) -> 0
A16: 3500 | B16: =A16/12 -> 291.66667 | C16: ='Total income package'!$D$80 -> 0 | D16: =B16+C16 -> 291.66667 | E16: =IF(D16<=$F$2,"Yes","No") -> Yes | F16: =IF(B16-$D$2>0,B16-$D$2,0) -> 82.666667 | G16: =F16*0.2 -> 16.533333 | H16: =F16-G16 -> 66.133333 | I16: =C16+H16 -> 66.133333 | J16: =IF(I16<$G$2,"Yes","No") -> Yes | K16: =IF(E16="Yes",MIN(IF($G$2-I16>0,$G$2-I16,0),$I$2),0) -> 318.86667 | L16: =IF('Total income package'!$A$20=TRUE,MIN(IF(K16>9.99,K16,0),$I$2),0) -> 318.86667 | M16: =IF(B16<$H$2,"Yes","No") -> Yes | N16: =IF(C16<$G$2,"Yes","No") -> Yes | O16: =IF(AND(M16="Yes",N16="Yes"),MIN($G$2,$I$2),0) -> 385 | P16: =I16+O16 -> 451.13333 | Q16: =IF(P16<$H$2,"Yes","No") -> Yes | R16: =IF(P16>$H$2,P16-$H$2,0) -> 0 | S16: =IF(P16>$H$2,O16-R16,O16) -> 385 | T16: =IF(AND('Total income package'!$A$22=TRUE,M16="Yes",S16>9.99),MIN(S16,$I$2),0) -> 0
A17: 4000 | B17: =A17/12 -> 333.33333 | C17: ='Total income package'!$D$80 -> 0 | D17: =B17+C17 -> 333.33333 | E17: =IF(D17<=$F$2,"Yes","No") -> Yes | F17: =IF(B17-$D$2>0,B17-$D$2,0) -> 124.33333 | G17: =F17*0.2 -> 24.866667 | H17: =F17-G17 -> 99.466667 | I17: =C17+H17 -> 99.466667 | J17: =IF(I17<$G$2,"Yes","No") -> Yes | K17: =IF(E17="Yes",MIN(IF($G$2-I17>0,$G$2-I17,0),$I$2),0) -> 285.53333 | L17: =IF('Total income package'!$A$20=TRUE,MIN(IF(K17>9.99,K17,0),$I$2),0) -> 285.53333 | M17: =IF(B17<$H$2,"Yes","No") -> Yes | N17: =IF(C17<$G$2,"Yes","No") -> Yes | O17: =IF(AND(M17="Yes",N17="Yes"),MIN($G$2,$I$2),0) -> 385 | P17: =I17+O17 -> 484.46667 | Q17: =IF(P17<$H$2,"Yes","No") -> Yes | R17: =IF(P17>$H$2,P17-$H$2,0) -> 0 | S17: =IF(P17>$H$2,O17-R17,O17) -> 385 | T17: =IF(AND('Total income package'!$A$22=TRUE,M17="Yes",S17>9.99),MIN(S17,$I$2),0) -> 0
A18: 4500 | B18: =A18/12 -> 375 | C18: ='Total income package'!$D$80 -> 0 | D18: =B18+C18 -> 375 | E18: =IF(D18<=$F$2,"Yes","No") -> Yes | F18: =IF(B18-$D$2>0,B18-$D$2,0) -> 166 | G18: =F18*0.2 -> 33.2 | H18: =F18-G18 -> 132.8 | I18: =C18+H18 -> 132.8 | J18: =IF(I18<$G$2,"Yes","No") -> Yes | K18: =IF(E18="Yes",MIN(IF($G$2-I18>0,$G$2-I18,0),$I$2),0) -> 252.2 | L18: =IF('Total income package'!$A$20=TRUE,MIN(IF(K18>9.99,K18,0),$I$2),0) -> 252.2 | M18: =IF(B18<$H$2,"Yes","No") -> Yes | N18: =IF(C18<$G$2,"Yes","No") -> Yes | O18: =IF(AND(M18="Yes",N18="Yes"),MIN($G$2,$I$2),0) -> 385 | P18: =I18+O18 -> 517.8 | Q18: =IF(P18<$H$2,"Yes","No") -> Yes | R18: =IF(P18>$H$2,P18-$H$2,0) -> 0 | S18: =IF(P18>$H$2,O18-R18,O18) -> 385 | T18: =IF(AND('Total income package'!$A$22=TRUE,M18="Yes",S18>9.99),MIN(S18,$I$2),0) -> 0
A19: 5000 | B19: =A19/12 -> 416.66667 | C19: ='Total income package'!$D$80 -> 0 | D19: =B19+C19 -> 416.66667 | E19: =IF(D19<=$F$2,"Yes","No") -> Yes | F19: =IF(B19-$D$2>0,B19-$D$2,0) -> 207.66667 | G19: =F19*0.2 -> 41.533333 | H19: =F19-G19 -> 166.13333 | I19: =C19+H19 -> 166.13333 | J19: =IF(I19<$G$2,"Yes","No") -> Yes | K19: =IF(E19="Yes",MIN(IF($G$2-I19>0,$G$2-I19,0),$I$2),0) -> 218.86667 | L19: =IF('Total income package'!$A$20=TRUE,MIN(IF(K19>9.99,K19,0),$I$2),0) -> 218.86667 | M19: =IF(B19<$H$2,"Yes","No") -> Yes | N19: =IF(C19<$G$2,"Yes","No") -> Yes | O19: =IF(AND(M19="Yes",N19="Yes"),MIN($G$2,$I$2),0) -> 385 | P19: =I19+O19 -> 551.13333 | Q19: =IF(P19<$H$2,"Yes","No") -> Yes | R19: =IF(P19>$H$2,P19-$H$2,0) -> 0 | S19: =IF(P19>$H$2,O19-R19,O19) -> 385 | T19: =IF(AND('Total income package'!$A$22=TRUE,M19="Yes",S19>9.99),MIN(S19,$I$2),0) -> 0
A20: 5500 | B20: =A20/12 -> 458.33333 | C20: ='Total income package'!$D$80 -> 0 | D20: =B20+C20 -> 458.33333 | E20: =IF(D20<=$F$2,"Yes","No") -> Yes | F20: =IF(B20-$D$2>0,B20-$D$2,0) -> 249.33333 | G20: =F20*0.2 -> 49.866667 | H20: =F20-G20 -> 199.46667 | I20: =C20+H20 -> 199.46667 | J20: =IF(I20<$G$2,"Yes","No") -> Yes | K20: =IF(E20="Yes",MIN(IF($G$2-I20>0,$G$2-I20,0),$I$2),0) -> 185.53333 | L20: =IF('Total income package'!$A$20=TRUE,MIN(IF(K20>9.99,K20,0),$I$2),0) -> 185.53333 | M20: =IF(B20<$H$2,"Yes","No") -> Yes | N20: =IF(C20<$G$2,"Yes","No") -> Yes | O20: =IF(AND(M20="Yes",N20="Yes"),MIN($G$2,$I$2),0) -> 385 | P20: =I20+O20 -> 584.46667 | Q20: =IF(P20<$H$2,"Yes","No") -> Yes | R20: =IF(P20>$H$2,P20-$H$2,0) -> 0 | S20: =IF(P20>$H$2,O20-R20,O20) -> 385 | T20: =IF(AND('Total income package'!$A$22=TRUE,M20="Yes",S20>9.99),MIN(S20,$I$2),0) -> 0
A21: 6000 | B21: =A21/12 -> 500 | C21: ='Total income package'!$D$80 -> 0 | D21: =B21+C21 -> 500 | E21: =IF(D21<=$F$2,"Yes","No") -> Yes | F21: =IF(B21-$D$2>0,B21-$D$2,0) -> 291 | G21: =F21*0.2 -> 58.2 | H21: =F21-G21 -> 232.8 | I21: =C21+H21 -> 232.8 | J21: =IF(I21<$G$2,"Yes","No") -> Yes | K21: =IF(E21="Yes",MIN(IF($G$2-I21>0,$G$2-I21,0),$I$2),0) -> 152.2 | L21: =IF('Total income package'!$A$20=TRUE,MIN(IF(K21>9.99,K21,0),$I$2),0) -> 152.2 | M21: =IF(B21<$H$2,"Yes","No") -> Yes | N21: =IF(C21<$G$2,"Yes","No") -> Yes | O21: =IF(AND(M21="Yes",N21="Yes"),MIN($G$2,$I$2),0) -> 385 | P21: =I21+O21 -> 617.8 | Q21: =IF(P21<$H$2,"Yes","No") -> Yes | R21: =IF(P21>$H$2,P21-$H$2,0) -> 0 | S21: =IF(P21>$H$2,O21-R21,O21) -> 385 | T21: =IF(AND('Total income package'!$A$22=TRUE,M21="Yes",S21>9.99),MIN(S21,$I$2),0) -> 0
... A25: 8000 | B25: =A25/12 -> 666.66667 | C25: ='Total income package'!$D$80 -> 0 | D25: =B25+C25 -> 666.66667 | E25: =IF(D25<=$F$2,"Yes","No") -> Yes | F25: =IF(B25-$D$2>0,B25-$D$2,0) -> 457.66667 | G25: =F25*0.2 -> 91.533333 | H25: =F25-G25 -> 366.13333 | I25: =C25+H25 -> 366.13333 | J25: =IF(I25<$G$2,"Yes","No") -> Yes | K25: =IF(E25="Yes",MIN(IF($G$2-I25>0,$G$2-I25,0),$I$2),0) -> 18.866667 | L25: =IF('Total income package'!$A$20=TRUE,MIN(IF(K25>9.99,K25,0),$I$2),0) -> 18.866667 | M25: =IF(B25<$H$2,"Yes","No") -> Yes | N25: =IF(C25<$G$2,"Yes","No") -> Yes | O25: =IF(AND(M25="Yes",N25="Yes"),MIN($G$2,$I$2),0) -> 385 | P25: =I25+O25 -> 751.13333 | Q25: =IF(P25<$H$2,"Yes","No") -> Yes | R25: =IF(P25>$H$2,P25-$H$2,0) -> 0 | S25: =IF(P25>$H$2,O25-R25,O25) -> 385 | T25: =IF(AND('Total income package'!$A$22=TRUE,M25="Yes",S25>9.99),MIN(S25,$I$2),0) -> 0
A26: 8500 | B26: =A26/12 -> 708.33333 | C26: ='Total income package'!$D$80 -> 0 | D26: =B26+C26 -> 708.33333 | E26: =IF(D26<=$F$2,"Yes","No") -> Yes | F26: =IF(B26-$D$2>0,B26-$D$2,0) -> 499.33333 | G26: =F26*0.2 -> 99.866667 | H26: =F26-G26 -> 399.46667 | I26: =C26+H26 -> 399.46667 | J26: =IF(I26<$G$2,"Yes","No") -> No | K26: =IF(E26="Yes",MIN(IF($G$2-I26>0,$G$2-I26,0),$I$2),0) -> 0 | L26: =IF('Total income package'!$A$20=TRUE,MIN(IF(K26>9.99,K26,0),$I$2),0) -> 0 | M26: =IF(D26<$H$2,"Yes","No") -> Yes | N26: =IF(C26<$G$2,"Yes","No") -> Yes | O26: =IF(AND(M26="Yes",N26="Yes"),MIN($G$2,$I$2),0) -> 385 | P26: =I26+O26 -> 784.46667 | Q26: =IF(P26<$H$2,"Yes","No") -> Yes | R26: =IF(P26>$H$2,P26-$H$2,0) -> 0 | S26: =IF(P26>$H$2,O26-R26,O26) -> 385 | T26: =IF(AND('Total income package'!$A$22=TRUE,M26="Yes",S26>9.99),MIN(S26,$I$2),0) -> 0
A27: 9000 | B27: =A27/12 -> 750 | C27: ='Total income package'!$D$80 -> 0 | D27: =B27+C27 -> 750 | E27: =IF(D27<=$F$2,"Yes","No") -> Yes | F27: =IF(B27-$D$2>0,B27-$D$2,0) -> 541 | G27: =F27*0.2 -> 108.2 | H27: =F27-G27 -> 432.8 | I27: =C27+H27 -> 432.8 | J27: =IF(I27<$G$2,"Yes","No") -> No | K27: =IF(E27="Yes",MIN(IF($G$2-I27>0,$G$2-I27,0),$I$2),0) -> 0 | L27: =IF('Total income package'!$A$20=TRUE,MIN(IF(K27>9.99,K27,0),$I$2),0) -> 0 | M27: =IF(D27<$H$2,"Yes","No") -> Yes | N27: =IF(C27<$G$2,"Yes","No") -> Yes | O27: =IF(AND(M27="Yes",N27="Yes"),MIN($G$2,$I$2),0) -> 385 | P27: =I27+O27 -> 817.8 | Q27: =IF(P27<$H$2,"Yes","No") -> Yes | R27: =IF(P27>$H$2,P27-$H$2,0) -> 0 | S27: =IF(P27>$H$2,O27-R27,O27) -> 385 | T27: =IF(AND('Total income package'!$A$22=TRUE,M27="Yes",S27>9.99),MIN(S27,$I$2),0) -> 0
A28: 9500 | B28: =A28/12 -> 791.66667 | C28: ='Total income package'!$D$80 -> 0 | D28: =B28+C28 -> 791.66667 | E28: =IF(D28<=$F$2,"Yes","No") -> No | F28: =IF(B28-$D$2>0,B28-$D$2,0) -> 582.66667 | G28: =F28*0.2 -> 116.53333 | H28: =F28-G28 -> 466.13333 | I28: =C28+H28 -> 466.13333 | J28: =IF(I28<$G$2,"Yes","No") -> No | K28: =IF(E28="Yes",MIN(IF($G$2-I28>0,$G$2-I28,0),$I$2),0) -> 0 | L28: =IF('Total income package'!$A$20=TRUE,MIN(IF(K28>9.99,K28,0),$I$2),0) -> 0 | M28: =IF(D28<$H$2,"Yes","No") -> Yes | N28: =IF(C28<$G$2,"Yes","No") -> Yes | O28: =IF(AND(M28="Yes",N28="Yes"),MIN($G$2,$I$2),0) -> 385 | P28: =I28+O28 -> 851.13333 | Q28: =IF(P28<$H$2,"Yes","No") -> Yes | R28: =IF(P28>$H$2,P28-$H$2,0) -> 0 | S28: =IF(P28>$H$2,O28-R28,O28) -> 385 | T28: =IF(AND('Total income package'!$A$22=TRUE,M28="Yes",S28>9.99),MIN(S28,$I$2),0) -> 0
A29: 10000 | B29: =A29/12 -> 833.33333 | C29: ='Total income package'!$D$80 -> 0 | D29: =B29+C29 -> 833.33333 | E29: =IF(D29<=$F$2,"Yes","No") -> No | F29: =IF(B29-$D$2>0,B29-$D$2,0) -> 624.33333 | G29: =F29*0.2 -> 124.86667 | H29: =F29-G29 -> 499.46667 | I29: =C29+H29 -> 499.46667 | J29: =IF(I29<$G$2,"Yes","No") -> No | K29: =IF(E29="Yes",MIN(IF($G$2-I29>0,$G$2-I29,0),$I$2),0) -> 0 | L29: =IF('Total income package'!$A$20=TRUE,MIN(IF(K29>9.99,K29,0),$I$2),0) -> 0 | M29: =IF(D29<$H$2,"Yes","No") -> Yes | N29: =IF(C29<$G$2,"Yes","No") -> Yes | O29: =IF(AND(M29="Yes",N29="Yes"),MIN($G$2,$I$2),0) -> 385 | P29: =I29+O29 -> 884.46667 | Q29: =IF(P29<$H$2,"Yes","No") -> Yes | R29: =IF(P29>$H$2,P29-$H$2,0) -> 0 | S29: =IF(P29>$H$2,O29-R29,O29) -> 385 | T29: =IF(AND('Total income package'!$A$22=TRUE,M29="Yes",S29>9.99),MIN(S29,$I$2),0) -> 0
A30: 10500 | B30: =A30/12 -> 875 | C30: ='Total income package'!$D$80 -> 0 | D30: =B30+C30 -> 875 | E30: =IF(D30<=$F$2,"Yes","No") -> No | F30: =IF(B30-$D$2>0,B30-$D$2,0) -> 666 | G30: =F30*0.2 -> 133.2 | H30: =F30-G30 -> 532.8 | I30: =C30+H30 -> 532.8 | J30: =IF(I30<$G$2,"Yes","No") -> No | K30: =IF(E30="Yes",MIN(IF($G$2-I30>0,$G$2-I30,0),$I$2),0) -> 0 | L30: =IF('Total income package'!$A$20=TRUE,MIN(IF(K30>9.99,K30,0),$I$2),0) -> 0 | M30: =IF(D30<$H$2,"Yes","No") -> Yes | N30: =IF(C30<$G$2,"Yes","No") -> Yes | O30: =IF(AND(M30="Yes",N30="Yes"),MIN($G$2,$I$2),0) -> 385 | P30: =I30+O30 -> 917.8 | Q30: =IF(P30<$H$2,"Yes","No") -> Yes | R30: =IF(P30>$H$2,P30-$H$2,0) -> 0 | S30: =IF(P30>$H$2,O30-R30,O30) -> 385 | T30: =IF(AND('Total income package'!$A$22=TRUE,M30="Yes",S30>9.99),MIN(S30,$I$2),0) -> 0
A31: 11000 | B31: =A31/12 -> 916.66667 | C31: ='Total income package'!$D$80 -> 0 | D31: =B31+C31 -> 916.66667 | E31: =IF(D31<=$F$2,"Yes","No") -> No | F31: =IF(B31-$D$2>0,B31-$D$2,0) -> 707.66667 | G31: =F31*0.2 -> 141.53333 | H31: =F31-G31 -> 566.13333 | I31: =C31+H31 -> 566.13333 | J31: =IF(I31<$G$2,"Yes","No") -> No | K31: =IF(E31="Yes",MIN(IF($G$2-I31>0,$G$2-I31,0),$I$2),0) -> 0 | L31: =IF('Total income package'!$A$20=TRUE,MIN(IF(K31>9.99,K31,0),$I$2),0) -> 0 | M31: =IF(D31<$H$2,"Yes","No") -> Yes | N31: =IF(C31<$G$2,"Yes","No") -> Yes | O31: =IF(AND(M31="Yes",N31="Yes"),MIN($G$2,$I$2),0) -> 385 | P31: =I31+O31 -> 951.13333 | Q31: =IF(P31<$H$2,"Yes","No") -> Yes | R31: =IF(P31>$H$2,P31-$H$2,0) -> 0 | S31: =IF(P31>$H$2,O31-R31,O31) -> 385 | T31: =IF(AND('Total income package'!$A$22=TRUE,M31="Yes",S31>9.99),MIN(S31,$I$2),0) -> 0
A32: 11500 | B32: =A32/12 -> 958.33333 | C32: ='Total income package'!$D$80 -> 0 | D32: =B32+C32 -> 958.33333 | E32: =IF(D32<=$F$2,"Yes","No") -> No | F32: =IF(B32-$D$2>0,B32-$D$2,0) -> 749.33333 | G32: =F32*0.2 -> 149.86667 | H32: =F32-G32 -> 599.46667 | I32: =C32+H32 -> 599.46667 | J32: =IF(I32<$G$2,"Yes","No") -> No | K32: =IF(E32="Yes",MIN(IF($G$2-I32>0,$G$2-I32,0),$I$2),0) -> 0 | L32: =IF('Total income package'!$A$20=TRUE,MIN(IF(K32>9.99,K32,0),$I$2),0) -> 0 | M32: =IF(D32<$H$2,"Yes","No") -> Yes | N32: =IF(C32<$G$2,"Yes","No") -> Yes | O32: =IF(AND(M32="Yes",N32="Yes"),MIN($G$2,$I$2),0) -> 385 | P32: =I32+O32 -> 984.46667 | Q32: =IF(P32<$H$2,"Yes","No") -> Yes | R32: =IF(P32>$H$2,P32-$H$2,0) -> 0 | S32: =IF(P32>$H$2,O32-R32,O32) -> 385 | T32: =IF(AND('Total income package'!$A$22=TRUE,M32="Yes",S32>9.99),MIN(S32,$I$2),0) -> 0
A33: 12000 | B33: =A33/12 -> 1000 | C33: ='Total income package'!$D$80 -> 0 | D33: =B33+C33 -> 1000 | E33: =IF(D33<=$F$2,"Yes","No") -> No | F33: =IF(B33-$D$2>0,B33-$D$2,0) -> 791 | G33: =F33*0.2 -> 158.2 | H33: =F33-G33 -> 632.8 | I33: =C33+H33 -> 632.8 | J33: =IF(I33<$G$2,"Yes","No") -> No | K33: =IF(E33="Yes",MIN(IF($G$2-I33>0,$G$2-I33,0),$I$2),0) -> 0 | L33: =IF('Total income package'!$A$20=TRUE,MIN(IF(K33>9.99,K33,0),$I$2),0) -> 0 | M33: =IF(D33<$H$2,"Yes","No") -> Yes | N33: =IF(C33<$G$2,"Yes","No") -> Yes | O33: =IF(AND(M33="Yes",N33="Yes"),MIN($G$2,$I$2),0) -> 385 | P33: =I33+O33 -> 1017.8 | Q33: =IF(P33<$H$2,"Yes","No") -> Yes | R33: =IF(P33>$H$2,P33-$H$2,0) -> 0 | S33: =IF(P33>$H$2,O33-R33,O33) -> 385 | T33: =IF(AND('Total income package'!$A$22=TRUE,M33="Yes",S33>9.99),MIN(S33,$I$2),0) -> 0
A34: 12500 | B34: =A34/12 -> 1041.6667 | C34: ='Total income package'!$D$80 -> 0 | D34: =B34+C34 -> 1041.6667 | E34: =IF(D34<=$F$2,"Yes","No") -> No | F34: =IF(B34-$D$2>0,B34-$D$2,0) -> 832.66667 | G34: =F34*0.2 -> 166.53333 | H34: =F34-G34 -> 666.13333 | I34: =C34+H34 -> 666.13333 | J34: =IF(I34<$G$2,"Yes","No") -> No | K34: =IF(E34="Yes",MIN(IF($G$2-I34>0,$G$2-I34,0),$I$2),0) -> 0 | L34: =IF('Total income package'!$A$20=TRUE,MIN(IF(K34>9.99,K34,0),$I$2),0) -> 0 | M34: =IF(D34<$H$2,"Yes","No") -> Yes | N34: =IF(C34<$G$2,"Yes","No") -> Yes | O34: =IF(AND(M34="Yes",N34="Yes"),MIN($G$2,$I$2),0) -> 385 | P34: =I34+O34 -> 1051.1333 | Q34: =IF(P34<$H$2,"Yes","No") -> Yes | R34: =IF(P34>$H$2,P34-$H$2,0) -> 0 | S34: =IF(P34>$H$2,O34-R34,O34) -> 385 | T34: =IF(AND('Total income package'!$A$22=TRUE,M34="Yes",S34>9.99),MIN(S34,$I$2),0) -> 0
A35: 13000 | B35: =A35/12 -> 1083.3333 | C35: ='Total income package'!$D$80 -> 0 | D35: =B35+C35 -> 1083.3333 | E35: =IF(D35<=$F$2,"Yes","No") -> No | F35: =IF(B35-$D$2>0,B35-$D$2,0) -> 874.33333 | G35: =F35*0.2 -> 174.86667 | H35: =F35-G35 -> 699.46667 | I35: =C35+H35 -> 699.46667 | J35: =IF(I35<$G$2,"Yes","No") -> No | K35: =IF(E35="Yes",MIN(IF($G$2-I35>0,$G$2-I35,0),$I$2),0) -> 0 | L35: =IF('Total income package'!$A$20=TRUE,MIN(IF(K35>9.99,K35,0),$I$2),0) -> 0 | M35: =IF(D35<$H$2,"Yes","No") -> Yes | N35: =IF(C35<$G$2,"Yes","No") -> Yes | O35: =IF(AND(M35="Yes",N35="Yes"),MIN($G$2,$I$2),0) -> 385 | P35: =I35+O35 -> 1084.4667 | Q35: =IF(P35<$H$2,"Yes","No") -> Yes | R35: =IF(P35>$H$2,P35-$H$2,0) -> 0 | S35: =IF(P35>$H$2,O35-R35,O35) -> 385 | T35: =IF(AND('Total income package'!$A$22=TRUE,M35="Yes",S35>9.99),MIN(S35,$I$2),0) -> 0
A36: 13500 | B36: =A36/12 -> 1125 | C36: ='Total income package'!$D$80 -> 0 | D36: =B36+C36 -> 1125 | E36: =IF(D36<=$F$2,"Yes","No") -> No | F36: =IF(B36-$D$2>0,B36-$D$2,0) -> 916 | G36: =F36*0.2 -> 183.2 | H36: =F36-G36 -> 732.8 | I36: =C36+H36 -> 732.8 | J36: =IF(I36<$G$2,"Yes","No") -> No | K36: =IF(E36="Yes",MIN(IF($G$2-I36>0,$G$2-I36,0),$I$2),0) -> 0 | L36: =IF('Total income package'!$A$20=TRUE,MIN(IF(K36>9.99,K36,0),$I$2),0) -> 0 | M36: =IF(D36<$H$2,"Yes","No") -> Yes | N36: =IF(C36<$G$2,"Yes","No") -> Yes | O36: =IF(AND(M36="Yes",N36="Yes"),MIN($G$2,$I$2),0) -> 385 | P36: =I36+O36 -> 1117.8 | Q36: =IF(P36<$H$2,"Yes","No") -> Yes | R36: =IF(P36>$H$2,P36-$H$2,0) -> 0 | S36: =IF(P36>$H$2,O36-R36,O36) -> 385 | T36: =IF(AND('Total income package'!$A$22=TRUE,M36="Yes",S36>9.99),MIN(S36,$I$2),0) -> 0
A37: 14000 | B37: =A37/12 -> 1166.6667 | C37: ='Total income package'!$D$80 -> 0 | D37: =B37+C37 -> 1166.6667 | E37: =IF(D37<=$F$2,"Yes","No") -> No | F37: =IF(B37-$D$2>0,B37-$D$2,0) -> 957.66667 | G37: =F37*0.2 -> 191.53333 | H37: =F37-G37 -> 766.13333 | I37: =C37+H37 -> 766.13333 | J37: =IF(I37<$G$2,"Yes","No") -> No | K37: =IF(E37="Yes",MIN(IF($G$2-I37>0,$G$2-I37,0),$I$2),0) -> 0 | L37: =IF('Total income package'!$A$20=TRUE,MIN(IF(K37>9.99,K37,0),$I$2),0) -> 0 | M37: =IF(D37<$H$2,"Yes","No") -> Yes | N37: =IF(C37<$G$2,"Yes","No") -> Yes | O37: =IF(AND(M37="Yes",N37="Yes"),MIN($G$2,$I$2),0) -> 385 | P37: =I37+O37 -> 1151.1333 | Q37: =IF(P37<$H$2,"Yes","No") -> Yes | R37: =IF(P37>$H$2,P37-$H$2,0) -> 0 | S37: =IF(P37>$H$2,O37-R37,O37) -> 385 | T37: =IF(AND('Total income package'!$A$22=TRUE,M37="Yes",S37>9.99),MIN(S37,$I$2),0) -> 0
... A209: 100000 | B209: =A209/12 -> 8333.3333 | C209: ='Total income package'!$D$80 -> 0 | D209: =B209+C209 -> 8333.3333 | E209: =IF(D209<=$F$2,"Yes","No") -> No | F209: =IF(B209-$D$2>0,B209-$D$2,0) -> 8124.3333 | G209: =F209*0.2 -> 1624.8667 | H209: =F209-G209 -> 6499.4667 | I209: =C209+H209 -> 6499.4667 | J209: =IF(I209<$G$2,"Yes","No") -> No | K209: =IF(E209="Yes",MIN(IF($G$2-I209>0,$G$2-I209,0),$I$2),0) -> 0 | L209: =IF('Total income package'!$A$20=TRUE,MIN(IF(K209>9.99,K209,0),$I$2),0) -> 0 | M209: =IF(D209<$H$2,"Yes","No") -> No | N209: =IF(C209<$G$2,"Yes","No") -> Yes | O209: =IF(AND(M209="Yes",N209="Yes"),MIN($G$2,$I$2),0) -> 0 | P209: =I209+O209 -> 6499.4667 | Q209: =IF(P209<$H$2,"Yes","No") -> No | R209: =IF(P209>$H$2,P209-$H$2,0) -> 4696.1333 | S209: =IF(P209>$H$2,O209-R209,O209) -> -4696.1333 | T209: =IF(AND('Total income package'!$A$22=TRUE,M209="Yes",S209>9.99),MIN(S209,$I$2),0) -> 0
A211: Exact income-start
B212: =IF($D$6>0,'Total income package'!$B$90,0) -> 1423 | C212: ='Total income package'!$D$80 -> 0 | D212: =B212+C212 -> 1423 | E212: =IF(D212<=$F$2,"Yes","No") -> No | F212: =IF(B212-$D$2>0,B212-$D$2,0) -> 1214 | G212: =F212*0.2 -> 242.8 | H212: =F212-G212 -> 971.2 | I212: =C212+H212 -> 971.2 | J212: =IF(I212<$G$2,"Yes","No") -> No | K212: =IF(E212="Yes",MIN(IF($G$2-I212>0,$G$2-I212,0),$I$2),0) -> 0 | L212: =IF('Total income package'!$A$20=TRUE,MIN(IF(K212>9.99,K212,0),$I$2),0) -> 0 | M212: =IF(D212<$H$2,"Yes","No") -> Yes | N212: =IF(C212<$G$2,"Yes","No") -> Yes | O212: =IF(M212="Yes",MIN($G$2,$I$2),0) -> 385 | P212: =I212+O212 -> 1356.2 | Q212: =IF(P212<$H$2,"Yes","No") -> Yes | R212: =IF(P212>$H$2,P212-$H$2,0) -> 0 | S212: =IF(P212>$H$2,O212-R212,O212) -> 385 | T212: =IF(AND('Total income package'!$A$22=TRUE,M212="Yes",S212>9.99),MIN(S212,$I$2),0) -> 0
A213: Exact income-new
B214: =IF($D$6>0,'Total income package'!$B$90,0) -> 1423 | C214: ='Total income package'!$D$80 -> 0 | D214: =B214+C214 -> 1423 | E214: =IF(D214<=$F$2,"Yes","No") -> No | F214: =IF(B214-$D$2>0,B214-$D$2,0) -> 1214 | G214: =F214*0.2 -> 242.8 | H214: =F214-G214 -> 971.2 | I214: =C214+H214 -> 971.2 | J214: =IF(I214<$G$2,"Yes","No") -> No | K214: =IF(E214="Yes",MIN(IF($G$2-I214>0,$G$2-I214,0),$I$2),0) -> 0 | L214: =IF('Total income package'!$A$20=TRUE,MIN(IF(K214>9.99,K214,0),$I$2),0) -> 0 | M214: =IF(D214<$H$2,"Yes","No") -> Yes | N214: =IF(C214<$G$2,"Yes","No") -> Yes | O214: =IF(M214="Yes",MIN($G$2,$I$2),0) -> 385 | P214: =I214+O214 -> 1356.2 | Q214: =IF(P214<$H$2,"Yes","No") -> Yes | R214: =IF(P214>$H$2,P214-$H$2,0) -> 0 | S214: =IF(P214>$H$2,O214-R214,O214) -> 385 | T214: =IF(AND('Total income package'!$A$22=TRUE,M214="Yes",S214>9.99),MIN(S214,$I$2),0) -> 0

Sheet WIC
A1: Location | B1: Number in Household | C1: Number of eligible children infant | D1: Number of eligible children toddler | E1: Number of eligible children 2yo | F1: Number of eligible children preschool | G1: Number of children <5 | H1: Monthly unearned income: SS, SSI, SSDI | I1: 185% FPL | J1: Adjunctive Financial Eligibility | O1: WIC includes SS, SSI, not include SNAP
A2: ='Total income package'!B3 -> Buckingham | B2: ='Total income package'!B32 -> 5 | C2: =COUNTIF('Total income package'!$B$48:$B$54,"Infant") -> 1 | D2: =COUNTIF('Total income package'!$B$48:$B$54,"Toddler") -> 0 | E2: =COUNTIF('Total income package'!$B$48:$B$54,"Two year old") -> 0 | F2: =COUNTIF('Total income package'!$B$48:$B$54,"Preschool") -> 0 | G2: =SUM(C2:F2) -> 1 | H2: ='Total income package'!H61+'Total income package'!F66+'Total income package'!D80 -> 250 | I2: =VLOOKUP(B2,'Program specific data'!A109:B116,2) -> 5805 | J2: Qualify for TANF? | K2: Qualify for Medicaid? | L2: Qualify for FAMIS? | M2: Qualify for SNAP?
E6: Not included
A7: Annual earned income (gross) | B7: Monthly earned income (gross) | C7: Monthly unearned income: SS, SSI, SSDI | D7: TANF or TANF/VIEW | E7: Monthly income | F7: Monthly WIC benefit
A8: 0 | B8: =A8/12 -> 0 | C8: =$H$2 -> 250 | D8: =MAX('TANF-VIEW'!L9,'TANF-VIEW'!T9) -> 385 | E8: =B8+C8+D8 -> 635 | F8: =IF(AND('Total income package'!$A$24=TRUE,E8<$I$2),'Program specific data'!$B$119*WIC!$G$2,0) -> 36.76
A9: 500 | B9: =A9/12 -> 41.666667 | C9: =$H$2 -> 250 | D9: =MAX('TANF-VIEW'!L10,'TANF-VIEW'!T10) -> 385 | E9: =B9+C9+D9 -> 676.66667 | F9: =IF(AND('Total income package'!$A$24=TRUE,E9<$I$2),'Program specific data'!$B$119*WIC!$G$2,0) -> 36.76
A10: 1000 | B10: =A10/12 -> 83.333333 | C10: =$H$2 -> 250 | D10: =MAX('TANF-VIEW'!L11,'TANF-VIEW'!T11) -> 385 | E10: =B10+C10+D10 -> 718.33333 | F10: =IF(AND('Total income package'!$A$24=TRUE,E10<$I$2),'Program specific data'!$B$119*WIC!$G$2,0) -> 36.76
A11: 1500 | B11: =A11/12 -> 125 | C11: =$H$2 -> 250 | D11: =MAX('TANF-VIEW'!L12,'TANF-VIEW'!T12) -> 385 | E11: =B11+C11+D11 -> 760 | F11: =IF(AND('Total income package'!$A$24=TRUE,E11<$I$2),'Program specific data'!$B$119*WIC!$G$2,0) -> 36.76
A12: 2000 | B12: =A12/12 -> 166.66667 | C12: =$H$2 -> 250 | D12: =MAX('TANF-VIEW'!L13,'TANF-VIEW'!T13) -> 385 | E12: =B12+C12+D12 -> 801.66667 | F12: =IF(AND('Total income package'!$A$24=TRUE,E12<$I$2),'Program specific data'!$B$119*WIC!$G$2,0) -> 36.76
A13: 2500 | B13: =A13/12 -> 208.33333 | C13: =$H$2 -> 250 | D13: =MAX('TANF-VIEW'!L14,'TANF-VIEW'!T14) -> 385 | E13: =B13+C13+D13 -> 843.33333 | F13: =IF(AND('Total income package'!$A$24=TRUE,E13<$I$2),'Program specific data'!$B$119*WIC!$G$2,0) -> 36.76
A14: 3000 | B14: =A14/12 -> 250 | C14: =$H$2 -> 250 | D14: =MAX('TANF-VIEW'!L15,'TANF-VIEW'!T15) -> 352.2 | E14: =B14+C14+D14 -> 852.2 | F14: =IF(AND('Total income package'!$A$24=TRUE,E14<$I$2),'Program specific data'!$B$119*WIC!$G$2,0) -> 36.76
A15: 3500 | B15: =A15/12 -> 291.66667 | C15: =$H$2 -> 250 | D15: =MAX('TANF-VIEW'!L16,'TANF-VIEW'!T16) -> 318.86667 | E15: =B15+C15+D15 -> 860.53333 | F15: =IF(AND('Total income package'!$A$24=TRUE,E15<$I$2),'Program specific data'!$B$119*WIC!$G$2,0) -> 36.76
A16: 4000 | B16: =A16/12 -> 333.33333 | C16: =$H$2 -> 250 | D16: =MAX('TANF-VIEW'!L17,'TANF-VIEW'!T17) -> 285.53333 | E16: =B16+C16+D16 -> 868.86667 | F16: =IF(AND('Total income package'!$A$24=TRUE,E16<$I$2),'Program specific data'!$B$119*WIC!$G$2,0) -> 36.76
A17: 4500 | B17: =A17/12 -> 375 | C17: =$H$2 -> 250 | D17: =MAX('TANF-VIEW'!L18,'TANF-VIEW'!T18) -> 252.2 | E17: =B17+C17+D17 -> 877.2 | F17: =IF(AND('Total income package'!$A$24=TRUE,E17<$I$2),'Program specific data'!$B$119*WIC!$G$2,0) -> 36.76
A18: 5000 | B18: =A18/12 -> 416.66667 | C18: =$H$2 -> 250 | D18: =MAX('TANF-VIEW'!L19,'TANF-VIEW'!T19) -> 218.86667 | E18: =B18+C18+D18 -> 885.53333 | F18: =IF(AND('Total income package'!$A$24=TRUE,E18<$I$2),'Program specific data'!$B$119*WIC!$G$2,0) -> 36.76
A19: 5500 | B19: =A19/12 -> 458.33333 | C19: =$H$2 -> 250 | D19: =MAX('TANF-VIEW'!L20,'TANF-VIEW'!T20) -> 185.53333 | E19: =B19+C19+D19 -> 893.86667 | F19: =IF(AND('Total income package'!$A$24=TRUE,E19<$I$2),'Program specific data'!$B$119*WIC!$G$2,0) -> 36.76
... A208: 100000 | B208: =A208/12 -> 8333.3333 | C208: =$H$2 -> 250 | D208: =MAX('TANF-VIEW'!L209,'TANF-VIEW'!T209) -> 0 | E208: =B208+C208+D208 -> 8583.3333 | F208: =IF(AND('Total income package'!$A$24=TRUE,E208<$I$2),'Program specific data'!$B$119*WIC!$G$2,0) -> 0
A210: Exact income-start
B211: ='Total income package'!$B$90 -> 1423 | C211: =$H$2 -> 250 | D211: =MAX('TANF-VIEW'!L212,'TANF-VIEW'!T212) -> 0 | E211: =B211+C211+D211 -> 1673 | F211: =IF(AND('Total income package'!$A$24=TRUE,E211<$I$2),'Program specific data'!$B$119*WIC!$G$2,0) -> 36.76
A212: Exact income-new
B213: ='Total income package'!$B$91 -> 3000 | C213: =$H$2 -> 250 | D213: =MAX('TANF-VIEW'!L214,'TANF-VIEW'!T214) -> 0 | E213: =B213+C213+D213 -> 3250 | F213: =IF(AND('Total income package'!$A$24=TRUE,E213<$I$2),'Program specific data'!$B$119*WIC!$G$2,0) -> 36.76

Sheet Location specific data
B1: TANF Standards of Assistance 7/2022 https://www.dss.virginia.gov/files/division/bp/tanf/manual/Final_XMTL_74.pdf | C1: Income limits https://www.huduser.gov/portal/datasets/il/il24/Section8-FY24.xlsx (Also Excel-Section8-FY24-income limits) | S1: Housing choice voucher data (Sources: https://www.huduser.gov/portal/datasets/il/il2024/2024summary.odn. https://www.huduser.gov/portal/datasets/fmr/fmrs/FY2024_code/select_Geography.odn https://www.huduser.gov/portal/datasets/fmr/fmrs/FY2025_code/2025state_summary.odn Also have PDFs FY 2025 Fair Market Rent Documentation System — Statewide Summary for Virginia | X1: Source https://www.virginiahousing.com/partners/housing-choice-vouchers/payment-standards | AC1: Market place data (from https://enroll.marketplace.virginia.gov/hix/preeligibility#/) Age ranges from https://www.cms.gov/data-research/statistics-trends-reports/marketplace-products/2024-marketplace-open-enrollment-period-public-use-files 2025 coverage year | AG1: Level I (Center) Max Reimbursement Rate (Full Day) https://www.childcare.virginia.gov/home/showpublisheddocument/51021 | AM1: Eligibility 250% of FPL capped at 85% SMI for Alexandria and Fairfax
A2: Location | B2: TANF Standard of assistance | C2: Very Low-Income Limit 1 person (<50% Median income) | D2: Very Low-Income Limit 2 person (<50% Median income) | E2: Very Low-Income Limit 3 person (<50% Median income) | F2: Very Low-Income Limit 4 person (<50% Median income) | G2: Very Low-Income Limit 5 person (<50% Median income) | H2: Very Low-Income Limit 6 person (<50% Median income) | I2: Very Low-Income Limit 7 person (<50% Median income) | J2: Very Low-Income Limit 8 person (<50% Median income) | K2: Low-Income Limit 1 person (<80% Median income) | L2: Low-Income Limit 2 person (<80% Median income) | M2: Low-Income Limit 3 person (<80% Median income) | N2: Low-Income Limit 4 person (<80% Median income) | O2: Low-Income Limit 5 person (<80% Median income) | P2: Low-Income Limit 6 person (<80% Median income) | Q2: Low-Income Limit 7 person (<80% Median income) | R2: Low-Income Limit 8 person (<80% Median income) | S2: Fair market rate efficiency | T2: Fair market rate 1 bedroom | U2: Fair market rate 2 bedroom | V2: Fair market rate 3 bedroom | W2: Fair market rate 4 bedroom | X2: Efficiency HCV Payment Standard | Y2: 1 BR HCV Payment Standard | Z2: 2 BR HCV Payment Standard | AA2: 3 BR HCV Payment Standard | AB2: 4 BR HCV Payment Standard | AC2: SLCSP-adult only 18-25 | AD2: SLCSP-adult only 26-34 | AE2: SLCSP-1 child | AF2: Zip code used | AG2: Infant | AH2: Toddler | AI2: 2yo | AJ2: Pre-school | AK2: School Age | AL2: Medicaid LIFC Income Limits Group | AM2: Child Care Susidy MSA groupngs
A3: Accomack | B3: 2 | C3: 27550 | D3: 31450 | E3: 35400 | F3: 39300 | G3: 42450 | H3: 45600 | I3: 48750 | J3: 51900 | K3: 44050 | L3: 50350 | M3: 56650 | N3: 62900 | O3: 67950 | P3: 73000 | Q3: 78000 | R3: 83050 | S3: 690 | T3: 776 | U3: 940 | V3: 1257 | W3: 1521 | X3: 842 | Y3: 915 | Z3: 1031 | AA3: 1423 | AB3: 1751 | AC3: 279.7 | AD3: 315.91 | AF3: 23301 | AG3: 71 | AH3: 61 | AI3: 47 | AJ3: 42 | AK3: 30 | AL3: 1 | AM3: 1
A4: Albemarle | B4: 3 | C4: 44050 | D4: 50350 | E4: 56650 | F4: 62900 | G4: 67950 | H4: 73000 | I4: 78000 | J4: 83050 | K4: 70500 | L4: 80550 | M4: 90600 | N4: 100650 | O4: 108750 | P4: 116800 | Q4: 124850 | R4: 132900 | S4: 1404 | T4: 1487 | U4: 1729 | V4: 2155 | W4: 2621 | X4: 1531 | Y4: 1556 | Z4: 1845 | AA4: 2325 | AB4: 2868 | AG4: 70 | AH4: 61 | AI4: 47 | AJ4: 42 | AK4: 38 | AL4: 2 | AM4: 2
A5: Alexandria City | B5: 3 | C5: 57400 | D5: 65600 | E5: 73800 | F5: 81950 | G5: 88550 | H5: 95100 | I5: 101650 | J5: 108200 | K5: 74800 | L5: 85450 | M5: 96150 | N5: 106800 | O5: 115350 | P5: 123900 | Q5: 132450 | R5: 141000 | S5: 2012 | T5: 2056 | U5: 2314 | V5: 2893 | W5: 3413 | X5: 1949 | Y5: 1983 | Z5: 2249 | AA5: 2798 | AB5: 3316 | AG5: 94 | AH5: 81 | AI5: 62 | AJ5: 58 | AK5: 56 | AL5: 3 | AM5: 4
A6: Alleghany | B6: 2 | C6: 27350 | D6: 31250 | E6: 35150 | F6: 39050 | G6: 42200 | H6: 45300 | I6: 48450 | J6: 51550 | K6: 43750 | L6: 50000 | M6: 56250 | N6: 62500 | O6: 67500 | P6: 72500 | Q6: 77500 | R6: 82500 | S6: 736 | T6: 738 | U6: 851 | V6: 1192 | W6: 1281 | X6: 823 | Y6: 828 | Z6: 995 | AA6: 1316 | AB6: 1379 | AG6: 67 | AH6: 58 | AI6: 45 | AJ6: 41 | AK6: 29 | AL6: 1 | AM6: 1
A7: Amelia | B7: 2 | C7: 39750 | D7: 45400 | E7: 51100 | F7: 56750 | G7: 61300 | H7: 65850 | I7: 70400 | J7: 74950 | K7: 63600 | L7: 72650 | M7: 81750 | N7: 90800 | O7: 98100 | P7: 105350 | Q7: 112600 | R7: 119900 | S7: 1488 | T7: 1545 | U7: 1711 | V7: 2166 | W7: 2677 | X7: 1460 | Y7: 1501 | Z7: 1685 | AA7: 2154 | AB7: 2632 | AG7: 64 | AH7: 56 | AI7: 43 | AJ7: 39 | AK7: 28 | AL7: 1 | AM7: 1
A8: Amherst | B8: 2 | C8: 31000 | D8: 35400 | E8: 39850 | F8: 44250 | G8: 47800 | H8: 51350 | I8: 54900 | J8: 58450 | K8: 49600 | L8: 56650 | M8: 63750 | N8: 70800 | O8: 76500 | P8: 82150 | Q8: 87800 | R8: 93500 | S8: 1043 | T8: 1062 | U8: 1200 | V8: 1647 | W8: 1785 | X8: 1042 | Y8: 1062 | Z8: 1202 | AA8: 1643 | AB8: 1789 | AG8: 64 | AH8: 56 | AI8: 43 | AJ8: 39 | AK8: 28 | AL8: 1 | AM8: 1
A9: Appomattox | B9: 2 | C9: 31000 | D9: 35400 | E9: 39850 | F9: 44250 | G9: 47800 | H9: 51350 | I9: 54900 | J9: 58450 | K9: 49600 | L9: 56650 | M9: 63750 | N9: 70800 | O9: 76500 | P9: 82150 | Q9: 87800 | R9: 93500 | S9: 1043 | T9: 1062 | U9: 1200 | V9: 1647 | W9: 1785 | X9: 1042 | Y9: 1062 | Z9: 1202 | AA9: 1643 | AB9: 1789 | AG9: 64 | AH9: 56 | AI9: 43 | AJ9: 39 | AK9: 28 | AL9: 1 | AM9: 1
A10: Arlington County | B10: 3 | C10: 57400 | D10: 65600 | E10: 73800 | F10: 81950 | G10: 88550 | H10: 95100 | I10: 101650 | J10: 108200 | K10: 74800 | L10: 85450 | M10: 96150 | N10: 106800 | O10: 115350 | P10: 123900 | Q10: 132450 | R10: 141000 | S10: 2012 | T10: 2056 | U10: 2314 | V10: 2893 | W10: 3413 | X10: 1949 | Y10: 1983 | Z10: 2249 | AA10: 2798 | AB10: 3316 | AG10: 94 | AH10: 81 | AI10: 70 | AJ10: 70 | AK10: 59 | AL10: 3 | AM10: 3
A11: Augusta | B11: 3 | C11: 33050 | D11: 37800 | E11: 42500 | F11: 47200 | G11: 51000 | H11: 54800 | I11: 58550 | J11: 62350 | K11: 52850 | L11: 60400 | M11: 67950 | N11: 75500 | O11: 81550 | P11: 87600 | Q11: 93650 | R11: 99700 | S11: 1107 | T11: 1114 | U11: 1282 | V11: 1796 | W11: 2092 | X11: 1079 | Y11: 1085 | Z11: 1263 | AA11: 1777 | AB11: 2114 | AG11: 70 | AH11: 61 | AI11: 47 | AJ11: 42 | AK11: 30 | AL11: 2 | AM11: 1
A12: Bath | B12: 2 | C12: 30450 | D12: 34800 | E12: 39150 | F12: 43500 | G12: 47000 | H12: 50500 | I12: 53950 | J12: 57450 | K12: 48750 | L12: 55700 | M12: 62650 | N12: 69600 | O12: 75200 | P12: 80750 | Q12: 86350 | R12: 91900 | S12: 698 | T12: 702 | U12: 867 | V12: 1128 | W12: 1355 | X12: 804 | Y12: 808 | Z12: 1003 | AA12: 1314 | AB12: 1538 | AG12: 67 | AH12: 58 | AI12: 45 | AJ12: 41 | AK12: 29 | AL12: 1 | AM12: 1
A13: Bedford | B13: 2 | C13: 31000 | D13: 35400 | E13: 39850 | F13: 44250 | G13: 47800 | H13: 51350 | I13: 54900 | J13: 58450 | K13: 49600 | L13: 56650 | M13: 63750 | N13: 70800 | O13: 76500 | P13: 82150 | Q13: 87800 | R13: 93500 | S13: 1043 | T13: 1062 | U13: 1200 | V13: 1647 | W13: 1785 | X13: 1042 | Y13: 1062 | Z13: 1202 | AA13: 1643 | AB13: 1789 | AG13: 64 | AH13: 56 | AI13: 43 | AJ13: 39 | AK13: 28 | AL13: 1 | AM13: 1
A14: Bland | B14: 2 | C14: 27350 | D14: 31250 | E14: 35150 | F14: 39050 | G14: 42200 | H14: 45300 | I14: 48450 | J14: 51550 | K14: 43750 | L14: 50000 | M14: 56250 | N14: 62500 | O14: 67500 | P14: 72500 | Q14: 77500 | R14: 82500 | S14: 685 | T14: 689 | U14: 851 | V14: 1192 | W14: 1330 | X14: 797 | Y14: 803 | Z14: 995 | AA14: 1402 | AB14: 1526 | AG14: 63 | AH14: 55 | AI14: 42 | AJ14: 38 | AK14: 27 | AL14: 1 | AM14: 1
A15: Botetourt | B15: 2 | C15: 31750 | D15: 36250 | E15: 40800 | F15: 45300 | G15: 48950 | H15: 52550 | I15: 56200 | J15: 59800 | K15: 50750 | L15: 58000 | M15: 65250 | N15: 72500 | O15: 78300 | P15: 84100 | Q15: 89900 | R15: 95700 | S15: 892 | T15: 948 | U15: 1141 | V15: 1597 | W15: 1885 | X15: 892 | Y15: 983 | Z15: 1196 | AA15: 1664 | AB15: 1936 | AG15: 67 | AH15: 58 | AI15: 45 | AJ15: 41 | AK15: 29 | AL15: 1 | AM15: 1
... A26: Charlottesville City | B26: 3 | C26: 44050 | D26: 50350 | E26: 56650 | F26: 62900 | G26: 67950 | H26: 73000 | I26: 78000 | J26: 83050 | K26: 70500 | L26: 80550 | M26: 90600 | N26: 100650 | O26: 108750 | P26: 116800 | Q26: 124850 | R26: 132900 | S26: 1404 | T26: 1487 | U26: 1729 | V26: 2155 | W26: 2621 | X26: 1531 | Y26: 1556 | Z26: 1845 | AA26: 2325 | AB26: 2868 | AG26: 70 | AH26: 61 | AI26: 47 | AJ26: 42 | AK26: 38 | AL26: 3 | AM26: 2
A27: Chesapeake | B27: 2 | C27: 37300 | D27: 42600 | E27: 47950 | F27: 53250 | G27: 57550 | H27: 61800 | I27: 66050 | J27: 70300 | K27: 59650 | L27: 68200 | M27: 76700 | N27: 85200 | O27: 92050 | P27: 98850 | Q27: 105650 | R27: 112500 | S27: 1475 | T27: 1483 | U27: 1696 | V27: 2361 | W27: 2809 | X27: 1406 | Y27: 1415 | Z27: 1642 | AA27: 2286 | AB27: 2785 | AC27: 346 | AE27: 821 | AF27: 23220 | AG27: 71 | AH27: 61 | AI27: 47 | AJ27: 42 | AK27: 30 | AL27: 2 | AM27: 2
A28: Chesterfield | B28: 2 | C28: 39750 | D28: 45400 | E28: 51100 | F28: 56750 | G28: 61300 | H28: 65850 | I28: 70400 | J28: 74950 | K28: 63600 | L28: 72650 | M28: 81750 | N28: 90800 | O28: 98100 | P28: 105350 | Q28: 112600 | R28: 119900 | S28: 1488 | T28: 1545 | U28: 1711 | V28: 2166 | W28: 2677 | X28: 1460 | Y28: 1501 | Z28: 1685 | AA28: 2154 | AB28: 2632 | AG28: 69 | AH28: 60 | AI28: 47 | AJ28: 41 | AK28: 35 | AL28: 2 | AM28: 2
A29: Clarke | B29: 2 | C29: 57400 | D29: 65600 | E29: 73800 | F29: 81950 | G29: 88550 | H29: 95100 | I29: 101650 | J29: 108200 | K29: 74800 | L29: 85450 | M29: 96150 | N29: 106800 | O29: 115350 | P29: 123900 | Q29: 132450 | R29: 141000 | S29: 2012 | T29: 2056 | U29: 2314 | V29: 2893 | W29: 3413 | X29: 1949 | Y29: 1983 | Z29: 2249 | AA29: 2798 | AB29: 3316 | AG29: 70 | AH29: 61 | AI29: 47 | AJ29: 42 | AK29: 30 | AL29: 1 | AM29: 3
A30: Colonial Heights | B30: 3 | C30: 39750 | D30: 45400 | E30: 51100 | F30: 56750 | G30: 61300 | H30: 65850 | I30: 70400 | J30: 74950 | K30: 63600 | L30: 72650 | M30: 81750 | N30: 90800 | O30: 98100 | P30: 105350 | Q30: 112600 | R30: 119900 | S30: 1488 | T30: 1545 | U30: 1711 | V30: 2166 | W30: 2677 | X30: 1460 | Y30: 1501 | Z30: 1685 | AA30: 2154 | AB30: 2632 | AG30: 69 | AH30: 60 | AI30: 47 | AJ30: 41 | AK30: 35 | AL30: 3 | AM30: 2
A31: Covington | B31: 2 | C31: 27350 | D31: 31250 | E31: 35150 | F31: 39050 | G31: 42200 | H31: 45300 | I31: 48450 | J31: 51550 | K31: 43750 | L31: 50000 | M31: 56250 | N31: 62500 | O31: 67500 | P31: 72500 | Q31: 77500 | R31: 82500 | S31: 736 | T31: 738 | U31: 851 | V31: 1192 | W31: 1281 | X31: 823 | Y31: 828 | Z31: 995 | AA31: 1316 | AB31: 1379 | AG31: 67 | AH31: 58 | AI31: 45 | AJ31: 41 | AK31: 29 | AL31: 2 | AM31: 1
A32: Craig | B32: 2 | C32: 31750 | D32: 36250 | E32: 40800 | F32: 45300 | G32: 48950 | H32: 52550 | I32: 56200 | J32: 59800 | K32: 50750 | L32: 58000 | M32: 65250 | N32: 72500 | O32: 78300 | P32: 84100 | Q32: 89900 | R32: 95700 | S32: 892 | T32: 948 | U32: 1141 | V32: 1597 | W32: 1885 | X32: 892 | Y32: 983 | Z32: 1196 | AA32: 1664 | AB32: 1936 | AG32: 67 | AH32: 58 | AI32: 45 | AJ32: 41 | AK32: 29 | AL32: 1 | AM32: 1
A33: Culpeper | B33: 2 | C33: 40300 | D33: 46050 | E33: 51800 | F33: 57550 | G33: 62200 | H33: 66800 | I33: 71400 | J33: 76000 | K33: 64500 | L33: 73700 | M33: 82900 | N33: 92100 | O33: 99500 | P33: 106850 | Q33: 114250 | R33: 121600 | S33: 1148 | T33: 1148 | U33: 1421 | V33: 1882 | W33: 2036 | X33: 1048 | Y33: 1054 | Z33: 1376 | AA33: 1769 | AB33: 2077 | AG33: 83 | AH33: 72 | AI33: 55 | AJ33: 50 | AK33: 35 | AL33: 1 | AM33: 3
A34: Cumberland | B34: 2 | C34: 27350 | D34: 31250 | E34: 35150 | F34: 39050 | G34: 42200 | H34: 45300 | I34: 48450 | J34: 51550 | K34: 43750 | L34: 50000 | M34: 56250 | N34: 62500 | O34: 67500 | P34: 72500 | Q34: 77500 | R34: 82500 | S34: 735 | T34: 739 | U34: 913 | V34: 1100 | W34: 1540 | X34: 888 | Y34: 894 | Z34: 1108 | AA34: 1340 | AB34: 1882 | AG34: 64 | AH34: 56 | AI34: 43 | AJ34: 39 | AK34: 28 | AL34: 1 | AM34: 1
A35: Danville city | B35: 2 | C35: 27350 | D35: 31250 | E35: 35150 | F35: 39050 | G35: 42200 | H35: 45300 | I35: 48450 | J35: 51550 | K35: 43750 | L35: 50000 | M35: 56250 | N35: 62500 | O35: 67500 | P35: 72500 | Q35: 77500 | R35: 82500 | S35: 584 | T35: 687 | U35: 851 | V35: 1165 | W35: 1311 | X35: 674 | Y35: 790 | Z35: 995 | AA35: 1350 | AB35: 1488 | AG35: 64 | AH35: 56 | AI35: 43 | AJ35: 39 | AK35: 28 | AL35: 1 | AM35: 1
A36: Dickenson County | B36: 2 | C36: 27350 | D36: 31250 | E36: 35150 | F36: 39050 | G36: 42200 | H36: 45300 | I36: 48450 | J36: 51550 | K36: 43750 | L36: 50000 | M36: 56250 | N36: 62500 | O36: 67500 | P36: 72500 | Q36: 77500 | R36: 82500 | S36: 685 | T36: 689 | U36: 851 | V36: 1025 | W36: 1330 | X36: 797 | Y36: 803 | Z36: 995 | AA36: 1203 | AB36: 1526 | AG36: 63 | AH36: 55 | AI36: 42 | AJ36: 38 | AK36: 27 | AL36: 1 | AM36: 1
A37: Dinwiddie | B37: 2 | C37: 39750 | D37: 45400 | E37: 51100 | F37: 56750 | G37: 61300 | H37: 65850 | I37: 70400 | J37: 74950 | K37: 63600 | L37: 72650 | M37: 81750 | N37: 90800 | O37: 98100 | P37: 105350 | Q37: 112600 | R37: 119900 | S37: 1488 | T37: 1545 | U37: 1711 | V37: 2166 | W37: 2677 | X37: 1460 | Y37: 1501 | Z37: 1685 | AA37: 2154 | AB37: 2632 | AG37: 69 | AH37: 60 | AI37: 47 | AJ37: 41 | AK37: 29 | AL37: 1 | AM37: 2
A38: Emporia | B38: 2 | C38: 27350 | D38: 31250 | E38: 35150 | F38: 39050 | G38: 42200 | H38: 45300 | I38: 48450 | J38: 51550 | K38: 43750 | L38: 50000 | M38: 56250 | N38: 62500 | O38: 67500 | P38: 72500 | Q38: 77500 | R38: 82500 | S38: 707 | T38: 711 | U38: 933 | V38: 1275 | W38: 1532 | X38: 805 | Y38: 810 | Z38: 1064 | AA38: 1437 | AB38: 1581 | AG38: 69 | AH38: 60 | AI38: 47 | AJ38: 41 | AK38: 29 | AL38: 1 | AM38: 1
A39: Essex | B39: 2 | C39: 27650 | D39: 31600 | E39: 35550 | F39: 39450 | G39: 42650 | H39: 45800 | I39: 48950 | J39: 52100 | K39: 44200 | L39: 50500 | M39: 56800 | N39: 63100 | O39: 68150 | P39: 73200 | Q39: 78250 | R39: 83300 | S39: 810 | T39: 815 | U39: 1006 | V39: 1246 | W39: 1438 | X39: 917 | Y39: 922 | Z39: 1145 | AA39: 1453 | AB39: 1756 | AG39: 68 | AH39: 59 | AI39: 45 | AJ39: 41 | AK39: 29 | AL39: 1 | AM39: 1
... A41: Fairfax county | B41: 3 | C41: 57400 | D41: 65600 | E41: 73800 | F41: 81950 | G41: 88550 | H41: 95100 | I41: 101650 | J41: 108200 | K41: 74800 | L41: 85450 | M41: 96150 | N41: 106800 | O41: 115350 | P41: 123900 | Q41: 132450 | R41: 141000 | S41: 2012 | T41: 2056 | U41: 2314 | V41: 2893 | W41: 3413 | X41: 1949 | Y41: 1983 | Z41: 2249 | AA41: 2798 | AB41: 3316 | AG41: 94 | AH41: 81 | AI41: 62 | AJ41: 59 | AK41: 52 | AL41: 3 | AM41: 4
A42: Falls Church City | B42: 3 | C42: 57400 | D42: 65600 | E42: 73800 | F42: 81950 | G42: 88550 | H42: 95100 | I42: 101650 | J42: 108200 | K42: 74800 | L42: 85450 | M42: 96150 | N42: 106800 | O42: 115350 | P42: 123900 | Q42: 132450 | R42: 141000 | S42: 2012 | T42: 2056 | U42: 2314 | V42: 2893 | W42: 3413 | X42: 1949 | Y42: 1983 | Z42: 2249 | AA42: 2798 | AB42: 3316 | AG42: 94 | AH42: 81 | AI42: 62 | AJ42: 59 | AK42: 52 | AL42: 3 | AM42: 4 | AN42: In Fairfax MSA
A43: Fauquier | B43: 3 | C43: 57400 | D43: 65600 | E43: 73800 | F43: 81950 | G43: 88550 | H43: 95100 | I43: 101650 | J43: 108200 | K43: 74800 | L43: 85450 | M43: 96150 | N43: 106800 | O43: 115350 | P43: 123900 | Q43: 132450 | R43: 141000 | S43: 2012 | T43: 2056 | U43: 2314 | V43: 2893 | W43: 3413 | X43: 1949 | Y43: 1983 | Z43: 2249 | AA43: 2798 | AB43: 3316 | AG43: 83 | AH43: 72 | AI43: 55 | AJ43: 50 | AK43: 35 | AL43: 1 | AM43: 3
A44: Floyd | B44: 2 | C44: 30900 | D44: 35250 | E44: 39700 | F44: 44100 | G44: 47650 | H44: 51200 | I44: 54700 | J44: 58250 | K44: 49400 | L44: 56450 | M44: 63500 | N44: 70550 | O44: 76200 | P44: 81850 | Q44: 87500 | R44: 93150 | S44: 691 | T44: 695 | U44: 912 | V44: 1149 | W44: 1209 | X44: 797 | Y44: 803 | Z44: 995 | AA44: 1333 | AB44: 1338 | AG44: 63 | AH44: 55 | AI44: 42 | AJ44: 38 | AK44: 27 | AL44: 1 | AM44: 1
